Workbook

Sheet 最後總成績算分
A1: 名字 | B1: 學號 | C1: 分組 | D1: Cybersecurity news presentation | E1: Malware analysis | F1: Machine learning in malware analysis | G1: Project Proposal | H1: Project Proposal Form | I1: Red team practice | J1: Red team practice Form | K1: Paper presentation | L1: Week 12 - Paper Form | M1: Week 13 - Paper Form | N1: Week 14 - Paper Form | O1: Final Project | P1: Final Project Form 1 | Q1: Final Project Form 2 | R1: Cybersec 2026 心得 | S1: LLM 回答 | T1: 缺席 | U1: 總分 | V1: 總分(無條件進位) | W1: 等第
D2: 0.1 | E2: 0.1 | F2: 0.1 | G2: 0.04 | H2: 0.01 | I2: 0.08 | J2: 0.02 | K2: 0.15 | L2: 0.05 | M2: 0.05 | N2: 0.05 | O2: 0.2 | P2: 0.025 | Q2: 0.025 | R2: 一次0.25 | S2: 一次0.25
A3: 黃文良 | B3: B11107152 | C3: ANTSLAB | D3: 86 | E3: 94 | F3: 100 | G3: 95 | H3: 86 | I3: 93 | J3: {=_xlfn.XLOOKUP($A3, 'Camping Simulation'!$B:$B, 'Camping Simulation'!$K:$K, "X")} -> 87 | K3: 94 | L3: 89 | M3: 89 | N3: 89 | O3: 95 | P3: 86 | Q3: 0 | R3: 1 | T3: 1 | U3: =D3*$D$2+E3*$E$2+F3*$F$2+G3*$G$2+H3*$H$2+I3*$I$2+J3*$J$2+K3*$K$2+L3*$L$2+M3*$M$2+N3*$N$2+O3*$O$2+P3*$P$2+Q3*$Q$2-5*T3+R3*0.25+S3*0.25 -> 85.69 | V3: =ROUNDUP(U3,0) -> 86 | W3: =IFS(V3>=90, "A+", V3>=85, "A", V3>=80, "A-", V3>=77, "B+", V3>=73, "B", V3>=70, "B-", TRUE, "") -> A
A4: 胡承學 | B4: B11107153 | C4: ANTSLAB | D4: 86 | E4: 94 | F4: 0 | G4: 95 | H4: 0 | I4: 93 | J4: {=_xlfn.XLOOKUP($A4, 'Camping Simulation'!$B:$B, 'Camping Simulation'!$K:$K, "X")} -> 90 | K4: 94 | L4: 90 | M4: 90 | N4: 90 | O4: 95 | P4: 88 | Q4: 89 | U4: =D4*$D$2+E4*$E$2+F4*$F$2+G4*$G$2+H4*$H$2+I4*$I$2+J4*$J$2+K4*$K$2+L4*$L$2+M4*$M$2+N4*$N$2+O4*$O$2+P4*$P$2+Q4*$Q$2-5*T4+R4*0.25+S4*0.25 -> 82.065 | V4: =ROUNDUP(U4,0) -> 83 | W4: =IFS(V4>=90, "A+", V4>=85, "A", V4>=80, "A-", V4>=77, "B+", V4>=73, "B", V4>=70, "B-", TRUE, "") -> A-
A5: 吳永保 | B5: M11407005 | C5: ANTSLAB | D5: 86 | E5: 94 | F5: 100 | G5: 95 | H5: 88 | I5: 93 | J5: {=_xlfn.XLOOKUP($A5, 'Camping Simulation'!$B:$B, 'Camping Simulation'!$K:$K, "X")} -> 89 | K5: 94 | L5: 92 | M5: 90 | N5: 92 | O5: 95 | P5: 89 | Q5: 92 | U5: =D5*$D$2+E5*$E$2+F5*$F$2+G5*$G$2+H5*$H$2+I5*$I$2+J5*$J$2+K5*$K$2+L5*$L$2+M5*$M$2+N5*$N$2+O5*$O$2+P5*$P$2+Q5*$Q$2-5*T5+R5*0.25+S5*0.25 -> 93.225 | V5: =ROUNDUP(U5,0) -> 94 | W5: =IFS(V5>=90, "A+", V5>=85, "A", V5>=80, "A-", V5>=77, "B+", V5>=73, "B", V5>=70, "B-", TRUE, "") -> A+
A6: 楊晴安 | B6: M11407507 | C6: ANTSLAB | D6: 86 | E6: 94 | F6: 100 | G6: 95 | H6: 89 | I6: 93 | J6: {=_xlfn.XLOOKUP($A6, 'Camping Simulation'!$B:$B, 'Camping Simulation'!$K:$K, "X")} -> 92 | K6: 94 | L6: 93 | M6: 91 | N6: 92 | O6: 95 | P6: 90 | Q6: 93 | R6: 1 | U6: =D6*$D$2+E6*$E$2+F6*$F$2+G6*$G$2+H6*$H$2+I6*$I$2+J6*$J$2+K6*$K$2+L6*$L$2+M6*$M$2+N6*$N$2+O6*$O$2+P6*$P$2+Q6*$Q$2-5*T6+R6*0.25+S6*0.25 -> 93.695 | V6: =ROUNDUP(U6,0) -> 94 | W6: =IFS(V6>=90, "A+", V6>=85, "A", V6>=80, "A-", V6>=77, "B+", V6>=73, "B", V6>=70, "B-", TRUE, "") -> A+
A7: 洪粲鈞 | B7: M11407519 | C7: ANTSLAB | D7: 86 | E7: 94 | F7: 100 | G7: 95 | H7: 93 | I7: 93 | J7: {=_xlfn.XLOOKUP($A7, 'Camping Simulation'!$B:$B, 'Camping Simulation'!$K:$K, "X")} -> 89 | K7: 94 | L7: 90 | M7: 92 | N7: 91 | O7: 95 | P7: 90 | Q7: 90 | R7: 1 | U7: =D7*$D$2+E7*$E$2+F7*$F$2+G7*$G$2+H7*$H$2+I7*$I$2+J7*$J$2+K7*$K$2+L7*$L$2+M7*$M$2+N7*$N$2+O7*$O$2+P7*$P$2+Q7*$Q$2-5*T7+R7*0.25+S7*0.25 -> 93.45 | V7: =ROUNDUP(U7,0) -> 94 | W7: =IFS(V7>=90, "A+", V7>=85, "A", V7>=80, "A-", V7>=77, "B+", V7>=73, "B", V7>=70, "B-", TRUE, "") -> A+
A8: 張惟凱 | B8: M11407522 | C8: ANTSLAB | D8: 86 | E8: 94 | F8: 100 | G8: 95 | H8: 92 | I8: 93 | J8: {=_xlfn.XLOOKUP($A8, 'Camping Simulation'!$B:$B, 'Camping Simulation'!$K:$K, "X")} -> 92 | K8: 94 | L8: 92 | M8: 91 | N8: 93 | O8: 95 | P8: 94 | Q8: 93 | R8: 1 | U8: =D8*$D$2+E8*$E$2+F8*$F$2+G8*$G$2+H8*$H$2+I8*$I$2+J8*$J$2+K8*$K$2+L8*$L$2+M8*$M$2+N8*$N$2+O8*$O$2+P8*$P$2+Q8*$Q$2-5*T8+R8*0.25+S8*0.25 -> 93.825 | V8: =ROUNDUP(U8,0) -> 94 | W8: =IFS(V8>=90, "A+", V8>=85, "A", V8>=80, "A-", V8>=77, "B+", V8>=73, "B", V8>=70, "B-", TRUE, "") -> A+
A9: SU YADANA WIN | B9: d11415809 | C9: BENI | D9: 90 | E9: 84 | F9: 100 | G9: 95 | H9: 88 | I9: 91 | J9: 0 | K9: 85 | L9: 94 | M9: 91 | N9: 90 | O9: 95 | P9: 95 | Q9: 95 | R9: 1 | U9: =D9*$D$2+E9*$E$2+F9*$F$2+G9*$G$2+H9*$H$2+I9*$I$2+J9*$J$2+K9*$K$2+L9*$L$2+M9*$M$2+N9*$N$2+O9*$O$2+P9*$P$2+Q9*$Q$2-5*T9+R9*0.25+S9*0.25 -> 89.86 | V9: =ROUNDUP(U9,0) -> 90 | W9: =IFS(V9>=90, "A+", V9>=85, "A", V9>=80, "A-", V9>=77, "B+", V9>=73, "B", V9>=70, "B-", TRUE, "") -> A+
A10: Jules GIRARD | B10: e11415022 | C10: BENI | D10: 90 | E10: 84 | F10: 0 | G10: 95 | H10: 90 | I10: 91 | J10: {=_xlfn.XLOOKUP($A10, 'Camping Simulation'!$B:$B, 'Camping Simulation'!$K:$K, "X")} -> 89 | K10: 85 | L10: 91 | M10: 90 | N10: 91 | O10: 95 | P10: 92 | Q10: 93 | U10: =D10*$D$2+E10*$E$2+F10*$F$2+G10*$G$2+H10*$H$2+I10*$I$2+J10*$J$2+K10*$K$2+L10*$L$2+M10*$M$2+N10*$N$2+O10*$O$2+P10*$P$2+Q10*$Q$2-5*T10+R10*0.25+S10*0.25 -> 81.135 | V10: =ROUNDUP(U10,0) -> 82 | W10: =IFS(V10>=90, "A+", V10>=85, "A", V10>=80, "A-", V10>=77, "B+", V10>=73, "B", V10>=70, "B-", TRUE, "") -> A-
A11: Benjamin GILLARD | B11: e11415026 | C11: BENI | D11: 90 | E11: 84 | F11: 100 | G11: 95 | H11: 88 | I11: 91 | J11: {=_xlfn.XLOOKUP($A11, 'Camping Simulation'!$B:$B, 'Camping Simulation'!$K:$K, "X")} -> 89 | K11: 85 | L11: 88 | M11: 90 | N11: 88 | O11: 95 | P11: 90 | Q11: 88 | U11: =D11*$D$2+E11*$E$2+F11*$F$2+G11*$G$2+H11*$H$2+I11*$I$2+J11*$J$2+K11*$K$2+L11*$L$2+M11*$M$2+N11*$N$2+O11*$O$2+P11*$P$2+Q11*$Q$2-5*T11+R11*0.25+S11*0.25 -> 90.64 | V11: =ROUNDUP(U11,0) -> 91 | W11: =IFS(V11>=90, "A+", V11>=85, "A", V11>=80, "A-", V11>=77, "B+", V11>=73, "B", V11>=70, "B-", TRUE, "") -> A+
A12: Ugo LINDEPERG | B12: e11415027 | C12: BENI | D12: 90 | E12: 84 | F12: 0 | G12: 95 | H12: 90 | I12: 91 | J12: 88 | K12: 85 | L12: 91 | M12: 88 | N12: 89 | O12: 95 | P12: 92 | Q12: 93 | U12: =D12*$D$2+E12*$E$2+F12*$F$2+G12*$G$2+H12*$H$2+I12*$I$2+J12*$J$2+K12*$K$2+L12*$L$2+M12*$M$2+N12*$N$2+O12*$O$2+P12*$P$2+Q12*$Q$2-5*T12+R12*0.25+S12*0.25 -> 80.915 | V12: =ROUNDUP(U12,0) -> 81 | W12: =IFS(V12>=90, "A+", V12>=85, "A", V12>=80, "A-", V12>=77, "B+", V12>=73, "B", V12>=70, "B-", TRUE, "") -> A-
A13: Oriiana Nedzelska | B13: f11415026 | C13: BENI | D13: 90 | E13: 84 | F13: 100 | G13: 95 | H13: 90 | I13: 91 | J13: {=_xlfn.XLOOKUP($A13, 'Camping Simulation'!$B:$B, 'Camping Simulation'!$K:$K, "X")} -> 92 | K13: 85 | L13: 92 | M13: 91 | N13: 93 | O13: 95 | P13: 93 | Q13: 92 | R13: 1 | S13: 1 | U13: =D13*$D$2+E13*$E$2+F13*$F$2+G13*$G$2+H13*$H$2+I13*$I$2+J13*$J$2+K13*$K$2+L13*$L$2+M13*$M$2+N13*$N$2+O13*$O$2+P13*$P$2+Q13*$Q$2-5*T13+R13*0.25+S13*0.25 -> 91.895 | V13: =ROUNDUP(U13,0) -> 92 | W13: =IFS(V13>=90, "A+", V13>=85, "A", V13>=80, "A-", V13>=77, "B+", V13>=73, "B", V13>=70, "B-", TRUE, "") -> A+
A14: Lise ZHENG | B14: f11402009 | C14: Cyber Punk | D14: 83 | E14: 90 | F14: 0 | G14: 92 | H14: 88 | I14: 92 | J14: 90 | K14: 88 | L14: 90 | M14: 89 | N14: 89 | O14: 92 | P14: 90 | Q14: 91 | U14: =D14*$D$2+E14*$E$2+F14*$F$2+G14*$G$2+H14*$H$2+I14*$I$2+J14*$J$2+K14*$K$2+L14*$L$2+M14*$M$2+N14*$N$2+O14*$O$2+P14*$P$2+Q14*$Q$2-5*T14+R14*0.25+S14*0.25 -> 80.545 | V14: =ROUNDUP(U14,0) -> 81 | W14: =IFS(V14>=90, "A+", V14>=85, "A", V14>=80, "A-", V14>=77, "B+", V14>=73, "B", V14>=70, "B-", TRUE, "") -> A-
A15: 柯議翔 | B15: M11407319 | C15: Cyber Punk | D15: 83 | E15: 90 | F15: 100 | G15: 92 | H15: 86 | I15: 92 | J15: {=_xlfn.XLOOKUP($A15, 'Camping Simulation'!$B:$B, 'Camping Simulation'!$K:$K, "X")} -> 90 | K15: 88 | L15: 92 | M15: 94 | N15: 90 | O15: 92 | P15: 93 | Q15: 91 | U15: =D15*$D$2+E15*$E$2+F15*$F$2+G15*$G$2+H15*$H$2+I15*$I$2+J15*$J$2+K15*$K$2+L15*$L$2+M15*$M$2+N15*$N$2+O15*$O$2+P15*$P$2+Q15*$Q$2-5*T15+R15*0.25+S15*0.25 -> 91 | V15: =ROUNDUP(U15,0) -> 91 | W15: =IFS(V15>=90, "A+", V15>=85, "A", V15>=80, "A-", V15>=77, "B+", V15>=73, "B", V15>=70, "B-", TRUE, "") -> A+
A16: 盛爾君 | B16: M11407501 | C16: Cyber Punk | D16: 83 | E16: 90 | F16: 100 | G16: 92 | H16: 87 | I16: 92 | J16: {=_xlfn.XLOOKUP($A16, 'Camping Simulation'!$B:$B, 'Camping Simulation'!$K:$K, "X")} -> 88 | K16: 88 | L16: 90 | M16: 89 | N16: 89 | O16: 92 | P16: 88 | Q16: 89 | U16: =D16*$D$2+E16*$E$2+F16*$F$2+G16*$G$2+H16*$H$2+I16*$I$2+J16*$J$2+K16*$K$2+L16*$L$2+M16*$M$2+N16*$N$2+O16*$O$2+P16*$P$2+Q16*$Q$2-5*T16+R16*0.25+S16*0.25 -> 90.395 | V16: =ROUNDUP(U16,0) -> 91 | W16: =IFS(V16>=90, "A+", V16>=85, "A", V16>=80, "A-", V16>=77, "B+", V16>=73, "B", V16>=70, "B-", TRUE, "") -> A+
A17: 許詠翔 | B17: M11407502 | C17: Cyber Punk | D17: 83 | E17: 90 | F17: 100 | G17: 92 | H17: 90 | I17: 92 | J17: {=_xlfn.XLOOKUP($A17, 'Camping Simulation'!$B:$B, 'Camping Simulation'!$K:$K, "X")} -> 92 | K17: 88 | L17: 94 | M17: 92 | N17: 92 | O17: 92 | P17: 92 | Q17: 92 | U17: =D17*$D$2+E17*$E$2+F17*$F$2+G17*$G$2+H17*$H$2+I17*$I$2+J17*$J$2+K17*$K$2+L17*$L$2+M17*$M$2+N17*$N$2+O17*$O$2+P17*$P$2+Q17*$Q$2-5*T17+R17*0.25+S17*0.25 -> 91.18 | V17: =ROUNDUP(U17,0) -> 92 | W17: =IFS(V17>=90, "A+", V17>=85, "A", V17>=80, "A-", V17>=77, "B+", V17>=73, "B", V17>=70, "B-", TRUE, "") -> A+
A18: 龔效諄 | B18: M11407618 | C18: Cyber Punk | D18: 83 | E18: 90 | F18: 100 | G18: 92 | H18: 88 | I18: 92 | J18: {=_xlfn.XLOOKUP($A18, 'Camping Simulation'!$B:$B, 'Camping Simulation'!$K:$K, "X")} -> 92 | K18: 88 | L18: 91 | M18: 93 | N18: 93 | O18: 92 | P18: 90 | Q18: 89 | R18: 1 | U18: =D18*$D$2+E18*$E$2+F18*$F$2+G18*$G$2+H18*$H$2+I18*$I$2+J18*$J$2+K18*$K$2+L18*$L$2+M18*$M$2+N18*$N$2+O18*$O$2+P18*$P$2+Q18*$Q$2-5*T18+R18*0.25+S18*0.25 -> 91.235 | V18: =ROUNDUP(U18,0) -> 92 | W18: =IFS(V18>=90, "A+", V18>=85, "A", V18>=80, "A-", V18>=77, "B+", V18>=73, "B", V18>=70, "B-", TRUE, "") -> A+
A19: Walfroy, Yves, Francois, SAINT-GUILHEM | B19: e11415031 | C19: Cyber Six | D19: 86 | E19: 90 | F19: 100 | G19: 92 | H19: 87 | I19: 92.5 | J19: 87 | K19: 81 | L19: 90 | M19: 0 | N19: 90 | O19: 92 | P19: 87 | Q19: 86 | U19: =D19*$D$2+E19*$E$2+F19*$F$2+G19*$G$2+H19*$H$2+I19*$I$2+J19*$J$2+K19*$K$2+L19*$L$2+M19*$M$2+N19*$N$2+O19*$O$2+P19*$P$2+Q19*$Q$2-5*T19+R19*0.25+S19*0.25 -> 85.165 | V19: =ROUNDUP(U19,0) -> 86 | W19: =IFS(V19>=90, "A+", V19>=85, "A", V19>=80, "A-", V19>=77, "B+", V19>=73, "B", V19>=70, "B-", TRUE, "") -> A
A20: DENNISON SOEDIBJO | B20: f11415018 | C20: Cyber Six | D20: 86 | E20: 90 | F20: 100 | G20: 92 | H20: 87 | I20: 92.5 | J20: {=_xlfn.XLOOKUP($A20, 'Camping Simulation'!$B:$B, 'Camping Simulation'!$K:$K, "X")} -> 91 | K20: 81 | L20: 90 | M20: 80 | N20: 80 | O20: 92 | P20: 80 | Q20: 80 | U20: =D20*$D$2+E20*$E$2+F20*$F$2+G20*$G$2+H20*$H$2+I20*$I$2+J20*$J$2+K20*$K$2+L20*$L$2+M20*$M$2+N20*$N$2+O20*$O$2+P20*$P$2+Q20*$Q$2-5*T20+R20*0.25+S20*0.25 -> 88.42 | V20: =ROUNDUP(U20,0) -> 89 | W20: =IFS(V20>=90, "A+", V20>=85, "A", V20>=80, "A-", V20>=77, "B+", V20>=73, "B", V20>=70, "B-", TRUE, "") -> A
A21: DIVEN DECHAL JATIPUTRA | B21: f11415019 | C21: Cyber Six | D21: 86 | E21: 90 | F21: 100 | G21: 92 | H21: 89 | I21: 92.5 | J21: {=_xlfn.XLOOKUP($A21, 'Camping Simulation'!$B:$B, 'Camping Simulation'!$K:$K, "X")} -> 89 | K21: 81 | L21: 91 | M21: 93 | N21: 92 | O21: 92 | P21: 80 | Q21: 92 | U21: =D21*$D$2+E21*$E$2+F21*$F$2+G21*$G$2+H21*$H$2+I21*$I$2+J21*$J$2+K21*$K$2+L21*$L$2+M21*$M$2+N21*$N$2+O21*$O$2+P21*$P$2+Q21*$Q$2-5*T21+R21*0.25+S21*0.25 -> 90 | V21: =ROUNDUP(U21,0) -> 90 | W21: =IFS(V21>=90, "A+", V21>=85, "A", V21>=80, "A-", V21>=77, "B+", V21>=73, "B", V21>=70, "B-", TRUE, "") -> A+
A22: JOSHUA PUTRA PRATAMA | B22: f11415027 | C22: Cyber Six | D22: 86 | E22: 90 | F22: 100 | G22: 92 | H22: 92 | I22: 92.5 | J22: {=_xlfn.XLOOKUP($A22, 'Camping Simulation'!$B:$B, 'Camping Simulation'!$K:$K, "X")} -> 92 | K22: 81 | L22: 92 | M22: 92 | N22: 93 | O22: 92 | P22: 93 | Q22: 93 | U22: =D22*$D$2+E22*$E$2+F22*$F$2+G22*$G$2+H22*$H$2+I22*$I$2+J22*$J$2+K22*$K$2+L22*$L$2+M22*$M$2+N22*$N$2+O22*$O$2+P22*$P$2+Q22*$Q$2-5*T22+R22*0.25+S22*0.25 -> 90.49 | V22: =ROUNDUP(U22,0) -> 91 | W22: =IFS(V22>=90, "A+", V22>=85, "A", V22>=80, "A-", V22>=77, "B+", V22>=73, "B", V22>=70, "B-", TRUE, "") -> A+
A23: Rivaldo Yudha Pradana | B23: M11407804 | C23: Cyber Six | D23: 86 | E23: 90 | F23: 100 | G23: 92 | H23: 92 | I23: 92.5 | J23: {=_xlfn.XLOOKUP($A23, 'Camping Simulation'!$B:$B, 'Camping Simulation'!$K:$K, "X")} -> 91 | K23: 81 | L23: 93 | M23: 92 | N23: 93 | O23: 92 | P23: 93 | Q23: 93 | U23: =D23*$D$2+E23*$E$2+F23*$F$2+G23*$G$2+H23*$H$2+I23*$I$2+J23*$J$2+K23*$K$2+L23*$L$2+M23*$M$2+N23*$N$2+O23*$O$2+P23*$P$2+Q23*$Q$2-5*T23+R23*0.25+S23*0.25 -> 90.52 | V23: =ROUNDUP(U23,0) -> 91 | W23: =IFS(V23>=90, "A+", V23>=85, "A", V23>=80, "A-", V23>=77, "B+", V23>=73, "B", V23>=70, "B-", TRUE, "") -> A+
A24: MIKHAEL GERSON SILAEN | B24: m11407809 | C24: Cyber Six | D24: 86 | E24: 90 | F24: 100 | G24: 92 | H24: 91 | I24: 92.5 | J24: {=_xlfn.XLOOKUP($A24, 'Camping Simulation'!$B:$B, 'Camping Simulation'!$K:$K, "X")} -> 92 | K24: 81 | L24: 92 | M24: 91 | N24: 91 | O24: 92 | P24: 93 | Q24: 93 | U24: =D24*$D$2+E24*$E$2+F24*$F$2+G24*$G$2+H24*$H$2+I24*$I$2+J24*$J$2+K24*$K$2+L24*$L$2+M24*$M$2+N24*$N$2+O24*$O$2+P24*$P$2+Q24*$Q$2-5*T24+R24*0.25+S24*0.25 -> 90.33 | V24: =ROUNDUP(U24,0) -> 91 | W24: =IFS(V24>=90, "A+", V24>=85, "A", V24>=80, "A-", V24>=77, "B+", V24>=73, "B", V24>=70, "B-", TRUE, "") -> A+
A25: Peter Jonathan Kuhn | B25: e11415021 | C25: European Avalanche | D25: 90 | E25: 84 | F25: 100 | G25: 92 | H25: 92 | I25: 91 | J25: 88 | K25: 90 | L25: 89 | M25: 0 | N25: 88 | O25: 92 | P25: 91 | Q25: 92 | R25: 1 | U25: =D25*$D$2+E25*$E$2+F25*$F$2+G25*$G$2+H25*$H$2+I25*$I$2+J25*$J$2+K25*$K$2+L25*$L$2+M25*$M$2+N25*$N$2+O25*$O$2+P25*$P$2+Q25*$Q$2-5*T25+R25*0.25+S25*0.25 -> 86.615 | V25: =ROUNDUP(U25,0) -> 87 | W25: =IFS(V25>=90, "A+", V25>=85, "A", V25>=80, "A-", V25>=77, "B+", V25>=73, "B", V25>=70, "B-", TRUE, "") -> A
A26: Ayman Rabih Kallouz | B26: e11415023 | C26: European Avalanche | D26: 90 | E26: 84 | F26: 100 | G26: 92 | H26: 88 | I26: 91 | J26: 0 | K26: 90 | L26: 89 | M26: 88 | N26: 90 | O26: 92 | P26: 92 | Q26: 92 | U26: =D26*$D$2+E26*$E$2+F26*$F$2+G26*$G$2+H26*$H$2+I26*$I$2+J26*$J$2+K26*$K$2+L26*$L$2+M26*$M$2+N26*$N$2+O26*$O$2+P26*$P$2+Q26*$Q$2-5*T26+R26*0.25+S26*0.25 -> 89.09 | V26: =ROUNDUP(U26,0) -> 90 | W26: =IFS(V26>=90, "A+", V26>=85, "A", V26>=80, "A-", V26>=77, "B+", V26>=73, "B", V26>=70, "B-", TRUE, "") -> A+
A27: Andreas Leeb | B27: e11415025 | C27: European Avalanche | D27: 90 | E27: 84 | F27: 100 | G27: 92 | H27: 90 | I27: 91 | J27: {=_xlfn.XLOOKUP($A27, 'Camping Simulation'!$B:$B, 'Camping Simulation'!$K:$K, "X")} -> 87 | K27: 90 | L27: 89 | M27: 87 | N27: 89 | O27: 92 | P27: 90 | Q27: 0 | U27: =D27*$D$2+E27*$E$2+F27*$F$2+G27*$G$2+H27*$H$2+I27*$I$2+J27*$J$2+K27*$K$2+L27*$L$2+M27*$M$2+N27*$N$2+O27*$O$2+P27*$P$2+Q27*$Q$2-5*T27+R27*0.25+S27*0.25 -> 88.4 | V27: =ROUNDUP(U27,0) -> 89 | W27: =IFS(V27>=90, "A+", V27>=85, "A", V27>=80, "A-", V27>=77, "B+", V27>=73, "B", V27>=70, "B-", TRUE, "") -> A
A28: Adam Pach | B28: e11415030 | C28: European Avalanche | D28: 90 | E28: 84 | F28: 100 | G28: 92 | H28: 88 | I28: 91 | J28: {=_xlfn.XLOOKUP($A28, 'Camping Simulation'!$B:$B, 'Camping Simulation'!$K:$K, "X")} -> 89 | K28: 90 | L28: 90 | M28: 88 | N28: 92 | O28: 92 | P28: 88 | Q28: 89 | U28: =D28*$D$2+E28*$E$2+F28*$F$2+G28*$G$2+H28*$H$2+I28*$I$2+J28*$J$2+K28*$K$2+L28*$L$2+M28*$M$2+N28*$N$2+O28*$O$2+P28*$P$2+Q28*$Q$2-5*T28+R28*0.25+S28*0.25 -> 90.845 | V28: =ROUNDUP(U28,0) -> 91 | W28: =IFS(V28>=90, "A+", V28>=85, "A", V28>=80, "A-", V28>=77, "B+", V28>=73, "B", V28>=70, "B-", TRUE, "") -> A+
A29: Bernardo Cavalcante Vieira de Andrade | B29: e11423008 | C29: European Avalanche | D29: 90 | E29: 84 | F29: 100 | G29: 92 | H29: 87 | I29: 91 | J29: 92 | K29: 90 | L29: 0 | M29: 90 | N29: 94 | O29: 92 | P29: 92 | Q29: 0 | U29: =D29*$D$2+E29*$E$2+F29*$F$2+G29*$G$2+H29*$H$2+I29*$I$2+J29*$J$2+K29*$K$2+L29*$L$2+M29*$M$2+N29*$N$2+O29*$O$2+P29*$P$2+Q29*$Q$2-5*T29+R29*0.25+S29*0.25 -> 84.47 | V29: =ROUNDUP(U29,0) -> 85 | W29: =IFS(V29>=90, "A+", V29>=85, "A", V29>=80, "A-", V29>=77, "B+", V29>=73, "B", V29>=70, "B-", TRUE, "") -> A
A30: Lucas Metzger | B30: f11415020 | C30: European Avalanche | D30: 90 | E30: 84 | F30: 100 | G30: 92 | H30: 87 | I30: 91 | J30: {=_xlfn.XLOOKUP($A30, 'Camping Simulation'!$B:$B, 'Camping Simulation'!$K:$K, "X")} -> 87 | K30: 90 | L30: 88 | M30: 88 | N30: 87 | O30: 92 | P30: 90 | Q30: 91 | U30: =D30*$D$2+E30*$E$2+F30*$F$2+G30*$G$2+H30*$H$2+I30*$I$2+J30*$J$2+K30*$K$2+L30*$L$2+M30*$M$2+N30*$N$2+O30*$O$2+P30*$P$2+Q30*$Q$2-5*T30+R30*0.25+S30*0.25 -> 90.545 | V30: =ROUNDUP(U30,0) -> 91 | W30: =IFS(V30>=90, "A+", V30>=85, "A", V30>=80, "A-", V30>=77, "B+", V30>=73, "B", V30>=70, "B-", TRUE, "") -> A+
A31: ITSUKI KURIYAMA | B31: F11415005 | C31: GPT+ | D31: 83 | E31: 88 | F31: 100 | G31: 91 | H31: 0 | I31: 90 | J31: 0 | K31: 78 | L31: 94 | M31: 93 | N31: 92 | O31: 91 | P31: 92 | Q31: 92 | R31: 1 | U31: =D31*$D$2+E31*$E$2+F31*$F$2+G31*$G$2+H31*$H$2+I31*$I$2+J31*$J$2+K31*$K$2+L31*$L$2+M31*$M$2+N31*$N$2+O31*$O$2+P31*$P$2+Q31*$Q$2-5*T31+R31*0.25+S31*0.25 -> 86.64 | V31: =ROUNDUP(U31,0) -> 87 | W31: =IFS(V31>=90, "A+", V31>=85, "A", V31>=80, "A-", V31>=77, "B+", V31>=73, "B", V31>=70, "B-", TRUE, "") -> A
A32: 祖祥恩 | B32: M11307310 | C32: GPT+ | D32: 83 | E32: 88 | F32: 100 | G32: 91 | H32: 85 | I32: 90 | J32: {=_xlfn.XLOOKUP($A32, 'Camping Simulation'!$B:$B, 'Camping Simulation'!$K:$K, "X")} -> 87 | K32: 78 | L32: 90 | M32: 90 | N32: 92 | O32: 91 | P32: 91 | Q32: 90 | U32: =D32*$D$2+E32*$E$2+F32*$F$2+G32*$G$2+H32*$H$2+I32*$I$2+J32*$J$2+K32*$K$2+L32*$L$2+M32*$M$2+N32*$N$2+O32*$O$2+P32*$P$2+Q32*$Q$2-5*T32+R32*0.25+S32*0.25 -> 88.555 | V32: =ROUNDUP(U32,0) -> 89 | W32: =IFS(V32>=90, "A+", V32>=85, "A", V32>=80, "A-", V32>=77, "B+", V32>=73, "B", V32>=70, "B-", TRUE, "") -> A
A33: 葉人瑋 | B33: m11407437 | C33: GPT+ | D33: 83 | E33: 88 | F33: 100 | G33: 91 | H33: 85 | I33: 90 | J33: {=_xlfn.XLOOKUP($A33, 'Camping Simulation'!$B:$B, 'Camping Simulation'!$K:$K, "X")} -> 89 | K33: 78 | L33: 90 | M33: 89 | N33: 90 | O33: 91 | P33: 85 | Q33: 0 | U33: =D33*$D$2+E33*$E$2+F33*$F$2+G33*$G$2+H33*$H$2+I33*$I$2+J33*$J$2+K33*$K$2+L33*$L$2+M33*$M$2+N33*$N$2+O33*$O$2+P33*$P$2+Q33*$Q$2-5*T33+R33*0.25+S33*0.25 -> 86.045 | V33: =ROUNDUP(U33,0) -> 87 | W33: =IFS(V33>=90, "A+", V33>=85, "A", V33>=80, "A-", V33>=77, "B+", V33>=73, "B", V33>=70, "B-", TRUE, "") -> A
A34: 蔡哲維 | B34: m11407524 | C34: GPT+ | D34: 83 | E34: 88 | F34: 100 | G34: 91 | H34: 0 | I34: 90 | J34: 0 | K34: 78 | L34: 90 | M34: 89 | N34: 90 | O34: 91 | P34: 0 | Q34: 87 | U34: =D34*$D$2+E34*$E$2+F34*$F$2+G34*$G$2+H34*$H$2+I34*$I$2+J34*$J$2+K34*$K$2+L34*$L$2+M34*$M$2+N34*$N$2+O34*$O$2+P34*$P$2+Q34*$Q$2-5*T34+R34*0.25+S34*0.25 -> 83.465 | V34: =ROUNDUP(U34,0) -> 84 | W34: =IFS(V34>=90, "A+", V34>=85, "A", V34>=80, "A-", V34>=77, "B+", V34>=73, "B", V34>=70, "B-", TRUE, "") -> A-
A35: 陳增勇 | B35: B11007106 | C35: Insect | D35: 92 | E35: 94 | F35: 100 | G35: 95 | H35: 88 | I35: 83 | J35: {=_xlfn.XLOOKUP($A35, 'Camping Simulation'!$B:$B, 'Camping Simulation'!$K:$K, "X")} -> 92 | K35: 82 | L35: 0 | M35: 91 | N35: 90 | O35: 95 | P35: 93 | Q35: 93 | U35: =D35*$D$2+E35*$E$2+F35*$F$2+G35*$G$2+H35*$H$2+I35*$I$2+J35*$J$2+K35*$K$2+L35*$L$2+M35*$M$2+N35*$N$2+O35*$O$2+P35*$P$2+Q35*$Q$2-5*T35+R35*0.25+S35*0.25 -> 86.76 | V35: =ROUNDUP(U35,0) -> 87 | W35: =IFS(V35>=90, "A+", V35>=85, "A", V35>=80, "A-", V35>=77, "B+", V35>=73, "B", V35>=70, "B-", TRUE, "") -> A
A36: Laina Farsiah | B36: D11415802 | C36: Insect | D36: 92 | E36: 94 | F36: 100 | G36: 95 | H36: 95 | I36: 83 | J36: {=_xlfn.XLOOKUP($A36, 'Camping Simulation'!$B:$B, 'Camping Simulation'!$K:$K, "X")} -> 94 | K36: 82 | L36: 92 | M36: 92 | N36: 95 | O36: 95 | P36: 94 | Q36: 94 | R36: 1 | U36: =D36*$D$2+E36*$E$2+F36*$F$2+G36*$G$2+H36*$H$2+I36*$I$2+J36*$J$2+K36*$K$2+L36*$L$2+M36*$M$2+N36*$N$2+O36*$O$2+P36*$P$2+Q36*$Q$2-5*T36+R36*0.25+S36*0.25 -> 92.07 | V36: =ROUNDUP(U36,0) -> 93 | W36: =IFS(V36>=90, "A+", V36>=85, "A", V36>=80, "A-", V36>=77, "B+", V36>=73, "B", V36>=70, "B-", TRUE, "") -> A+
A37: Alim Misbullah | B37: D11415803 | C37: Insect | D37: 92 | E37: 94 | F37: 100 | G37: 95 | H37: 90 | I37: 83 | J37: {=_xlfn.XLOOKUP($A37, 'Camping Simulation'!$B:$B, 'Camping Simulation'!$K:$K, "X")} -> 93 | K37: 82 | L37: 92 | M37: 90 | N37: 91 | O37: 95 | P37: 91 | Q37: 93 | R37: 1 | U37: =D37*$D$2+E37*$E$2+F37*$F$2+G37*$G$2+H37*$H$2+I37*$I$2+J37*$J$2+K37*$K$2+L37*$L$2+M37*$M$2+N37*$N$2+O37*$O$2+P37*$P$2+Q37*$Q$2-5*T37+R37*0.25+S37*0.25 -> 91.6 | V37: =ROUNDUP(U37,0) -> 92 | W37: =IFS(V37>=90, "A+", V37>=85, "A", V37>=80, "A-", V37>=77, "B+", V37>=73, "B", V37>=70, "B-", TRUE, "") -> A+
A38: Danis Putra Perdana | B38: D11415806 | C38: Insect | D38: 92 | E38: 94 | F38: 100 | G38: 95 | H38: 90 | I38: 83 | J38: {=_xlfn.XLOOKUP($A38, 'Camping Simulation'!$B:$B, 'Camping Simulation'!$K:$K, "X")} -> 89 | K38: 82 | L38: 90 | M38: 91 | N38: 90 | O38: 95 | P38: 88 | Q38: 89 | R38: 1 | U38: =D38*$D$2+E38*$E$2+F38*$F$2+G38*$G$2+H38*$H$2+I38*$I$2+J38*$J$2+K38*$K$2+L38*$L$2+M38*$M$2+N38*$N$2+O38*$O$2+P38*$P$2+Q38*$Q$2-5*T38+R38*0.25+S38*0.25 -> 91.245 | V38: =ROUNDUP(U38,0) -> 92 | W38: =IFS(V38>=90, "A+", V38>=85, "A", V38>=80, "A-", V38>=77, "B+", V38>=73, "B", V38>=70, "B-", TRUE, "") -> A+
A39: Puspa Ira Dewi Candra Wulan | B39: D11415807 | C39: Insect | D39: 92 | E39: 94 | F39: 100 | G39: 95 | H39: 88 | I39: 83 | J39: {=_xlfn.XLOOKUP($A39, 'Camping Simulation'!$B:$B, 'Camping Simulation'!$K:$K, "X")} -> 90 | K39: 82 | L39: 93 | M39: 91 | N39: 89 | O39: 95 | P39: 93 | Q39: 91 | R39: 1 | S39: 1 | U39: =D39*$D$2+E39*$E$2+F39*$F$2+G39*$G$2+H39*$H$2+I39*$I$2+J39*$J$2+K39*$K$2+L39*$L$2+M39*$M$2+N39*$N$2+O39*$O$2+P39*$P$2+Q39*$Q$2-5*T39+R39*0.25+S39*0.25 -> 91.77 | V39: =ROUNDUP(U39,0) -> 92 | W39: =IFS(V39>=90, "A+", V39>=85, "A", V39>=80, "A-", V39>=77, "B+", V39>=73, "B", V39>=70, "B-", TRUE, "") -> A+
A40: Aurelio Naufal Effendy | B40: M11415802 | C40: Insect | D40: 92 | E40: 94 | F40: 100 | G40: 95 | H40: 90 | I40: 83 | J40: {=_xlfn.XLOOKUP($A40, 'Camping Simulation'!$B:$B, 'Camping Simulation'!$K:$K, "X")} -> 95 | K40: 82 | L40: 92 | M40: 92 | N40: 92 | O40: 95 | P40: 90 | Q40: 92 | U40: =D40*$D$2+E40*$E$2+F40*$F$2+G40*$G$2+H40*$H$2+I40*$I$2+J40*$J$2+K40*$K$2+L40*$L$2+M40*$M$2+N40*$N$2+O40*$O$2+P40*$P$2+Q40*$Q$2-5*T40+R40*0.25+S40*0.25 -> 91.49 | V40: =ROUNDUP(U40,0) -> 92 | W40: =IFS(V40>=90, "A+", V40>=85, "A", V40>=80, "A-", V40>=77, "B+", V40>=73, "B", V40>=70, "B-", TRUE, "") -> A+
A41: 檢查配分用 | D41: 100 | E41: 100 | F41: 100 | G41: 100 | H41: 100 | I41: 100 | J41: 100 | K41: 100 | L41: 100 | M41: 100 | N41: 100 | O41: 100 | P41: 100 | Q41: 100 | R41: 1 | S41: 1 | U41: =D41*$D$2+E41*$E$2+F41*$F$2+G41*$G$2+H41*$H$2+I41*$I$2+J41*$J$2+K41*$K$2+L41*$L$2+M41*$M$2+N41*$N$2+O41*$O$2+P41*$P$2+Q41*$Q$2-5*T41+R41*0.25+S41*0.25 -> 100.5 | V41: =ROUNDUP(U41,0) -> 101
R42: 一次0.25

Sheet Grade
A1: 名字 | B1: 學號 | C1: 分組 | D1: Cybersecurity news presentation | E1: CTI report slide | F1: Malware analysis | G1: Cuckoo slide/json | H1: Machine learning in malware analysis | I1: Project Proposal | J1: Project Proposal Form | K1: Project Proposal Slide | L1: Red team practice | M1: Caldera Form | N1: Caldera Slide+md+json+proco | O1: Paper presentation | P1: Week 12 - Paper Form | Q1: Week 13 - Paper Form | R1: Week 14 - Paper Form | S1: Paper slide | T1: Final Project 老師 | U1: Final Project Form 1 | V1: Final Project Form 2 | W1: Final Project md+code/log+slide | X1: Cybersec 2026 心得 | Y1: LLM 回答 | Z1: 缺席 | AA1: 總分 | AD1: Name | AF1: Name
D2: 0.1 | E2: // | F2: 0.1 | G2: // | H2: 0.1 | I2: 0.04 | J2: 0.01 | K2: // | L2: 0.08 | M2: 0.02 | N2: // | O2: 0.15 | P2: 0.05 | Q2: 0.05 | R2: 0.05 | S2: // | T2: 0.2 | U2: 0.025 | V2: 0.025 | W2: // | X2: bonus | Y2: bonus | AD2: W12
A3: 黃文良 | B3: B11107152 | C3: ANTSLAB | D3: 86 | E3: 1 | F3: 94 | G3: 1 | H3: 100 | I3: 95 | J3: 86 | K3: 1 | L3: 93 | M3: {=_xlfn.XLOOKUP($A3, 'Camping Simulation'!$B:$B, 'Camping Simulation'!$K:$K, "X")} -> 87 | N3: 0 | O3: 94 | P3: {=_xlfn.XLOOKUP($B3, 'W12 paper end'!$C:$C, 'W12 paper end'!$L:$L, "0")} -> 89 | Q3: {=_xlfn.XLOOKUP($B3, 'W13 paper end'!$C:$C, 'W13 paper end'!$L:$L, "0")} -> 89 | R3: {=_xlfn.XLOOKUP($B3, 'W14 paper end'!$C:$C, 'W14 paper end'!$K:$K, "0")} -> 89 | S3: 1 | T3: 95 | U3: 86 | V3: 0 | W3: 1 | X3: {=IF(ISNA(_xlfn.XLOOKUP(U3, AB:AB, AB:AB)), "", "✔")} | Z3: 1 | AA3: =D3*$D$2+F3*$F$2+H3*$H$2+I3*$I$2+J3*$J$2+L3*$L$2+M3*$M$2+O3*$O$2+P3*$P$2+Q3*$Q$2+R3*$R$2+T3*$T$2+U3*$U$2+V3*$V$2-5*Z3 -> 85.44 | AD3: Su Yadana Win | AE3: =IF(COUNTIF($A:$A, AD3)>0, "✓", "") -> ✓ | AF3: Su Yadana Win | AG3: =IF(COUNTIF($A:$A, AF3)>0, "✓", "") -> ✓
A4: 胡承學 | B4: B11107153 | C4: ANTSLAB | D4: 86 | E4: 1 | F4: 94 | G4: 1 | H4: 0 | I4: 95 | J4: 0 | K4: 1 | L4: 93 | M4: {=_xlfn.XLOOKUP($A4, 'Camping Simulation'!$B:$B, 'Camping Simulation'!$K:$K, "X")} -> 90 | N4: 0 | O4: 94 | P4: {=_xlfn.XLOOKUP($B4, 'W12 paper end'!$C:$C, 'W12 paper end'!$L:$L, "X")} -> 90 | Q4: {=_xlfn.XLOOKUP($B4, 'W13 paper end'!$C:$C, 'W13 paper end'!$L:$L, "0")} -> 90 | R4: {=_xlfn.XLOOKUP($B4, 'W14 paper end'!$C:$C, 'W14 paper end'!$K:$K, "0")} -> 90 | S4: 1 | T4: 95 | U4: 88 | V4: 89 | W4: 1 | AA4: =D4*$D$2+F4*$F$2+H4*$H$2+I4*$I$2+J4*$J$2+L4*$L$2+M4*$M$2+O4*$O$2+P4*$P$2+Q4*$Q$2+R4*$R$2+T4*$T$2+U4*$U$2+V4*$V$2-5*Z4 -> 82.065 | AD4: Peter Jonathan Kuhn | AE4: =IF(COUNTIF(A:A, AD4)>0, "✓", "") -> ✓ | AF4: 葉人瑋 | AG4: =IF(COUNTIF($A:$A, AF4)>0, "✓", "") -> ✓
A5: 吳永保 | B5: M11407005 | C5: ANTSLAB | D5: 86 | E5: 1 | F5: 94 | G5: 1 | H5: 100 | I5: 95 | J5: 88 | K5: 1 | L5: 93 | M5: {=_xlfn.XLOOKUP($A5, 'Camping Simulation'!$B:$B, 'Camping Simulation'!$K:$K, "X")} -> 89 | N5: 0 | O5: 94 | P5: {=_xlfn.XLOOKUP($B5, 'W12 paper end'!$C:$C, 'W12 paper end'!$L:$L, "X")} -> 92 | Q5: {=_xlfn.XLOOKUP($B5, 'W13 paper end'!$C:$C, 'W13 paper end'!$L:$L, "0")} -> 90 | R5: {=_xlfn.XLOOKUP($B5, 'W14 paper end'!$B:$B, 'W14 paper end'!$K:$K, "0")} -> 92 | S5: 1 | T5: 95 | U5: 89 | V5: 92 | W5: 1 | AA5: =D5*$D$2+F5*$F$2+H5*$H$2+I5*$I$2+J5*$J$2+L5*$L$2+M5*$M$2+O5*$O$2+P5*$P$2+Q5*$Q$2+R5*$R$2+T5*$T$2+U5*$U$2+V5*$V$2-5*Z5 -> 93.225 | AD5: 蔡哲維 | AE5: =IF(COUNTIF(A:A, AD5)>0, "✓", "") -> ✓ | AF5: 祖祥恩 | AG5: =IF(COUNTIF($A:$A, AF5)>0, "✓", "") -> ✓
A6: 楊晴安 | B6: M11407507 | C6: ANTSLAB | D6: 86 | E6: 1 | F6: 94 | G6: 1 | H6: 100 | I6: 95 | J6: 89 | K6: 1 | L6: 93 | M6: {=_xlfn.XLOOKUP($A6, 'Camping Simulation'!$B:$B, 'Camping Simulation'!$K:$K, "X")} -> 92 | N6: 0 | O6: 94 | P6: {=_xlfn.XLOOKUP($B6, 'W12 paper end'!$C:$C, 'W12 paper end'!$L:$L, "X")} -> 93 | Q6: {=_xlfn.XLOOKUP($B6, 'W13 paper end'!$C:$C, 'W13 paper end'!$L:$L, "0")} -> 91 | R6: {=_xlfn.XLOOKUP($B6, 'W14 paper end'!$C:$C, 'W14 paper end'!$K:$K, "0")} -> 92 | S6: 1 | T6: 95 | U6: 90 | V6: 93 | W6: 1 | X6: V | AA6: =D6*$D$2+F6*$F$2+H6*$H$2+I6*$I$2+J6*$J$2+L6*$L$2+M6*$M$2+O6*$O$2+P6*$P$2+Q6*$Q$2+R6*$R$2+T6*$T$2+U6*$U$2+V6*$V$2-5*Z6 -> 93.445 | AD6: Lucas Metzger | AE6: =IF(COUNTIF(A:A, AD6)>0, "✓", "") -> ✓ | AF6: Laina Farsiah | AG6: =IF(COUNTIF($A:$A, AF6)>0, "✓", "") -> ✓
A7: 洪粲鈞 | B7: M11407519 | C7: ANTSLAB | D7: 86 | E7: 1 | F7: 94 | G7: 1 | H7: 100 | I7: 95 | J7: 93 | K7: 1 | L7: 93 | M7: {=_xlfn.XLOOKUP($A7, 'Camping Simulation'!$B:$B, 'Camping Simulation'!$K:$K, "X")} -> 89 | N7: 0 | O7: 94 | P7: {=_xlfn.XLOOKUP($B7, 'W12 paper end'!$C:$C, 'W12 paper end'!$L:$L, "0")} -> 90 | Q7: {=_xlfn.XLOOKUP($B7, 'W13 paper end'!$C:$C, 'W13 paper end'!$L:$L, "0")} -> 92 | R7: {=_xlfn.XLOOKUP($B7, 'W14 paper end'!$C:$C, 'W14 paper end'!$K:$K, "0")} -> 91 | S7: 1 | T7: 95 | U7: 90 | V7: 90 | W7: 1 | X7: V | AA7: =D7*$D$2+F7*$F$2+H7*$H$2+I7*$I$2+J7*$J$2+L7*$L$2+M7*$M$2+O7*$O$2+P7*$P$2+Q7*$Q$2+R7*$R$2+T7*$T$2+U7*$U$2+V7*$V$2-5*Z7 -> 93.2 | AD7: Ayman Kallouz | AE7: =IF(COUNTIF(A:A, AD7)>0, "✓", "") | AF7: 龔效諄 | AG7: =IF(COUNTIF($A:$A, AF7)>0, "✓", "") -> ✓
A8: 張惟凱 | B8: M11407522 | C8: ANTSLAB | D8: 86 | E8: 1 | F8: 94 | G8: 1 | H8: 100 | I8: 95 | J8: 92 | K8: 1 | L8: 93 | M8: {=_xlfn.XLOOKUP($A8, 'Camping Simulation'!$B:$B, 'Camping Simulation'!$K:$K, "X")} -> 92 | N8: 0 | O8: 94 | P8: {=_xlfn.XLOOKUP($B8, 'W12 paper end'!$C:$C, 'W12 paper end'!$L:$L, "X")} -> 92 | Q8: {=_xlfn.XLOOKUP($B8, 'W13 paper end'!$C:$C, 'W13 paper end'!$L:$L, "0")} -> 91 | R8: {=_xlfn.XLOOKUP($B8, 'W14 paper end'!$C:$C, 'W14 paper end'!$K:$K, "0")} -> 93 | S8: 1 | T8: 95 | U8: 94 | V8: 93 | W8: 1 | X8: V | AA8: =D8*$D$2+F8*$F$2+H8*$H$2+I8*$I$2+J8*$J$2+L8*$L$2+M8*$M$2+O8*$O$2+P8*$P$2+Q8*$Q$2+R8*$R$2+T8*$T$2+U8*$U$2+V8*$V$2-5*Z8 -> 93.575 | AD8: 祖祥恩 | AE8: =IF(COUNTIF(A:A, AD8)>0, "✓", "") -> ✓ | AF8: Puspa Ira Dewi Candra Wulan | AG8: =IF(COUNTIF($A:$A, AF8)>0, "✓", "") -> ✓
A9: SU YADANA WIN | B9: d11415809 | C9: BENI | D9: 90 | E9: 1 | F9: 84 | G9: 1 | H9: 100 | I9: 95 | J9: 88 | K9: 1 | L9: 91 | M9: 0 | N9: 1 | O9: 85 | P9: {=_xlfn.XLOOKUP($B9, 'W12 paper end'!$C:$C, 'W12 paper end'!$L:$L, "X")} -> 94 | Q9: {=_xlfn.XLOOKUP($B9, 'W13 paper end'!$C:$C, 'W13 paper end'!$L:$L, "0")} -> 91 | R9: {=_xlfn.XLOOKUP($B9, 'W14 paper end'!$C:$C, 'W14 paper end'!$K:$K, "0")} -> 90 | S9: 1 | T9: 95 | U9: 95 | V9: 95 | W9: 1 | X9: V | AA9: =D9*$D$2+F9*$F$2+H9*$H$2+I9*$I$2+J9*$J$2+L9*$L$2+M9*$M$2+O9*$O$2+P9*$P$2+Q9*$Q$2+R9*$R$2+T9*$T$2+U9*$U$2+V9*$V$2-5*Z9 -> 89.61 | AD9: Benjamin Gillard | AE9: =IF(COUNTIF(A:A, AD9)>0, "✓", "") -> ✓ | AF9: ZHENG Lise | AG9: =IF(COUNTIF($A:$A, AF9)>0, "✓", "")
A10: Jules GIRARD | B10: e11415022 | C10: BENI | D10: 90 | E10: 1 | F10: 84 | G10: 1 | H10: 0 | I10: 95 | J10: 90 | K10: 1 | L10: 91 | M10: {=_xlfn.XLOOKUP($A10, 'Camping Simulation'!$B:$B, 'Camping Simulation'!$K:$K, "X")} -> 89 | N10: 1 | O10: 85 | P10: {=_xlfn.XLOOKUP($B10, 'W12 paper end'!$C:$C, 'W12 paper end'!$L:$L, "0")} -> 91 | Q10: {=_xlfn.XLOOKUP($B10, 'W13 paper end'!$C:$C, 'W13 paper end'!$L:$L, "0")} -> 90 | R10: {=_xlfn.XLOOKUP($B10, 'W14 paper end'!$C:$C, 'W14 paper end'!$K:$K, "0")} -> 91 | S10: 1 | T10: 95 | U10: 92 | V10: 93 | W10: 1 | AA10: =D10*$D$2+F10*$F$2+H10*$H$2+I10*$I$2+J10*$J$2+L10*$L$2+M10*$M$2+O10*$O$2+P10*$P$2+Q10*$Q$2+R10*$R$2+T10*$T$2+U10*$U$2+V10*$V$2-5*Z10 -> 81.135 | AD10: 柯議翔 | AE10: =IF(COUNTIF(A:A, AD10)>0, "✓", "") -> ✓ | AF10: danis putra perdana | AG10: =IF(COUNTIF($A:$A, AF10)>0, "✓", "") -> ✓
A11: Benjamin GILLARD | B11: e11415026 | C11: BENI | D11: 90 | E11: 1 | F11: 84 | G11: 1 | H11: 100 | I11: 95 | J11: 88 | K11: 1 | L11: 91 | M11: {=_xlfn.XLOOKUP($A11, 'Camping Simulation'!$B:$B, 'Camping Simulation'!$K:$K, "X")} -> 89 | N11: 1 | O11: 85 | P11: {=_xlfn.XLOOKUP($B11, 'W12 paper end'!$C:$C, 'W12 paper end'!$L:$L, "0")} -> 88 | Q11: {=_xlfn.XLOOKUP($B11, 'W13 paper end'!$C:$C, 'W13 paper end'!$L:$L, "0")} -> 90 | R11: {=_xlfn.XLOOKUP($B11, 'W14 paper end'!$C:$C, 'W14 paper end'!$K:$K, "0")} -> 88 | S11: 1 | T11: 95 | U11: 90 | V11: 88 | W11: 1 | AA11: =D11*$D$2+F11*$F$2+H11*$H$2+I11*$I$2+J11*$J$2+L11*$L$2+M11*$M$2+O11*$O$2+P11*$P$2+Q11*$Q$2+R11*$R$2+T11*$T$2+U11*$U$2+V11*$V$2-5*Z11 -> 90.64 | AD11: 龔效諄 | AE11: =IF(COUNTIF(A:A, AD11)>0, "✓", "") -> ✓ | AF11: Alim Misbullah | AG11: =IF(COUNTIF($A:$A, AF11)>0, "✓", "") -> ✓
A12: Ugo LINDEPERG | B12: e11415027 | C12: BENI | D12: 90 | E12: 1 | F12: 84 | G12: 1 | H12: 0 | I12: 95 | J12: 90 | K12: 1 | L12: 91 | M12: 0 | N12: 1 | O12: 85 | P12: {=_xlfn.XLOOKUP($B12, 'W12 paper end'!$C:$C, 'W12 paper end'!$L:$L, "0")} -> 91 | Q12: {=_xlfn.XLOOKUP($B12, 'W13 paper end'!$C:$C, 'W13 paper end'!$L:$L, "0")} -> 88 | R12: {=_xlfn.XLOOKUP($B12, 'W14 paper end'!$C:$C, 'W14 paper end'!$K:$K, "0")} -> 89 | S12: 1 | T12: 95 | U12: 92 | V12: 93 | W12: 1 | AA12: =D12*$D$2+F12*$F$2+H12*$H$2+I12*$I$2+J12*$J$2+L12*$L$2+M12*$M$2+O12*$O$2+P12*$P$2+Q12*$Q$2+R12*$R$2+T12*$T$2+U12*$U$2+V12*$V$2-5*Z12 -> 79.155 | AD12: Mikhael Gerson Silaen | AE12: =IF(COUNTIF(A:A, AD12)>0, "✓", "") -> ✓ | AF12: Oriiana Nedzelska | AG12: =IF(COUNTIF($A:$A, AF12)>0, "✓", "") -> ✓
A13: Oriiana Nedzelska | B13: f11415026 | C13: BENI | D13: 90 | E13: 1 | F13: 84 | G13: 1 | H13: 100 | I13: 95 | J13: 90 | K13: 1 | L13: 91 | M13: {=_xlfn.XLOOKUP($A13, 'Camping Simulation'!$B:$B, 'Camping Simulation'!$K:$K, "X")} -> 92 | N13: 1 | O13: 85 | P13: {=_xlfn.XLOOKUP($B13, 'W12 paper end'!$C:$C, 'W12 paper end'!$L:$L, "0")} -> 92 | Q13: {=_xlfn.XLOOKUP($B13, 'W13 paper end'!$C:$C, 'W13 paper end'!$L:$L, "0")} -> 91 | R13: {=_xlfn.XLOOKUP($B13, 'W14 paper end'!$C:$C, 'W14 paper end'!$K:$K, "0")} -> 93 | S13: 1 | T13: 95 | U13: 93 | V13: 92 | W13: 1 | X13: V | Y13: V | AA13: =D13*$D$2+F13*$F$2+H13*$H$2+I13*$I$2+J13*$J$2+L13*$L$2+M13*$M$2+O13*$O$2+P13*$P$2+Q13*$Q$2+R13*$R$2+T13*$T$2+U13*$U$2+V13*$V$2-5*Z13 -> 91.395 | AD13: Diven Dechal Jatiputra | AE13: =IF(COUNTIF(A:A, AD13)>0, "✓", "") -> ✓ | AF13: Andreas Leeb | AG13: =IF(COUNTIF($A:$A, AF13)>0, "✓", "") -> ✓
A14: Lise ZHENG | B14: f11402009 | C14: Cyber Punk | D14: 83 | E14: 1 | F14: 90 | G14: 1 | H14: 0 | I14: 92 | J14: 88 | K14: 1 | L14: 92 | M14: 0 | N14: 1 | O14: 88 | P14: {=_xlfn.XLOOKUP($B14, 'W12 paper end'!$C:$C, 'W12 paper end'!$L:$L, "0")} -> 90 | Q14: {=_xlfn.XLOOKUP($B14, 'W13 paper end'!$C:$C, 'W13 paper end'!$L:$L, "0")} -> 89 | R14: {=_xlfn.XLOOKUP($B14, 'W14 paper end'!$C:$C, 'W14 paper end'!$K:$K, "0")} -> 89 | S14: 1 | T14: 92 | U14: 90 | V14: 91 | W14: 1 | AA14: =D14*$D$2+F14*$F$2+H14*$H$2+I14*$I$2+J14*$J$2+L14*$L$2+M14*$M$2+O14*$O$2+P14*$P$2+Q14*$Q$2+R14*$R$2+T14*$T$2+U14*$U$2+V14*$V$2-5*Z14 -> 78.745 | AD14: Adam Pach | AE14: =IF(COUNTIF(A:A, AD14)>0, "✓", "") -> ✓ | AF14: 柯議翔 | AG14: =IF(COUNTIF($A:$A, AF14)>0, "✓", "") -> ✓
A15: 柯議翔 | B15: M11407319 | C15: Cyber Punk | D15: 83 | E15: 1 | F15: 90 | G15: 1 | H15: 100 | I15: 92 | J15: 86 | K15: 1 | L15: 92 | M15: {=_xlfn.XLOOKUP($A15, 'Camping Simulation'!$B:$B, 'Camping Simulation'!$K:$K, "X")} -> 90 | N15: 1 | O15: 88 | P15: {=_xlfn.XLOOKUP($B15, 'W12 paper end'!$C:$C, 'W12 paper end'!$L:$L, "0")} -> 92 | Q15: {=_xlfn.XLOOKUP($B15, 'W13 paper end'!$C:$C, 'W13 paper end'!$L:$L, "0")} -> 94 | R15: {=_xlfn.XLOOKUP($B15, 'W14 paper end'!$C:$C, 'W14 paper end'!$K:$K, "0")} -> 90 | S15: 1 | T15: 92 | U15: 93 | V15: 91 | W15: 1 | AA15: =D15*$D$2+F15*$F$2+H15*$H$2+I15*$I$2+J15*$J$2+L15*$L$2+M15*$M$2+O15*$O$2+P15*$P$2+Q15*$Q$2+R15*$R$2+T15*$T$2+U15*$U$2+V15*$V$2-5*Z15 -> 91 | AD15: 許詠翔 | AE15: =IF(COUNTIF(A:A, AD15)>0, "✓", "") -> ✓ | AF15: Mikhael | AG15: =IF(COUNTIF($A:$A, AF15)>0, "✓", "")
A16: 盛爾君 | B16: M11407501 | C16: Cyber Punk | D16: 83 | E16: 1 | F16: 90 | G16: 1 | H16: 100 | I16: 92 | J16: 87 | K16: 1 | L16: 92 | M16: {=_xlfn.XLOOKUP($A16, 'Camping Simulation'!$B:$B, 'Camping Simulation'!$K:$K, "X")} -> 88 | N16: 1 | O16: 88 | P16: {=_xlfn.XLOOKUP($B16, 'W12 paper end'!$C:$C, 'W12 paper end'!$L:$L, "0")} -> 90 | Q16: {=_xlfn.XLOOKUP($B16, 'W13 paper end'!$C:$C, 'W13 paper end'!$L:$L, "0")} -> 89 | R16: {=_xlfn.XLOOKUP($B16, 'W14 paper end'!$C:$C, 'W14 paper end'!$K:$K, "0")} -> 89 | S16: 1 | T16: 92 | U16: 88 | V16: 89 | W16: 1 | AA16: =D16*$D$2+F16*$F$2+H16*$H$2+I16*$I$2+J16*$J$2+L16*$L$2+M16*$M$2+O16*$O$2+P16*$P$2+Q16*$Q$2+R16*$R$2+T16*$T$2+U16*$U$2+V16*$V$2-5*Z16 -> 90.395 | AD16: GIRARD Jules | AE16: =IF(COUNTIF(A:A, AD16)>0, "✓", "") | AF16: Lucas Metzger | AG16: =IF(COUNTIF($A:$A, AF16)>0, "✓", "") -> ✓
A17: 許詠翔 | B17: M11407502 | C17: Cyber Punk | D17: 83 | E17: 1 | F17: 90 | G17: 1 | H17: 100 | I17: 92 | J17: 90 | K17: 1 | L17: 92 | M17: {=_xlfn.XLOOKUP($A17, 'Camping Simulation'!$B:$B, 'Camping Simulation'!$K:$K, "X")} -> 92 | N17: 1 | O17: 88 | P17: {=_xlfn.XLOOKUP($B17, 'W12 paper end'!$C:$C, 'W12 paper end'!$L:$L, "0")} -> 94 | Q17: {=_xlfn.XLOOKUP($B17, 'W13 paper end'!$C:$C, 'W13 paper end'!$L:$L, "0")} -> 92 | R17: {=_xlfn.XLOOKUP($B17, 'W14 paper end'!$C:$C, 'W14 paper end'!$K:$K, "0")} -> 92 | S17: 1 | T17: 92 | U17: 92 | V17: 92 | W17: 1 | AA17: =D17*$D$2+F17*$F$2+H17*$H$2+I17*$I$2+J17*$J$2+L17*$L$2+M17*$M$2+O17*$O$2+P17*$P$2+Q17*$Q$2+R17*$R$2+T17*$T$2+U17*$U$2+V17*$V$2-5*Z17 -> 91.18 | AD17: Saint Guilhem Walfroy | AE17: =IF(COUNTIF(A:A, AD17)>0, "✓", "") | AF17: 陳增勇 | AG17: =IF(COUNTIF($A:$A, AF17)>0, "✓", "")
A18: 龔效諄 | B18: M11407618 | C18: Cyber Punk | D18: 83 | E18: 1 | F18: 90 | G18: 1 | H18: 100 | I18: 92 | J18: 88 | K18: 1 | L18: 92 | M18: {=_xlfn.XLOOKUP($A18, 'Camping Simulation'!$B:$B, 'Camping Simulation'!$K:$K, "X")} -> 92 | N18: 1 | O18: 88 | P18: {=_xlfn.XLOOKUP($B18, 'W12 paper end'!$C:$C, 'W12 paper end'!$L:$L, "0")} -> 91 | Q18: {=_xlfn.XLOOKUP($B18, 'W13 paper end'!$C:$C, 'W13 paper end'!$L:$L, "0")} -> 93 | R18: {=_xlfn.XLOOKUP($B18, 'W14 paper end'!$C:$C, 'W14 paper end'!$K:$K, "0")} -> 93 | S18: 1 | T18: 92 | U18: 90 | V18: 89 | W18: 1 | X18: V | AA18: =D18*$D$2+F18*$F$2+H18*$H$2+I18*$I$2+J18*$J$2+L18*$L$2+M18*$M$2+O18*$O$2+P18*$P$2+Q18*$Q$2+R18*$R$2+T18*$T$2+U18*$U$2+V18*$V$2-5*Z18 -> 90.985 | AD18: Puspa Ira Dewi Candra Wulan | AE18: =IF(COUNTIF(A:A, AD18)>0, "✓", "") | AF18: Rivaldo Yudha Pradana | AG18: =IF(COUNTIF($A:$A, AF18)>0, "✓", "") -> ✓
A19: Walfroy, Yves, Francois, SAINT-GUILHEM | B19: e11415031 | C19: Cyber Si0 | D19: 86 | E19: 1 | F19: 90 | G19: 1 | H19: 100 | I19: 92 | J19: 87 | K19: 1 | L19: 92.5 | M19: 0 | N19: 1 | O19: 81 | P19: {=_xlfn.XLOOKUP($B19, 'W12 paper end'!$C:$C, 'W12 paper end'!$L:$L, "0")} -> 90 | Q19: {=_xlfn.XLOOKUP($B19, 'W13 paper end'!$C:$C, 'W13 paper end'!$L:$L, "0")} -> 0 | R19: {=_xlfn.XLOOKUP($B19, 'W14 paper end'!$C:$C, 'W14 paper end'!$K:$K, "0")} -> 90 | S19: 1 | T19: 92 | U19: 87 | V19: 86 | W19: 1 | AA19: =D19*$D$2+F19*$F$2+H19*$H$2+I19*$I$2+J19*$J$2+L19*$L$2+M19*$M$2+O19*$O$2+P19*$P$2+Q19*$Q$2+R19*$R$2+T19*$T$2+U19*$U$2+V19*$V$2-5*Z19 -> 83.425 | AD19: Lise ZHENG | AE19: =IF(COUNTIF(A:A, AD19)>0, "✓", "") -> ✓ | AF19: 許詠翔 | AG19: =IF(COUNTIF($A:$A, AF19)>0, "✓", "") -> ✓
A20: DENNISON SOEDIBJO | B20: f11415018 | C20: Cyber Si0 | D20: 86 | E20: 1 | F20: 90 | G20: 1 | H20: 100 | I20: 92 | J20: 87 | K20: 1 | L20: 92.5 | M20: {=_xlfn.XLOOKUP($A20, 'Camping Simulation'!$B:$B, 'Camping Simulation'!$K:$K, "X")} -> 91 | N20: 1 | O20: 81 | P20: {=_xlfn.XLOOKUP($B20, 'W12 paper end'!$C:$C, 'W12 paper end'!$L:$L, "0")} -> 90 | Q20: {=_xlfn.XLOOKUP($B20, 'W13 paper end'!$C:$C, 'W13 paper end'!$L:$L, "0")} | R20: {=_xlfn.XLOOKUP($B20, 'W14 paper end'!$C:$C, 'W14 paper end'!$K:$K, "0")} | S20: 1 | T20: 92 | U20: 0 | V20: 0 | W20: 1 | AA20: =D20*$D$2+F20*$F$2+H20*$H$2+I20*$I$2+J20*$J$2+L20*$L$2+M20*$M$2+O20*$O$2+P20*$P$2+Q20*$Q$2+R20*$R$2+T20*$T$2+U20*$U$2+V20*$V$2-5*Z20 -> 76.42 | AD20: Alim Misbullah | AE20: =IF(COUNTIF(A:A, AD20)>0, "✓", "") -> ✓ | AF20: Benjamin Gillard | AG20: =IF(COUNTIF($A:$A, AF20)>0, "✓", "") -> ✓
A21: DIVEN DECHAL JATIPUTRA | B21: f11415019 | C21: Cyber Si0 | D21: 86 | E21: 1 | F21: 90 | G21: 1 | H21: 100 | I21: 92 | J21: 89 | K21: 1 | L21: 92.5 | M21: {=_xlfn.XLOOKUP($A21, 'Camping Simulation'!$B:$B, 'Camping Simulation'!$K:$K, "X")} -> 89 | N21: 1 | O21: 81 | P21: {=_xlfn.XLOOKUP($B21, 'W12 paper end'!$C:$C, 'W12 paper end'!$L:$L, "0")} -> 91 | Q21: {=_xlfn.XLOOKUP($B21, 'W13 paper end'!$C:$C, 'W13 paper end'!$L:$L, "0")} -> 93 | R21: {=_xlfn.XLOOKUP($B21, 'W14 paper end'!$C:$C, 'W14 paper end'!$K:$K, "0")} -> 92 | S21: 1 | T21: 92 | U21: 0 | V21: 92 | W21: 1 | AA21: =D21*$D$2+F21*$F$2+H21*$H$2+I21*$I$2+J21*$J$2+L21*$L$2+M21*$M$2+O21*$O$2+P21*$P$2+Q21*$Q$2+R21*$R$2+T21*$T$2+U21*$U$2+V21*$V$2-5*Z21 -> 88 | AD21: Lindeperg Ugo | AE21: =IF(COUNTIF(A:A, AD21)>0, "✓", "") | AF21: Aurelio Naufal Effendy | AG21: =IF(COUNTIF($A:$A, AF21)>0, "✓", "") -> ✓
A22: JOSHUA PUTRA PRATAMA | B22: f11415027 | C22: Cyber Si0 | D22: 86 | E22: 1 | F22: 90 | G22: 1 | H22: 100 | I22: 92 | J22: 92 | K22: 1 | L22: 92.5 | M22: {=_xlfn.XLOOKUP($A22, 'Camping Simulation'!$B:$B, 'Camping Simulation'!$K:$K, "X")} -> 92 | N22: 1 | O22: 81 | P22: {=_xlfn.XLOOKUP($B22, 'W12 paper end'!$C:$C, 'W12 paper end'!$L:$L, "0")} -> 92 | Q22: {=_xlfn.XLOOKUP($B22, 'W13 paper end'!$C:$C, 'W13 paper end'!$L:$L, "0")} -> 92 | R22: {=_xlfn.XLOOKUP($B22, 'W14 paper end'!$C:$C, 'W14 paper end'!$K:$K, "0")} -> 93 | S22: 1 | T22: 92 | U22: 93 | V22: 93 | W22: 1 | AA22: =D22*$D$2+F22*$F$2+H22*$H$2+I22*$I$2+J22*$J$2+L22*$L$2+M22*$M$2+O22*$O$2+P22*$P$2+Q22*$Q$2+R22*$R$2+T22*$T$2+U22*$U$2+V22*$V$2-5*Z22 -> 90.49 | AD22: Laina Farsiah | AE22: =IF(COUNTIF(A:A, AD22)>0, "✓", "") -> ✓ | AF22: Jules GIRARD | AG22: =IF(COUNTIF($A:$A, AF22)>0, "✓", "") -> ✓
A23: Rivaldo Yudha Pradana | B23: M11407804 | C23: Cyber Si0 | D23: 86 | E23: 1 | F23: 90 | G23: 1 | H23: 100 | I23: 92 | J23: 92 | K23: 1 | L23: 92.5 | M23: {=_xlfn.XLOOKUP($A23, 'Camping Simulation'!$B:$B, 'Camping Simulation'!$K:$K, "X")} -> 91 | N23: 1 | O23: 81 | P23: {=_xlfn.XLOOKUP($B23, 'W12 paper end'!$C:$C, 'W12 paper end'!$L:$L, "0")} -> 93 | Q23: {=_xlfn.XLOOKUP($B23, 'W13 paper end'!$C:$C, 'W13 paper end'!$L:$L, "0")} -> 92 | R23: {=_xlfn.XLOOKUP($B23, 'W14 paper end'!$C:$C, 'W14 paper end'!$K:$K, "0")} -> 93 | S23: 1 | T23: 92 | U23: 93 | V23: 93 | W23: 1 | AA23: =D23*$D$2+F23*$F$2+H23*$H$2+I23*$I$2+J23*$J$2+L23*$L$2+M23*$M$2+O23*$O$2+P23*$P$2+Q23*$Q$2+R23*$R$2+T23*$T$2+U23*$U$2+V23*$V$2-5*Z23 -> 90.52 | AD23: 葉人瑋 | AE23: =IF(COUNTIF(A:A, AD23)>0, "✓", "") -> ✓ | AF23: 盛爾君 | AG23: =IF(COUNTIF($A:$A, AF23)>0, "✓", "") -> ✓
A24: MIKHAEL GERSON SILAEN | B24: m11407809 | C24: Cyber Si0 | D24: 86 | E24: 1 | F24: 90 | G24: 1 | H24: 100 | I24: 92 | J24: 91 | K24: 1 | L24: 92.5 | M24: {=_xlfn.XLOOKUP($A24, 'Camping Simulation'!$B:$B, 'Camping Simulation'!$K:$K, "X")} -> 92 | N24: 1 | O24: 81 | P24: {=_xlfn.XLOOKUP($B24, 'W12 paper end'!$C:$C, 'W12 paper end'!$L:$L, "0")} -> 92 | Q24: {=_xlfn.XLOOKUP($B24, 'W13 paper end'!$C:$C, 'W13 paper end'!$L:$L, "0")} -> 91 | R24: {=_xlfn.XLOOKUP($B24, 'W14 paper end'!$C:$C, 'W14 paper end'!$K:$K, "0")} -> 91 | S24: 1 | T24: 92 | U24: 93 | V24: 93 | W24: 1 | AA24: =D24*$D$2+F24*$F$2+H24*$H$2+I24*$I$2+J24*$J$2+L24*$L$2+M24*$M$2+O24*$O$2+P24*$P$2+Q24*$Q$2+R24*$R$2+T24*$T$2+U24*$U$2+V24*$V$2-5*Z24 -> 90.33 | AD24: Rivaldo Yudha Pradana | AE24: =IF(COUNTIF(A:A, AD24)>0, "✓", "") -> ✓ | AF24: Adam Pach | AG24: =IF(COUNTIF($A:$A, AF24)>0, "✓", "") -> ✓
A25: Peter Jonathan Kuhn | B25: e11415021 | C25: European Avalanche | D25: 90 | E25: 1 | F25: 84 | G25: 1 | H25: 100 | I25: 92 | J25: 92 | K25: 1 | L25: 91 | M25: 0 | N25: 1 | O25: 90 | P25: {=_xlfn.XLOOKUP($B25, 'W12 paper end'!$C:$C, 'W12 paper end'!$L:$L, "0")} -> 89 | Q25: {=_xlfn.XLOOKUP($B25, 'W13 paper end'!$C:$C, 'W13 paper end'!$L:$L, "0")} -> 0 | R25: {=_xlfn.XLOOKUP($B25, 'W14 paper end'!$C:$C, 'W14 paper end'!$K:$K, "0")} -> 88 | S25: 1 | T25: 92 | U25: 91 | V25: 92 | W25: 1 | X25: V | AA25: =D25*$D$2+F25*$F$2+H25*$H$2+I25*$I$2+J25*$J$2+L25*$L$2+M25*$M$2+O25*$O$2+P25*$P$2+Q25*$Q$2+R25*$R$2+T25*$T$2+U25*$U$2+V25*$V$2-5*Z25 -> 84.605 | AD25: Andreas Leeb | AE25: =IF(COUNTIF(A:A, AD25)>0, "✓", "") -> ✓ | AF25: Ugo LINDEPERG | AG25: =IF(COUNTIF($A:$A, AF25)>0, "✓", "")
A26: Ayman Rabih Kallouz | B26: e11415023 | C26: European Avalanche | D26: 90 | E26: 1 | F26: 84 | G26: 1 | H26: 100 | I26: 92 | J26: 88 | K26: 1 | L26: 91 | M26: 0 | N26: 1 | O26: 90 | P26: {=_xlfn.XLOOKUP($B26, 'W12 paper end'!$C:$C, 'W12 paper end'!$L:$L, "0")} -> 89 | Q26: {=_xlfn.XLOOKUP($B26, 'W13 paper end'!$C:$C, 'W13 paper end'!$L:$L, "0")} -> 88 | R26: {=_xlfn.XLOOKUP($B26, 'W14 paper end'!$C:$C, 'W14 paper end'!$K:$K, "0")} -> 90 | S26: 1 | T26: 92 | U26: 92 | V26: 92 | W26: 1 | AA26: =D26*$D$2+F26*$F$2+H26*$H$2+I26*$I$2+J26*$J$2+L26*$L$2+M26*$M$2+O26*$O$2+P26*$P$2+Q26*$Q$2+R26*$R$2+T26*$T$2+U26*$U$2+V26*$V$2-5*Z26 -> 89.09 | AD26: Aurelio Naufal Effendy | AE26: =IF(COUNTIF(A:A, AD26)>0, "✓", "") -> ✓ | AF26: 柯議翔 | AG26: =IF(COUNTIF($A:$A, AF26)>0, "✓", "") -> ✓
A27: Andreas Leeb | B27: e11415025 | C27: European Avalanche | D27: 90 | E27: 1 | F27: 84 | G27: 1 | H27: 100 | I27: 92 | J27: 90 | K27: 1 | L27: 91 | M27: {=_xlfn.XLOOKUP($A27, 'Camping Simulation'!$B:$B, 'Camping Simulation'!$K:$K, "X")} -> 87 | N27: 1 | O27: 90 | P27: {=_xlfn.XLOOKUP($B27, 'W12 paper end'!$C:$C, 'W12 paper end'!$L:$L, "0")} -> 89 | Q27: {=_xlfn.XLOOKUP($B27, 'W13 paper end'!$C:$C, 'W13 paper end'!$L:$L, "0")} -> 87 | R27: {=_xlfn.XLOOKUP($B27, 'W14 paper end'!$C:$C, 'W14 paper end'!$K:$K, "0")} -> 89 | S27: 1 | T27: 92 | U27: 90 | V27: 0 | W27: 1 | AA27: =D27*$D$2+F27*$F$2+H27*$H$2+I27*$I$2+J27*$J$2+L27*$L$2+M27*$M$2+O27*$O$2+P27*$P$2+Q27*$Q$2+R27*$R$2+T27*$T$2+U27*$U$2+V27*$V$2-5*Z27 -> 88.4 | AD27: Danis Putra Perdana | AE27: =IF(COUNTIF(A:A, AD27)>0, "✓", "") -> ✓ | AF27: 張惟凱 | AG27: =IF(COUNTIF($A:$A, AF27)>0, "✓", "") -> ✓
A28: Adam Pach | B28: e11415030 | C28: European Avalanche | D28: 90 | E28: 1 | F28: 84 | G28: 1 | H28: 100 | I28: 92 | J28: 88 | K28: 1 | L28: 91 | M28: {=_xlfn.XLOOKUP($A28, 'Camping Simulation'!$B:$B, 'Camping Simulation'!$K:$K, "X")} -> 89 | N28: 1 | O28: 90 | P28: {=_xlfn.XLOOKUP($B28, 'W12 paper end'!$C:$C, 'W12 paper end'!$L:$L, "0")} -> 90 | Q28: {=_xlfn.XLOOKUP($B28, 'W13 paper end'!$C:$C, 'W13 paper end'!$L:$L, "0")} -> 88 | R28: {=_xlfn.XLOOKUP($B28, 'W14 paper end'!$C:$C, 'W14 paper end'!$K:$K, "0")} -> 92 | S28: 1 | T28: 92 | U28: 0 | V28: 89 | W28: 1 | AA28: =D28*$D$2+F28*$F$2+H28*$H$2+I28*$I$2+J28*$J$2+L28*$L$2+M28*$M$2+O28*$O$2+P28*$P$2+Q28*$Q$2+R28*$R$2+T28*$T$2+U28*$U$2+V28*$V$2-5*Z28 -> 88.645 | AD28: Oriiana Nedzelska | AE28: =IF(COUNTIF(A:A, AD28)>0, "✓", "") -> ✓ | AF28: 吳永保 | AG28: =IF(COUNTIF($A:$A, AF28)>0, "✓", "") -> ✓
A29: Bernardo Cavalcante Vieira de Andrade | B29: e11423008 | C29: European Avalanche | D29: 90 | E29: 1 | F29: 84 | G29: 1 | H29: 100 | I29: 92 | J29: 87 | K29: 1 | L29: 91 | M29: 0 | N29: 1 | O29: 90 | P29: {=_xlfn.XLOOKUP($B29, 'W12 paper end'!$C:$C, 'W12 paper end'!$L:$L, "0")} -> 0 | Q29: {=_xlfn.XLOOKUP($B29, 'W13 paper end'!$C:$C, 'W13 paper end'!$L:$L, "0")} -> 90 | R29: {=_xlfn.XLOOKUP($B29, 'W14 paper end'!$C:$C, 'W14 paper end'!$K:$K, "0")} -> 94 | S29: 1 | T29: 92 | U29: 92 | V29: 0 | W29: 1 | AA29: =D29*$D$2+F29*$F$2+H29*$H$2+I29*$I$2+J29*$J$2+L29*$L$2+M29*$M$2+O29*$O$2+P29*$P$2+Q29*$Q$2+R29*$R$2+T29*$T$2+U29*$U$2+V29*$V$2-5*Z29 -> 82.63 | AD29: 盛爾君 | AE29: =IF(COUNTIF(A:A, AD29)>0, "✓", "") -> ✓ | AF29: 蔡哲維 | AG29: =IF(COUNTIF($A:$A, AF29)>0, "✓", "") -> ✓
A30: Lucas Metzger | B30: f11415020 | C30: European Avalanche | D30: 90 | E30: 1 | F30: 84 | G30: 1 | H30: 100 | I30: 92 | J30: 87 | K30: 1 | L30: 91 | M30: {=_xlfn.XLOOKUP($A30, 'Camping Simulation'!$B:$B, 'Camping Simulation'!$K:$K, "X")} -> 87 | N30: 1 | O30: 90 | P30: {=_xlfn.XLOOKUP($B30, 'W12 paper end'!$C:$C, 'W12 paper end'!$L:$L, "0")} -> 88 | Q30: {=_xlfn.XLOOKUP($B30, 'W13 paper end'!$C:$C, 'W13 paper end'!$L:$L, "0")} -> 88 | R30: {=_xlfn.XLOOKUP(A30, 'W14 paper end'!B:B, 'W14 paper end'!K:K, "X")} -> 87 | S30: 1 | T30: 92 | U30: 90 | V30: 91 | W30: 1 | AA30: =D30*$D$2+F30*$F$2+H30*$H$2+I30*$I$2+J30*$J$2+L30*$L$2+M30*$M$2+O30*$O$2+P30*$P$2+Q30*$Q$2+R30*$R$2+T30*$T$2+U30*$U$2+V30*$V$2-5*Z30 -> 90.545 | AD30: 洪粲鈞 | AE30: =IF(COUNTIF(A:A, AD30)>0, "✓", "") -> ✓ | AF30: Joshua Putra Pratama | AG30: =IF(COUNTIF($A:$A, AF30)>0, "✓", "") -> ✓
A31: ITSUKI KURIYAMA | B31: F11415005 | C31: GPT+ | D31: 83 | E31: 1 | F31: 88 | G31: 1 | H31: 100 | I31: 91 | J31: 0 | K31: 1 | L31: 90 | M31: 0 | N31: 1 | O31: 78 | P31: {=_xlfn.XLOOKUP($B31, 'W12 paper end'!$C:$C, 'W12 paper end'!$L:$L, "0")} -> 94 | Q31: {=_xlfn.XLOOKUP($B31, 'W13 paper end'!$C:$C, 'W13 paper end'!$L:$L, "0")} -> 93 | R31: {=_xlfn.XLOOKUP(A31, 'W14 paper end'!B:B, 'W14 paper end'!K:K, "X")} -> 92 | S31: 1 | T31: 91 | U31: 92 | V31: 92 | W31: 1 | X31: V | AA31: =D31*$D$2+F31*$F$2+H31*$H$2+I31*$I$2+J31*$J$2+L31*$L$2+M31*$M$2+O31*$O$2+P31*$P$2+Q31*$Q$2+R31*$R$2+T31*$T$2+U31*$U$2+V31*$V$2-5*Z31 -> 86.39 | AD31: Joshua Putra Pratama | AE31: =IF(COUNTIF(A:A, AD31)>0, "✓", "") -> ✓ | AF31: Ayman Kallouz | AG31: =IF(COUNTIF($A:$A, AF31)>0, "✓", "")
A32: 祖祥恩 | B32: M11307310 | C32: GPT+ | D32: 83 | E32: 1 | F32: 88 | G32: 1 | H32: 100 | I32: 91 | J32: 85 | K32: 1 | L32: 90 | M32: {=_xlfn.XLOOKUP($A32, 'Camping Simulation'!$B:$B, 'Camping Simulation'!$K:$K, "X")} -> 87 | N32: 1 | O32: 78 | P32: {=_xlfn.XLOOKUP($B32, 'W12 paper end'!$C:$C, 'W12 paper end'!$L:$L, "0")} -> 90 | Q32: {=_xlfn.XLOOKUP($B32, 'W13 paper end'!$C:$C, 'W13 paper end'!$L:$L, "0")} -> 90 | R32: {=_xlfn.XLOOKUP(A32, 'W14 paper end'!B:B, 'W14 paper end'!K:K, "X")} -> 92 | S32: 1 | T32: 91 | U32: 91 | V32: 90 | W32: 1 | AA32: =D32*$D$2+F32*$F$2+H32*$H$2+I32*$I$2+J32*$J$2+L32*$L$2+M32*$M$2+O32*$O$2+P32*$P$2+Q32*$Q$2+R32*$R$2+T32*$T$2+U32*$U$2+V32*$V$2-5*Z32 -> 88.555 | AD32: 黃文良 | AE32: =IF(COUNTIF(A:A, AD32)>0, "✓", "") -> ✓ | AF32: 洪粲鈞 | AG32: =IF(COUNTIF($A:$A, AF32)>0, "✓", "") -> ✓
A33: 葉人瑋 | B33: m11407437 | C33: GPT+ | D33: 83 | E33: 1 | F33: 88 | G33: 1 | H33: 100 | I33: 91 | J33: 85 | K33: 1 | L33: 90 | M33: {=_xlfn.XLOOKUP($A33, 'Camping Simulation'!$B:$B, 'Camping Simulation'!$K:$K, "X")} -> 89 | N33: 1 | O33: 78 | P33: {=_xlfn.XLOOKUP($B33, 'W12 paper end'!$C:$C, 'W12 paper end'!$L:$L, "0")} -> 90 | Q33: {=_xlfn.XLOOKUP($B33, 'W13 paper end'!$C:$C, 'W13 paper end'!$L:$L, "0")} -> 89 | R33: {=_xlfn.XLOOKUP($B33, 'W14 paper end'!$C:$C, 'W14 paper end'!$K:$K, "0")} -> 90 | S33: 1 | T33: 91 | U33: 85 | V33: 0 | W33: 1 | AA33: =D33*$D$2+F33*$F$2+H33*$H$2+I33*$I$2+J33*$J$2+L33*$L$2+M33*$M$2+O33*$O$2+P33*$P$2+Q33*$Q$2+R33*$R$2+T33*$T$2+U33*$U$2+V33*$V$2-5*Z33 -> 86.045 | AD33: 張惟凱 | AE33: =IF(COUNTIF(A:A, AD33)>0, "✓", "") -> ✓ | AF33: Diven Dechal Jatiputra | AG33: =IF(COUNTIF($A:$A, AF33)>0, "✓", "") -> ✓
A34: 蔡哲維 | B34: m11407524 | C34: GPT+ | D34: 83 | E34: 1 | F34: 88 | G34: 1 | H34: 100 | I34: 91 | J34: 0 | K34: 1 | L34: 90 | M34: 0 | N34: 1 | O34: 78 | P34: {=_xlfn.XLOOKUP($B34, 'W12 paper end'!$C:$C, 'W12 paper end'!$L:$L, "0")} -> 90 | Q34: {=_xlfn.XLOOKUP($B34, 'W13 paper end'!$C:$C, 'W13 paper end'!$L:$L, "0")} -> 89 | R34: {=_xlfn.XLOOKUP($B34, 'W14 paper end'!$C:$C, 'W14 paper end'!$K:$K, "0")} -> 90 | S34: 1 | T34: 91 | U34: 0 | V34: 87 | W34: 1 | AA34: =D34*$D$2+F34*$F$2+H34*$H$2+I34*$I$2+J34*$J$2+L34*$L$2+M34*$M$2+O34*$O$2+P34*$P$2+Q34*$Q$2+R34*$R$2+T34*$T$2+U34*$U$2+V34*$V$2-5*Z34 -> 83.465 | AD34: 胡承學 | AE34: =IF(COUNTIF(A:A, AD34)>0, "✓", "") -> ✓ | AF34: 黃文良 | AG34: =IF(COUNTIF($A:$A, AF34)>0, "✓", "") -> ✓
A35: 陳增勇 | B35: B11007106 | C35: Insect | D35: 92 | E35: 1 | F35: 94 | G35: 1 | H35: 100 | I35: 95 | J35: 88 | K35: 1 | L35: 83 | M35: {=_xlfn.XLOOKUP($A35, 'Camping Simulation'!$B:$B, 'Camping Simulation'!$K:$K, "X")} -> 92 | N35: 1 | O35: 82 | P35: {=_xlfn.XLOOKUP($B35, 'W12 paper end'!$C:$C, 'W12 paper end'!$L:$L, "0")} -> 0 | Q35: {=_xlfn.XLOOKUP($B35, 'W13 paper end'!$C:$C, 'W13 paper end'!$L:$L, "0")} -> 91 | R35: {=_xlfn.XLOOKUP($B35, 'W14 paper end'!$C:$C, 'W14 paper end'!$K:$K, "0")} -> 90 | S35: 1 | T35: 95 | U35: 93 | V35: 92 | W35: 1 | AA35: =D35*$D$2+F35*$F$2+H35*$H$2+I35*$I$2+J35*$J$2+L35*$L$2+M35*$M$2+O35*$O$2+P35*$P$2+Q35*$Q$2+R35*$R$2+T35*$T$2+U35*$U$2+V35*$V$2-5*Z35 -> 86.735 | AD35: Dennison Soedibjo | AE35: =IF(COUNTIF(A:A, AD35)>0, "✓", "") -> ✓ | AF35: 楊晴安 | AG35: =IF(COUNTIF($A:$A, AF35)>0, "✓", "") -> ✓
A36: Laina Farsiah | B36: D11415802 | C36: Insect | D36: 92 | E36: 1 | F36: 94 | G36: 1 | H36: 100 | I36: 95 | J36: 95 | K36: 1 | L36: 83 | M36: {=_xlfn.XLOOKUP($A36, 'Camping Simulation'!$B:$B, 'Camping Simulation'!$K:$K, "X")} -> 94 | N36: 1 | O36: 82 | P36: {=_xlfn.XLOOKUP($B36, 'W12 paper end'!$C:$C, 'W12 paper end'!$L:$L, "0")} -> 92 | Q36: {=_xlfn.XLOOKUP($B36, 'W13 paper end'!$C:$C, 'W13 paper end'!$L:$L, "0")} -> 92 | R36: {=_xlfn.XLOOKUP($B36, 'W14 paper end'!$C:$C, 'W14 paper end'!$K:$K, "0")} -> 95 | S36: 1 | T36: 95 | U36: 94 | V36: 94 | W36: 1 | X36: V | AA36: =D36*$D$2+F36*$F$2+H36*$H$2+I36*$I$2+J36*$J$2+L36*$L$2+M36*$M$2+O36*$O$2+P36*$P$2+Q36*$Q$2+R36*$R$2+T36*$T$2+U36*$U$2+V36*$V$2-5*Z36 -> 91.82 | AD36: 吳永保 | AE36: =IF(COUNTIF(A:A, AD36)>0, "✓", "") -> ✓ | AF36: Bernardo Andrade | AG36: =IF(COUNTIF($A:$A, AF36)>0, "✓", "")
A37: Alim Misbullah | B37: D11415803 | C37: Insect | D37: 92 | E37: 1 | F37: 94 | G37: 1 | H37: 100 | I37: 95 | J37: 90 | K37: 1 | L37: 83 | M37: {=_xlfn.XLOOKUP($A37, 'Camping Simulation'!$B:$B, 'Camping Simulation'!$K:$K, "X")} -> 93 | N37: 1 | O37: 82 | P37: {=_xlfn.XLOOKUP($B37, 'W12 paper end'!$C:$C, 'W12 paper end'!$L:$L, "0")} -> 92 | Q37: {=_xlfn.XLOOKUP($B37, 'W13 paper end'!$C:$C, 'W13 paper end'!$L:$L, "0")} -> 90 | R37: {=_xlfn.XLOOKUP($B37, 'W14 paper end'!$C:$C, 'W14 paper end'!$K:$K, "0")} -> 91 | S37: 1 | T37: 95 | U37: 91 | V37: 93 | W37: 1 | X37: V | AA37: =D37*$D$2+F37*$F$2+H37*$H$2+I37*$I$2+J37*$J$2+L37*$L$2+M37*$M$2+O37*$O$2+P37*$P$2+Q37*$Q$2+R37*$R$2+T37*$T$2+U37*$U$2+V37*$V$2-5*Z37 -> 91.35 | AD37: 楊晴安 | AE37: =IF(COUNTIF(A:A, AD37)>0, "✓", "") -> ✓ | AF37: 胡承學 | AG37: =IF(COUNTIF($A:$A, AF37)>0, "✓", "") -> ✓
A38: Danis Putra Perdana | B38: D11415806 | C38: Insect | D38: 92 | E38: 1 | F38: 94 | G38: 1 | H38: 100 | I38: 95 | J38: 90 | K38: 1 | L38: 83 | M38: {=_xlfn.XLOOKUP($A38, 'Camping Simulation'!$B:$B, 'Camping Simulation'!$K:$K, "X")} -> 89 | N38: 1 | O38: 82 | P38: {=_xlfn.XLOOKUP($B38, 'W12 paper end'!$C:$C, 'W12 paper end'!$L:$L, "0")} -> 90 | Q38: {=_xlfn.XLOOKUP($B38, 'W13 paper end'!$C:$C, 'W13 paper end'!$L:$L, "0")} -> 91 | R38: {=_xlfn.XLOOKUP($B38, 'W14 paper end'!$C:$C, 'W14 paper end'!$K:$K, "0")} -> 90 | S38: 1 | T38: 95 | U38: 88 | V38: 89 | W38: 1 | X38: V | AA38: =D38*$D$2+F38*$F$2+H38*$H$2+I38*$I$2+J38*$J$2+L38*$L$2+M38*$M$2+O38*$O$2+P38*$P$2+Q38*$Q$2+R38*$R$2+T38*$T$2+U38*$U$2+V38*$V$2-5*Z38 -> 90.995 | AD38: Ituski Kuriyama | AE38: =IF(COUNTIF(A:A, AD38)>0, "✓", "") | AF38: Itsuki Kuriyama | AG38: =IF(COUNTIF($A:$A, AF38)>0, "✓", "") -> ✓
A39: Puspa Ira Dewi Candra Wulan | B39: D11415807 | C39: Insect | D39: 92 | E39: 1 | F39: 94 | G39: 1 | H39: 100 | I39: 95 | J39: 88 | K39: 1 | L39: 83 | M39: {=_xlfn.XLOOKUP($A39, 'Camping Simulation'!$B:$B, 'Camping Simulation'!$K:$K, "X")} -> 90 | N39: 1 | O39: 82 | P39: {=_xlfn.XLOOKUP($B39, 'W12 paper end'!$C:$C, 'W12 paper end'!$L:$L, "X")} -> 93 | Q39: {=_xlfn.XLOOKUP($B39, 'W13 paper end'!$C:$C, 'W13 paper end'!$L:$L, "0")} -> 91 | R39: {=_xlfn.XLOOKUP($B39, 'W14 paper end'!$C:$C, 'W14 paper end'!$K:$K, "0")} -> 89 | S39: 1 | T39: 95 | U39: 93 | V39: 91 | W39: 1 | X39: V | Y39: V | AA39: =D39*$D$2+F39*$F$2+H39*$H$2+I39*$I$2+J39*$J$2+L39*$L$2+M39*$M$2+O39*$O$2+P39*$P$2+Q39*$Q$2+R39*$R$2+T39*$T$2+U39*$U$2+V39*$V$2-5*Z39 -> 91.27
A40: Aurelio Naufal Effendy | B40: M11415802 | C40: Insect | D40: 92 | E40: 1 | F40: 94 | G40: 1 | H40: 100 | I40: 95 | J40: 90 | K40: 1 | L40: 83 | M40: {=_xlfn.XLOOKUP($A40, 'Camping Simulation'!$B:$B, 'Camping Simulation'!$K:$K, "X")} -> 95 | N40: 1 | O40: 82 | P40: {=_xlfn.XLOOKUP($B40, 'W12 paper end'!$C:$C, 'W12 paper end'!$L:$L, "X")} -> 92 | Q40: {=_xlfn.XLOOKUP($B40, 'W13 paper end'!$C:$C, 'W13 paper end'!$L:$L, "0")} -> 92 | R40: {=_xlfn.XLOOKUP($B40, 'W14 paper end'!$C:$C, 'W14 paper end'!$K:$K, "0")} -> 92 | S40: 1 | T40: 95 | U40: 90 | V40: 92 | W40: 1 | AA40: =D40*$D$2+F40*$F$2+H40*$H$2+I40*$I$2+J40*$J$2+L40*$L$2+M40*$M$2+O40*$O$2+P40*$P$2+Q40*$Q$2+R40*$R$2+T40*$T$2+U40*$U$2+V40*$V$2-5*Z40 -> 91.49
A41: 檢查 | D41: 100 | F41: 100 | H41: 100 | I41: 100 | J41: 100 | L41: 100 | M41: 100 | O41: 100 | P41: 100 | Q41: 100 | R41: 100 | T41: 100 | U41: 100 | V41: 100 | AA41: =D41*$D$2+F41*$F$2+H41*$H$2+I41*$I$2+J41*$J$2+L41*$L$2+M41*$M$2+O41*$O$2+P41*$P$2+Q41*$Q$2+R41*$R$2+T41*$T$2+U41*$U$2+V41*$V$2-5*Z41 -> 100

Sheet Professor ratings
A1: News Groups | B1: News(CTI report) | C1: News 成績 | D1: Cuckoo 順序 | E1: Cuckoo 成績 | F1: Cuckoo 有人沒到 | G1: Campaign | H1: Paper Presentation | I1: Paper Presentation 成績 | J1: Term Project
A2: beni | B2: SolarStorm Supply Chain Attack Timeline | C2: 90 | D2: beni (emotet) | E2: 84 | G2: 91 | H2: POIROT: Aligning Attack Behavior with Kernel Audit Records for Cyber Threat Hunting | I2: 85 | J2: 95
A3: European avalanche | B3: Taming Agentic Browsers: Vulnerability in Chrome Allowed Extensions to Hijack New Gemini Panel | C3: 90 | D3: European avalanche | E3: 84 | G3: 91 | H3: PalmTree: Learning an Assembly Language Model for Instruction Embedding | I3: 90 | J3: 92
A4: Cybersix | B4: Threat Assessment: BlackCat Ransomware | C4: 86 | D4: Cybersix (Agent Tesla) | E4: 90 | G4: 92.5 | H4: HOLMES: Real-Time APT Detection through Correlation of Suspicious Information Flows | I4: 81 | J4: 92
A5: insect | B5: LANDFALL: New Commercial-Grade Android Spyware in Exploit Chain Targeting Samsung Devices | C5: 92 | D5: insect | E5: 94 | G5: 83 | H5: You Are What You Do: Hunting Stealthy Malware via Data Provenance Analysis | I5: 82 | J5: 95
A6: ANTSLAB | B6: Fooling AI Agents: Web-Based Indirect Prompt Injection Observed in the Wild | C6: 86 | D6: ANTSLAB | E6: 94 | F6: 1位未到(黃文良) --> 報告者要到，否則會扣分唷，請他來跟我請假 (我沒有收到請假，所以扣5分唷) | G6: 93 | H6: SoK: Automated TTP Extraction from CTI Reports – Are We There Yet? | I6: 94 | J6: 95
A7: GPT+ | B7: Hack the Real Box: APT41’s New Subgroup Earth Longzhi | C7: 83 | D7: GPT+ | E7: 88 | F7: 1位請假(ITSUKI KURIYAMA) | G7: 90 | H7: Formalizing and Benchmarking Prompt Injection Attacks and Defenses | I7: 78 | J7: 91
A8: cyberpunk | B8: Model Namespace Reuse: An AI Supply-Chain Attack Exploiting Model Name Trust | C8: 83 | D8: cyberpunk (Agent Tesla) | E8: 90 | G8: 92 | H8: A Framework for Formalizing LLM Agent Security | I8: 88 | J8: 92

Sheet Cybersec
A1: 名字 | B1: 學號 | C1: 電子郵件信箱 | D1: 分組 | E1: Cybersec 2026 心得 | F1: B | G1: LLM
A2: 黃文良 | B2: B11107152 | C2: a0930747852@gmail.com | D2: ANTSLAB | E2: {=IF(ISNA(_xlfn.XLOOKUP(B2, H:H, H:H)), "", "✔")} | F2: =IF(ISNA(_xlfn.XLOOKUP(B2, H:H, H:H)), "", "✔")
A3: 胡承學 | B3: B11107153 | C3: B11107153@mail.ntust.edu.tw | D3: ANTSLAB | F3: =IF(ISNA(_xlfn.XLOOKUP(B3, H:H, H:H)), "", "✔")
A4: 吳永保 | B4: M11407005 | C4: M11407005@mail.ntust.edu.tw | D4: ANTSLAB | F4: =IF(ISNA(_xlfn.XLOOKUP(B4, H:H, H:H)), "", "✔")
A5: 楊晴安 | B5: M11407507 | C5: M11407507@mail.ntust.edu.tw | D5: ANTSLAB | E5: V | F5: =IF(ISNA(_xlfn.XLOOKUP(B5, H:H, H:H)), "", "✔")
A6: 洪粲鈞 | B6: M11407519 | C6: M11407519@mail.ntust.edu.tw | D6: ANTSLAB | E6: V | F6: =IF(ISNA(_xlfn.XLOOKUP(B6, H:H, H:H)), "", "✔")
A7: 張惟凱 | B7: M11407522 | C7: M11407522@mail.ntust.edu.tw | D7: ANTSLAB | E7: V | F7: =IF(ISNA(_xlfn.XLOOKUP(B7, H:H, H:H)), "", "✔")
A8: SU YADANA WIN | B8: d11415809 | C8: D11415809@mail.ntust.edu.tw | D8: BENI | E8: V | F8: =IF(ISNA(_xlfn.XLOOKUP(B8, H:H, H:H)), "", "✔")
A9: Jules GIRARD | B9: e11415022 | C9: jules.girard@etu.uca.fr | D9: BENI | F9: =IF(ISNA(_xlfn.XLOOKUP(B9, H:H, H:H)), "", "✔")
A10: Benjamin GILLARD | B10: e11415026 | C10: Benjamin.GILLARD@etu.uca.fr | D10: BENI | F10: =IF(ISNA(_xlfn.XLOOKUP(B10, H:H, H:H)), "", "✔")
A11: Ugo LINDEPERG | B11: e11415027 | C11: Ugo.LINDEPERG@etu.uca.fr | D11: BENI | F11: =IF(ISNA(_xlfn.XLOOKUP(B11, H:H, H:H)), "", "✔")
A12: Oriiana Nedzelska | B12: f11415026 | C12: oriiana.nedzelska@stud.hslu.ch | D12: BENI | E12: V | F12: =IF(ISNA(_xlfn.XLOOKUP(B12, H:H, H:H)), "", "✔") | G12: V
A13: Lise ZHENG | B13: f11402009 | C13: lise.zheng@etu.cyu.fr | D13: Cyber Punk | F13: =IF(ISNA(_xlfn.XLOOKUP(B13, H:H, H:H)), "", "✔")
A14: 柯議翔 | B14: M11407319 | C14: M11407319@mail.ntust.edu.tw | D14: Cyber Punk | F14: =IF(ISNA(_xlfn.XLOOKUP(B14, H:H, H:H)), "", "✔")
A15: 盛爾君 | B15: M11407501 | C15: M11407501@mail.ntust.edu.tw | D15: Cyber Punk | F15: =IF(ISNA(_xlfn.XLOOKUP(B15, H:H, H:H)), "", "✔")
A16: 許詠翔 | B16: M11407502 | C16: M11407502@mail.ntust.edu.tw | D16: Cyber Punk | F16: =IF(ISNA(_xlfn.XLOOKUP(B16, H:H, H:H)), "", "✔")
A17: 龔效諄 | B17: M11407618 | C17: M11407618@mail.ntust.edu.tw | D17: Cyber Punk | E17: V | F17: =IF(ISNA(_xlfn.XLOOKUP(B17, H:H, H:H)), "", "✔")
A18: Walfroy, Yves, Francois, SAINT-GUILHEM | B18: e11415031 | C18: walfroy.saint_guilhem@utt.fr | D18: Cyber Six | F18: =IF(ISNA(_xlfn.XLOOKUP(B18, H:H, H:H)), "", "✔")
A19: DENNISON SOEDIBJO | B19: f11415018 | C19: dennison.soedibjo@binus.ac.id | D19: Cyber Six | F19: =IF(ISNA(_xlfn.XLOOKUP(B19, H:H, H:H)), "", "✔")
A20: DIVEN DECHAL JATIPUTRA | B20: f11415019 | C20: diven.jatiputra@binus.ac.id | D20: Cyber Six | F20: =IF(ISNA(_xlfn.XLOOKUP(B20, H:H, H:H)), "", "✔")
A21: JOSHUA PUTRA PRATAMA | B21: f11415027 | C21: joshua.pratama@binus.ac.id | D21: Cyber Six | F21: =IF(ISNA(_xlfn.XLOOKUP(B21, H:H, H:H)), "", "✔")
A22: Rivaldo Yudha Pradana | B22: M11407804 | C22: M11407804@mail.ntust.edu.tw | D22: Cyber Six | F22: =IF(ISNA(_xlfn.XLOOKUP(B22, H:H, H:H)), "", "✔")
A23: MIKHAEL GERSON SILAEN | B23: m11407809 | C23: M11407809@mail.ntust.edu.tw | D23: Cyber Six | F23: =IF(ISNA(_xlfn.XLOOKUP(B23, H:H, H:H)), "", "✔")
A24: Peter Jonathan Kuhn | B24: e11415021 | C24: peter.kuhn@ost.ch | D24: European Avalanche | E24: V | F24: =IF(ISNA(_xlfn.XLOOKUP(B24, H:H, H:H)), "", "✔")
A25: Ayman Rabih Kallouz | B25: e11415023 | C25: ayman.kallouz@stud.tu-darmstadt.de | D25: European Avalanche | F25: =IF(ISNA(_xlfn.XLOOKUP(B25, H:H, H:H)), "", "✔")
A26: Andreas Leeb | B26: e11415025 | C26: k12215901@students.jku.at | D26: European Avalanche | F26: =IF(ISNA(_xlfn.XLOOKUP(B26, H:H, H:H)), "", "✔")
A27: Adam Pach | B27: e11415030 | C27: adam.pach.st@vsb.cz | D27: European Avalanche | F27: =IF(ISNA(_xlfn.XLOOKUP(B27, H:H, H:H)), "", "✔")
A28: Bernardo Cavalcante Vieira de Andrade | B28: e11423008 | C28: bernardo.d.andrade@tecnico.ulisboa.pt | D28: European Avalanche | F28: =IF(ISNA(_xlfn.XLOOKUP(B28, H:H, H:H)), "", "✔")
A29: Lucas Metzger | B29: f11415020 | C29: luc.metzger.24@lehre.mosbach.dhbw.de | D29: European Avalanche | F29: =IF(ISNA(_xlfn.XLOOKUP(B29, H:H, H:H)), "", "✔")
A30: ITSUKI KURIYAMA | B30: F11415005 | C30: b3122018@edu.kit.ac.jp | D30: GPT+ | E30: V | F30: =IF(ISNA(_xlfn.XLOOKUP(B30, H:H, H:H)), "", "✔")
A31: 祖祥恩 | B31: M11307310 | C31: M11307310@mail.ntust.edu.tw | D31: GPT+ | F31: =IF(ISNA(_xlfn.XLOOKUP(B31, H:H, H:H)), "", "✔")
A32: 葉人瑋 | B32: m11407437 | C32: M11407437@mail.ntust.edu.tw | D32: GPT+ | F32: =IF(ISNA(_xlfn.XLOOKUP(B32, H:H, H:H)), "", "✔")
A33: 蔡哲維 | B33: m11407524 | C33: M11407524@mail.ntust.edu.tw | D33: GPT+ | F33: =IF(ISNA(_xlfn.XLOOKUP(B33, H:H, H:H)), "", "✔")
A34: 陳增勇 | B34: B11007106 | C34: B11007106@mail.ntust.edu.tw | D34: Insect | F34: =IF(ISNA(_xlfn.XLOOKUP(B34, H:H, H:H)), "", "✔")
A35: Laina Farsiah | B35: D11415802 | C35: D11415802@mail.ntust.edu.tw | D35: Insect | E35: V | F35: =IF(ISNA(_xlfn.XLOOKUP(B35, H:H, H:H)), "", "✔")
A36: Alim Misbullah | B36: D11415803 | C36: D11415803@mail.ntust.edu.tw | D36: Insect | E36: V | F36: =IF(ISNA(_xlfn.XLOOKUP(B36, H:H, H:H)), "", "✔")
A37: Danis Putra Perdana | B37: D11415806 | C37: D11415806@mail.ntust.edu.tw | D37: Insect | E37: V | F37: =IF(ISNA(_xlfn.XLOOKUP(B37, H:H, H:H)), "", "✔")
A38: Puspa Ira Dewi Candra Wulan | B38: D11415807 | C38: D11415807@mail.ntust.edu.tw | D38: Insect | E38: V | G38: V
A39: Aurelio Naufal Effendy | B39: M11415802 | C39: M11415802@mail.ntust.edu.tw | D39: Insect | F39: {=IF(ISNA(_xlfn.XLOOKUP(B39, H:H, H:H)), "", "✔")}

Sheet Project Proposal Review Form 
A1: 時間戳記 | B1: Name | C1: Students ID | D1: Research Topic of this group | E1: Strengths / Pros (2 points) | F1: Suggestions for Improvement (2 points) | G1: Research Topic of this group 2 | H1: Strengths / Pros (2 points) | I1: Suggestions for Improvement (2 points) 2 | J1: Research Topic of this group 3 | K1: Strengths / Pros (2 points) 2 | L1: Suggestions for Improvement (2 points) 3 | M1: Research Topic of this group 4 | N1: Strengths / Pros (2 points) 3 | O1: Suggestions for Improvement (2 points) 4 | P1: Research Topic of this group 5 | Q1: Strengths / Pros (2 points) 4 | R1: Suggestions for Improvement (2 points) 5 | S1: Research Topic of this group 6 | T1: Strengths / Pros (2 points) 5 | U1: Suggestions for Improvement (2 points) 6 | V1: Research Topic of this group 7 | W1: Strengths / Pros (2 points) 6 | X1: Suggestions for Improvement (2 points) 7 | Y1: 第 1 欄
A2: 46141.482 | B2: Danis Putra Perdana | C2: D11415806 | D2: ML for detecting malware | E2: Using diverse neural network, big dataset | F2: Explain more clearly the research objective, Add another dataset that doesn't just have numeric array | G2: Network intrusion detection using RF classifiers | H2: Effective for FAR, using AI model | I2: You need search the strong novelty, try another method and compare the result | J2: Automated CTI report using mitre att&ck | K2: Comprehensive threat mapping, standardization and consistent analisys because use mitre att&ck | L2: Integrate with real time data, add risk priority | M2: Automated CTI analysis via multimodal | N2: Use multimodal, automated cti use LLM | O2: Make clear what multimodal you are mean, output too simple because you using LLM | P2: Mitre att&ck detection | Q2: Using graph based, can detect unseen technique with audit log | R2: Make clear what you're will make. search what is the novelty of your project, it's prof. huang published paper | S2: This is our team | T2: This is our team | U2: This is our team | V2: Hijacking technique: stealing s steam session | W2: Real case, real-world attack simulation | X2: Make new idea than just reproduce a case study, try to use another technique beside just hijacking | Y2: 89
A3: 46141.484 | B3: Laina Farsiah | C3: D11415802 | D3: The research focuses on classifying malware versus benign samples using t-SNE, with a comparison to a baseline LightGBM model. Overall, the topic is relevant and important in the field of cybersecurity. | E3: 1.The use of a large-scale dataset is a strong point, as it increases the reliability and generalizability of the results. 2.The comparison with a baseline model (LightGBM) provides a useful benchmark to evaluate the effectiveness of the proposed approach. | F3: 1.The study currently focuses on binary classification (malware vs. benign). It would be beneficial to consider a more fine-grained classification (e.g., different types of malware) to provide deeper insights and practical value. 2.Since t-SNE is primarily a dimensionality reduction and visualization technique, it would be helpful to clarify its role in the classification pipeline and justify why it improves performance compared to other feature extraction or dimensionality reduction methods. | G3: Enhanced Network Intrusion Detection Using Random Forest Classifier | H3: 1.The study addresses a critical problem in cybersecurity, particularly in detecting anomalies and potential network intrusions, which is highly relevant in today’s digital landscape. 2.The use of a Random Forest classifier is appropriate, as it is well-known for effectively handling high-dimensional features and improving classification performance. | I3: 1.The presentation mentions the use of two datasets; however, the rationale behind using both datasets is not clearly explained. It would be helpful to clarify whether they are used for comparison, validation, or improving model generalization. 2.The evaluation could be strengthened by providing more detailed performance analysis. | J3: Automated Mitre Att&ck Technique Classification from CTI Report using Transformer Models | K3: 1.The study effectively addresses a multi-label classification problem, which is highly relevant since CTI reports often involve multiple techniques simultaneously. 2.The incorporation of a two-level hierarchical structure is well-aligned with the MITRE ATT&CK framework and adds meaningful depth to the classification task. 3.The focus on long-tail techniques is valuable, as these are often underrepresented yet critical for improving real-world detection capabilities. | L3: 1.The methodology could be strengthened by providing more details on how the hierarchical relationships are modeled within the Transformer. 2.It would be beneficial to include a more comprehensive evaluation, such as comparisons with baseline models or an analysis of performance on rare (long-tail) classes to better demonstrate the effectiveness of the approach. | M3: Automated CTI Analysis Via Multimedia LLMs | N3: 1.The focus on inference optimization is valuable, as it directly impacts the efficiency and practicality of deploying LLM-based systems in real-world scenarios. 2.The use of local model hosting via Ollama is a strong point, particularly in terms of data privacy, cost control, and independence from external APIs. 3.The multimodal output enhances the capability of the system to perform more comprehensive CTI analysis. | O3: 1.The presentation could provide more technical details on the inference optimization techniques used (e.g., quantization, batching, or model selection) to better demonstrate the novelty and effectiveness of the approach. 2. Why do you have so early "conclusion"? This is still proposal presentation. | P3: Mitre Att&ck Technique Detection | Q3: 1.The use of SAGA (Synthetic Audit Log Generation) based on real-world cyber threat intelligence is a strong approach, as it helps address data scarcity while maintaining realistic attack patterns. 2.The incorporation of graph construction is a valuable design choice, as it can effectively capture relationships and dependencies between different attack techniques. | R3: 1.The title could be more specific and descriptive to better reflect the methodology and key contributions of the study (e.g., mentioning SAGA or graph-based techniques). 2.The methodology section could be further clarified, particularly regarding how the graph is constructed and utilized for detection, as well as how it improves performance compared to existing approaches. | S3: This my team | T3: This my team | U3: This my team | V3: Stealing a Steam Session: A Case Study on DPAPI and Browser Cookie Hijacking on Windows | W3: 1.The project presents a clear end-to-end demonstration, which helps illustrate the full attack workflow and makes the research more practical and understandable. 2.The demonstration of bypass techniques, particularly session hijacking, effectively highlights real-world security risks and increases the impact of the study. | X3: 1.It would be beneficial to discuss potential mitigation strategies or defenses in more detail. 2.So the work not only demonstrates the attack but also contributes to improving system security. | Y3: 90
A4: 46141.484 | B4: Ugo LINDEPERG | C4: E11415027 | D4: Use T-SNE to explore malware dataset | E4: -help human with complex situation (high dimensional data) -help non technical people to understand | F4: -Maybe 3d will be better than 2d to represent -Maybe its gonna be hard to have a accurancy as good as the actual AI | G4: Detect network intrusion with random forest classifiers | H4: -Feature importance ranking -High resistance to overfitting | I4: -Detection of zero-day vulnerabilities (by combining random forest with IDS maybe) -Implement model compression or dimensionality reduction model to be able to operate wire speed without dropping packets | J4: Its my group | K4: its my group | L4: its my group | M4: Analysis of CTI report with multimodal vision | N4: -Extraction of dark data because multimodal can perform OCR and visual reasoning -Context aware summary that correlates visual evidences with technical descriptions, this reduce the time an analyst spend pivoting between reading and analyzing | O4: -Maybe they will be visual hallucinations (diagrams for example), so they should implement cross modal verification, where the model need to find a textual reference in the report to confirm -Maybe hacker will try to use adversional perturbations to trick the vision model, maybe they need to integrate robustness training and specialized pre processing filter that clean the image of potential hidden noise | P4: Mitre attack technique detection | Q4: -It can give contextual awareness -Create a common language between the red teams and blue teams (MITRE framework) | R4: -Implement contextual correlation to avoid random alert and focus on the sequence of techniques -They can try to make the system able to remember the user historical baseline, to see when this user is deviating | S4: Explainable sequence based mitre attack technique detection from endpoint telemetry using AI and large language models | T4: -Contextual reasoning over event sequences -Built in natural language explainability | U4: -Implement a pre processing layer, to filter out noise and group related events -Use knowledge graphs to force the model to look up the official MITRE attack definitions and documemtation in real time | V4: Stealing a steam session | W4: -Real life problem -Very original topic | X4: -Try to generalize -Maybe its too specialized | Y4: 91
A5: 46141.485 | B5: Su Yadana Win | C5: D11415809 | D5: Use T-SNE to explore malware dataset | E5: Motivation is exapmple of tSNE, help non technical people to understand , , Convotional network and virtual network, maximize accuracy and large of model | F5: Outliers: Are there malware samples floating all alone? These might be "Zero-day" threats or highly obfuscated samples. Overlaps: Do two different families overlap? This suggests they share code or were created by the same threat actor. Benign vs. Malicious: Does the "Benign" cluster stay separate? If malware is overlapping with benign files, that's where false positives happen. | G5: Enhanced network intrusion detection using random forest classifiers on cicids dataset | H5: can perform features selection to identify the most important network flow features for detecting malicious activities such as flow duration, packet length, and inter-arrival time, can focus the detection task on DDoS and Brute force attacks, as these are common and high impact network threats. | I5: future, should Use SHAP (SHapley Additive exPlanations). In a real-world Security Operations Center (SOC), an analyst needs to know why the AI flagged a packet as "DDoS." SHAP provides a visual breakdown of which features (e.g., "Flow Duration," "Packet Length") pushed the model toward that decision. | J5: Automated MITRE ATTACK Technique and Classification from CTI Reports Using Transformer Models | K5: Our group | L5: Our group | M5: Automated CTI Analysis with multi model LLM | N5: it can be utilized RAG technology to ground analysis in official knowledge bases, ensuring extracted intelligence is accurately mapped to the MITRE attack framework with high tracebility. it can laverage LLMs to automatically identify and extract IoCs and Tatics and techniques and procedures (TTPs), transforminng manual workflows into efficient pipelines. | O5: add F1 score, in cybersecurity research, accuracy can be misleading, adding an F1 score shows it can be accounting for false positives which is a critical issue in threat intelligence. | P5: MITRE Attack techniques detection | Q5: can perform multi-class edge classification can transform isolated system audit logs into dynamic provenance graphs (Process, File, Network) which can be preserved the topological context of system activities. | R5: Should implement Temporal Semantic Reduction. Instead of mapping every single system call, group repetitive "benign" patterns into a single "macro-edge." This reduces the graph size and allows the GAT to focus on anomalous structural changes rather than volume. | S5: Explainable Sequence-based MITRE ATTACk Technique detection from endpoint telemetry using AI and Large Language Models | T5: can detects attacker behavior from endpoint logs and maps them to MITRE ATTACK techniques, can detect malicious activities from Windows/Sysmon logs, can predict AttACK techniques automatically | U5: Integrate SHAP (SHapley Additive exPlanations) or LIME between the AI Model and the LLM. Why: This allows you to feed the LLM the exact features that triggered the detection (e.g., "The model flagged this because the Entropy of the CommandLine was unusually high"). This makes the LLM’s explanation grounded in data, not just a hallucination of what looks "hackery." | V5: Stealing a Steam Session (A case study on DPAPI and Browser Cookie Hijacking on Windows) | W5: can reproduce the DPAPI+ Chrome cookie hijack on Steam inside a sandboxed Windows VM, can capture commands, screenshots, and intermediate artifacts so each step is reproducible, to produce a defender's checklist, and show that session hijacking defeats both passwords | X5: Even if you successfully use pypykatz to steal the session cookie, the cookie is now cryptographically "bound" to the user's specific hardware (TPM). to improve that, should demonstrate that the stolen cookie works on the victim's machine if re-imported, but fails on the attacker's machine because the hardware key is missing. This turns your project from a "scary hack" into a high-level discussion on hardware-root-of-trust.
A6: 46141.485 | B6: Benjamin Gillard | C6: E11415026 | D6: T-SNE to detect malware dataset | E6: - can be use on high dimensional data - they compare to other techniques and try to optimize the model to improve performance | F6: - test the generalization of the model on other dataset - | G6: Detect network intusion | H6: use a simple ia that is easy to understand (random forest) can handle a high dimentional | I6: train another ia to compare performance try there model on a real network | J6: Automated MITRE ATT&CK Technique Classification from CTI Reports using Transformer Models | K6: -- | L6: - | M6: multimodal vision to analyse cti report | N6: - traceability of the mapped MITRE ATT&CK framework - the possibility of using image to understand more information | O6: - try the model on real data - compare to other model | P6: MITRE ATT&CK techniques detection | Q6: - using graph to preserve the context - using Synthetic data to increase the number of data | R6: -try in real life scenario - comparison to other model | S6: explainable sequence-based MITRE ATT&CK technique detection from endpoint telemetry using AI and largelanguage models | T6: - do the MITRE ATT&CK classification from the logs - can be use in real time and on massive logs | U6: - try on a virtual machine to simulate real time information - use other logs like network or cross computer log to detect lateral movement | V6: Stealing a Steam Session | W6: documentation of every stage cross-platform | X6: explain other technique and why not using them try on other platform and not only steam
A7: 46141.486 | B7: Lucas Metzger | C7: F11415020 | D7: Visualizing EMBER: fast t‑SNE for malware feature exploration | E7: I am part of this group | F7: I am part of this group | G7: Enhanced network intrusion detection using random forest classifiers | H7: High performance metrics, low false alarm rate | I7: Challenge to avoid overfitting, project structure could be more precise | J7: Automated MITRE ATT&CK Technique Classification from CTI Reports using Transformer Models | K7: Using the latest MIRE ATT&CK taxonomy, solving the problems of current BERT-based approches | L7: Third research question is not specific enough, one benchmark for five models | M7: Automated CTI analysis via multimodal LLMs | N7: Multimodal LLMs becoming more relevant, modern LLM technique | O7: data could be too less for good machine learning results, golden dataset | P7: MITRE ATT&CK Technique detection | Q7: graph attention network (GAT), automated learning-based model capable of classifying raw system logs | R7: only 28 logs in total, source node type specificity | S7: Explainable sequence-based MITRE ATT&CK Technique detection from endpoint telemetry using AI and LLMs | T7: Using sequences instead of single log events, use LLM also as analyst assistant | U7: metrics maybe don't show the complete behavior, unclear Splunk data | V7: Stealing a Steam Session | W7: end-to-end-demo, novel approach | X7: pypykatz doesn't contain compiled binaries, key extraction
A8: 46141.488 | B8: 龔效諄 | C8: M11407618 | D8: visualizing EMBER : malware feature exploration | E8: use ML to analyze high dimension data、reducing dimensionally with PCA | F8: 1.loss of interpretability : the original feature of EMBER are inherently meaningful but after PCA will lost it's meangful 2.linearity limitation:PCA is a linear method but the malware features are always nonlinear combination. | G8: enhanced network instruction detection | H8: good performance with rf 、use of a realistic dataset | I8: maybe can include more kind of method and more threat categories | J8: automated mitre attack technique classification from CTI report | K8: compare with many version of BERT、analyze many kind of attack tactics | L8: improve evaluation strategy、 | M8: N/A | N8: N/A | O8: N/A | P8: mitre attack technique detection | Q8: effective contextual analysis via GAT 、structure provenance tracking | R8: synthetic data bias、computational complexity and scalability | S8: explainable sequence-based mitre attack technique detection | T8: strong justification for"sequence-based learning"、high quality data foundation | U8: feature engineering and inference latency、the gap between explainability and model logic | V8: stealing a stream session | W8: methodological rigor、comprehensive attack chain analysis | X8: didn't touch the modern defense evasion、lack of countermeasure depth
A9: 46141.488 | B9: Ayman Kallouz | C9: E11415023 | D9: I am part of this group | E9: / | F9: / | G9: Enhanced network intrusion detection using AI | H9: High performance metrics, low false positive rate | I9: 1. no time analysis, 2. only one week worth of data for one dataset | J9: MITRE Attack Classification | K9: 1. can save a lot of time for analyzing attacks, 2. solving current BERT challenges | L9: 1. some categories in the dataset could be underrepresented, 2. presentation was hard to follow | M9: automated cti analysis via multimodal LLMS | N9: 1.automated IoCs extraction makes it easy, 2. precise mitre attack mapping | O9: 1. confusing dataset usage, 2. may be hard to clean the data by hand and error prone | P9: Mitre Attack Technique detection | Q9: 1. combination of GAT and MLP classifier, 2. parsing raw data makes it easy to use the pipeline afterwards since it automatically processes it | R9: 1. only 28 logs, 2.reasons not clear why they use GAT instead of traditional networks | S9: Explainable sequence-based mitre attack technique detection from endpoint telemetry | T9: 1. makes log based analyzation easy, 2. usage of transformer models | U9: cant find any cons since the group seems to be very well prepared | V9: Stealing a Steam Session | W9: 1. demo showing, 2.well organized and already done | X9: 1. no AI project, 2. doing too detailed for a proposal
A10: 46141.488 | B10: GIRARD Jules | C10: E11415022 | D10: Malware clustering visualisation with tSNE | E10: Many architectures comparisons Big dataset with many data to improve models | F10: Add omparison with paper already publish datatset with pre extracted feature reduce possiblity to find new interesting features | G10: random forest based network intrusion dection system (IDS) | H10: Handles high dimensional traffic efficiently many features (41) | I10: the F1-score is most important metric and should be highlight more ctaegories for web-based attacks | J10: our group | K10: our group | L10: our group | M10: multimodal mitre attack report mapping | N10: Multimodal model with vision RAG technologies to build knowledge bases | O10: comparison with closed source model (Claude or GPT) and with chain-of-thought multi label vs unique label per sentence | P10: Mitre attack technique detection | Q10: aware of the topological context (provenance, graph) strong methodology with Graph Attention Network | R10: Find a dataset from a real attack if possible ? Performance comparaison (accurace, execution speed) | S10: LLM based explanation and IDS with endpoint telemetry | T10: sequence aware model with sliding window comparison with classical ML | U10: implement RAG technologies to improve detection patterns merge other information with these logs, like network information ? | V10: Stealing steam session | W10: modern technics (bypass 2FA) defender's checklist and recommendations | X10: full attack with initial access explain in detail the role of LSASS in this attack.
A11: 46141.488 | B11: peter kuhn | C11: E11415021 | D11: i am part of it | E11: best | F11: more compute necessary | G11: analyse DDoS Attaks | H11: high relevance, as DDoS is common. good overview of F1 score | I11: use more modern method then random forest. use more modern (9 year old) data | J11: interprete cti reports with transformers | K11: good monetary incentive; reading techincal reports is straining indeed | L11: very similar to one of the papers in the class; BERT is old, use Gemini, same company different name of current product | M11: multimodal LLM to enhance text comperhencion | N11: multimodal LLM are innovativ. different approch to self craft the dataset direktly form the web scraping. | O11: A lot of compute power will be needed. 512 token chunkning is too low for modern systems and images | P11: end to end TTP detection with GAT | Q11: usefull for the greater Cyber security community; they try to use the Graph Attention Network wich are applicable for the task, good choice | R11: only using syntetic data, sim to real gap might be too big to be usefull; no references for the GAT | S11: look at endpoints with llm | T11: cool approche with sequence learning and LLM; good to have a backup dataset. | U11: limit the objectiv to a smaller achivible goal, otherwise it will be too much work; no concrete idea with Ai transformer model they will use | V11: take over steam account on windows | W11: unique approch, to demo a proper attack; real cyber techinques used, no GenAI garbage needed | X11: do not use a VM, but a bare metal machine, more realistic; use more performant linguage then python, like C#
A12: 46141.488 | B12: Adam Pach | C12: E11415030 | D12: my group | E12: my group | F12: my group | G12: AI Network Attack detection | H12: 1. Comparing more models for higher accuracy 2. Good defined goal | I12: 1. Structure is poor 2. I did not understand the much the architecture | J12: Mitre Attack Classification | K12: 1. Interesting topic, could save a lot of time 2. I like the architecture of the Transformers | L12: 1. Lot of text in the presentation. There was lot of text and it was hard to understand it 2.Overall, I am not sure if the team understand the project | M12: Automated CTI via Multimodel | N12: 1. Good objectives 2. I like using Ollama so you can run models locally | O12: 1. Half of the group was impossible to understand 2.Confusing using of datasets | P12: Mitre Attack classification | Q12: 1. Architecture is already defined 2.I like using a raw data, easier to use for the end user | R12: 1. Small amount of logs 2. Bit confusing presentation | S12: Mitre attack and Techniques Mapping | T12: 1. Like the main objective. Team has a vision what they want to do 2. Using more AI approaches 3. Well defined architecture 4. LLM integration | U12: 1. Its hard to find something wrong, the team seams to be well prepared | V12: Stealing a Steam Session | W12: 1. Build a demo, so they will show us how it could be done 2. They know how the attack work and show it to us | X12: 1. Maybe for a proposal thet are going to much deep dive 2. Don't mention AI, I thought it must be part of project
A13: 46141.488 | B13: Puspa Ira Dewi Candra Wulan | C13: D11415807 | D13: Visualizing Ember to Malware Feature Exploration | E13: Applies multiple dimensionality reduction techniques (PCA, t-SNE, UMAP) to explore high dimensional malware feature space and reveal potential clustering patterns between benign and malicious samples | F13: Incorporate representation space analysis under distribution shift or obfuscation scenarios to evaluate feature robustness and boundary stability in malware detection | G13: Enhanced Network Intrusion detection using random forest classifier | H13: Random Forest effectively handles high dimensional and noisy network traffic data, while providing robust performance and reducing overfitting compared to single decision tree models. | I13: The work can be strengthened by addressing class imbalance and evaluating robustness under concept drift, evaluating cross-dataset generalization (training on one dataset and testing on another) to better assess model robustness. | J13: Automated MITRE ATT&CK technique Classification from CTI report using transformer models | K13: Transformer models effectively capture contextual semantics in CTI reports, enabling more accurate classification of MITRE ATT&CK techniques from unstructured threat intelligence text | L13: Can be strengthened by addressing multilabel complexity and label imbalance, as CTI reports often correspond to multiple ATT&CK techniques. Additionally, evaluating cross-source generalization and performance on unseen or evolving techniques would provide deeper insight into model robustness in realworld scenarios. | M13: Automated CTI analysis via multimodal | N13: The project presents a comprehensive end-to-end CTI analysis pipeline by integrating multimodal parsing, LLM based extraction, and RAG based grounding. This enables richer understanding of both textual and visual threat intelligence data while improving the accuracy and traceability of MITRE ATT&CK mapping | O13: Can be strengthened by evaluating robustness across modalities, particularly when visual or textual inputs are incomplete or noisy. Additionally, analyzing alignment between modalities and assessing how RAG grounding influences mapping accuracy and potential hallucination would provide deeper insight into system reliability | P13: MITRE ATT&CK Technique Detection | Q13: Leverages a graph based representation of system activity by constructing a heterogeneous provenance graph, enabling the modeling of complex relationships between entities and events. The use of Graph Attention Networks allows the model to capture structural dependencies and contextual interactions that are difficult to represent with traditional feature based approaches | R13: Can be strengthened by evaluating robustness under structural perturbations and incomplete logs, as real world system data is often noisy or partially missing. Additionally, analyzing model interpretability and understanding which graph structures or interactions contribute to predictions would provide deeper insight into model behavior | S13: Our group | T13: Our group | U13: Our group | V13: Stealing a Steam Session | W13: The project demonstrates a detailed and realistic attack chain by extracting DPAPI master keys and leveraging them to decrypt browser data, showing strong understanding of system-level security mechanisms and credential protection weaknesses | X13: Can be strengthened by evaluating the effectiveness of the proposed mitigation strategies, particularly how well they prevent or detect the demonstrated attack in practice. Additionally, analyzing potential bypass scenarios or limitations of these defenses would provide deeper insight into their real-world reliability
A14: 46141.489 | B14: andreas leeb | C14: e11415025 | D14: i am it | E14: top | F14: top | G14: Network analysis, with ddos | H14: good achivibility of project; good use of legacy dataset | I14: improve Data accuquistion to more then only AWS; what is innovativ in the project? | J14: read papers with llms | K14: transformers are the future; three different questions are attempted to answer. | L14: reading should still be human, if people want to learn; use the old miter frameworks for reports that are old. so the framework matches the report. | M14: MLLM to read miter reports | N14: closese the gap of missing graphs in 'normal' llm reading reports. RAG is a modern LLM technique, that might aliviate the small token chunking. cool to use local hardware for LLMs | O14: 20 repotrs is a very low number for Deep learning.512 token chunking is limiting on long term dependecies. | P14: classify raw system logs to miter attac using graphs | Q14: Graphs are a new and exiting research topic for ML. good quality data set selected | R14: capture raw logs from a cuckoo VM as test data; GAT allready includes a MLP, needs not to be done seperatly in the methodology slide. | S14: telemetry of endpoits with AI | T14: real pain point addressed with false positiv alerts; no transformer family is named, so they can choose once they know what they need. | U14: be os independent, with unix and macOS as well; the dataset includes a lot of useless information as well | V14: steal the Steam out of window | W14: real world application of the demo; usage of VM to stay safe, good usage of red team lecture | X14: session coockies do not last long, use different apporch; do cross platform tests on macOS, as the python tool allready allows for it.
A15: 46141.489 | B15: Aurelio Naufal Effendy | C15: M11415802 | D15: Visualizing EMBER: fast t-SNE for malware feature exploration | E15: Good use of the algorithm. The EMBER dataset sample was also quite huge | F15: Address parameter that are used for the method (better if using hyperparameter tuning). Not sure about the objectives (either binary classification or multi-class classification or like clustering problem). | G15: Enhanced Network Intrusion Detection Using Random Forest Classifiers | H15: The steps and explanation of the project are complete and detail. | I15: I think random forest is a bit outdated right now, maybe could try like more modern algorithm that might perform better. | J15: Automated MITRE ATT&CK Technique Classification from CTI Reports using Transformer Models | K15: Good background information, detailed problem, research question, deliverables, etc. | L15: Lacks the technique explanation. What if the MITRE ATT&CK list keep updated? will the model will be automated as well? (since they mentioned that they use the newest version of it). | M15: Automated CTI Analysis via Multimodal LLMs | N15: Cool idea, in line with the LLM trend as well. | O15: Consider the computational resources to finetune the LLMs. Conclusion should not be included in the proposal. Why include multimodal in the title when they say they only analyze text. | P15: MITRE ATT&CK Technique Detection | Q15: The technique used is quite complex, the dataset is also variable. | R15: Should include the specific method/specific thing in the title. Too much objectives (might be hard to do so many things at once). | S15: Explainable Sequence-Based MITRE ATT&CK Technique Detection from Endpoint Telemetry Using AI and Large Language Models | T15: Our Group | U15: Our Group | V15: Stealing a Steam Session: A Case Study on DPAPI and Browser Cookie Hijacking on Windows | W15: Quite unique research topic, different from the others | X15: Lacking real goal/objectives (since doing a case study), too much explanation about the detail (should be just in the final project).
A16: 46141.489 | B16: Alim Misbullah | C16: D11415803 | D16: Visualizing EMBER: fast t-SNE for malware feature exploration | E16: 1. Use t-SNE to reduce high dimensional malware dataset features. 2. Two-stage pipeline development: malware detection with binary classes and multi-class categorization. | F16: 1. It is better to compare with more models after implementing t-SNE. 2. It better to show distribution of original dataset and after t-SNE. | G16: Network Intrusion Detection (Enhanced Network Instrusion Detection Using Random Forest Classifier on the CIC-IDS 2018 Dataset) | H16: 1. The CIC-IDS 2018 is one of the most comprehensive and modern IDS datasets. 2. Random Forest is highly effective for anomaly detection. | I16: 1. It is better to try hybrid models or ensemble models (combination between RF and Deep Learning) 2. Added method for handling imbalanced dataset because CIC-IDS 2018 (e.g. SMOTE/ADASYN) | J16: MITRE ATT&CK Technique Detection (Automated MITRE ATT&CK Technique Classification from CTI Report using Transformer Models._ | K16: 1. Uses MITRE ATT&CK as industry-standard mapping 2. Handles unstructured text (CTI reports) effectively | L16: 1. Real-time deployment challenges 2. Handling noise and ambiguity in CTI text | M16: Automated CTI Analysis Via Multimodal LLMs | N16: 1. Uses Multimodal LLMs as cutting-edge research area 2. Reduces analyst workload significantly | O16: 1. How to deal with high computational cost and resource requirements 2. How to handle difficulty in explainability and trustworthiness | P16: MITRE ATT&CK Technique Detection | Q16: 1. Proposed End-to-End TTP Detection, Graph-Based Anomaly Detection and Context-Aware 2. Use SAGA (Synthetic Audit log Generation for APT campaigns) which is widely used dataset for MITRE ATT&CK Technique detection. | R16: 1. Compare different MLP layers to boost model performance. 2. Why do you have benign class. | S16: Explainable Sequence-Based MITRE ATT&CK Technique Detection from Endpoint Telemetry Using AI and Large Language Models | T16: My team | U16: From TA: Maybe can check which event is good or not. | V16: Stealing a Steam Session: Study on DPAPI and Browser Cookies Hacking on Windows | W16: 1. Build end-to-end demo, document every stage, producer defender checklist, and demonstrate the bypass. 2. Combines OS-level and application-level security analysis including red team and blue team training. | X16: 1. How to evaluate the implementation 2. Consider to use stable tool for creating the end-to-end demo.
A17: 46141.489 | B17: 盛爾君 | C17: 11407501 | D17: Visualizing EMBER: fast t-SNE for malware feature exploration | E17: visualizing high dimensional malware data makes people understand easily | F17: great | G17: Enhanced network intrusion detection using random forest classifiers | H17: high performance metrics, handle high dimension traffic features | I17: overfitting won't be a problem cuz you guys can do it. | J17: Automated MITRE ATTACK technique classification from CTI reports using transformer models | K17: solve human bottleneck, modern bert 512 token | L17: multihead, confusion matrix | M17: automated mitre attack via multimodal llm | N17: multimodal, llms | O17: llama3 other model, no augmentation | P17: mitre attack technique detection | Q17: graph attention, end to end ttp detection | R17: types of features use for modeling, why gat? | S17: explainable sequence-based mitre attack technique detection from endpoint telemetry using ai and large lanquage models | T17: llms automatic mitre attack technique detection, sequence event window | U17: website please~, we try all llm | V17: stealing a steam session | W17: session not cookie, | X17: session cookie, don't steal my steam account
A18: 46141.489 | B18: Lise Zheng | C18: F11402009 | D18: fast t-SNE for malware feature exploration | E18: clear vizualisation of malware families, ml to analyze dimension data | F18: compare with other techniques, integrate with feature extraction models | G18: enhanced network intrusion detection using rf classifiers | H18: strong perf with rf, use of realistic datasets | I18: include real time detection analysis, compare with other ml models | J18: automated mitre attack technique classification from cti report using transformer models | K18: good use of transformer models, good evaluation strategy | L18: clarify datasets used, define performance targets | M18: N/A | N18: N/A | O18: N/A | P18: mitre attack technique detection | Q18: use of gat, structured attack lifecycle modeling | R18: add explainability for graph decisions, validate realism of synthetic data | S18: explainable sequence based mitre attack technique detection from endpoint tele;etry using ai and llm | T18: strong coverage of endpoint telemetry, use of large real world splunk dataset | U18: evaluate real time performance, address class imbalance in labels | V18: stealing a steam session | W18: strong attack scenario, defensive output included | X18: broaden browser coverage, evaluate attack detection tools
A19: 46141.489 | B19: 陳增勇 | C19: B11007106 | D19: Visualizing Ember fast T-sne for Malware Feature Exploration | E19: Using EMBER does provide an advantage where it allows for the rapid identification of complex structural clusters and behavioral anomalies within high-dimensional malware datasets. | F19: The presentation itself is great and are in depth, but some of the parts are being explained a bit too fast | G19: Enhanced Network Intrusion Detection Using Random Forest classifiers | H19: since the main idea of the system will incorporate automation, it will definitely reduce the cost for traditional systems. | I19: Presentation are great, the presenters are clear and slow enough for me to understand the content of the presentation. | J19: Automated MITRE att&ck technique classification from CTI Reports using Transformer Models | K19: Considering the nature of SOC, CTI teams, security tools, and map utilizes different naming conventions, this aims to unite and create a universal language for all related professionals in the field. In addition, this project aims to not only cut down on costs, it also aims to increase efficiency in analyzing and identifying MITRE attacks. | L19: I felt the flow after the introduction was a bit slow, other than that, the presentation was great and the presenters talked clearly | M19: Automated CTI analysis Via Multimodal LLMS | N19: Implementing AI into the workload has the goal of increasing the efficiency and to aid analysts in their field to automatically map MITRE ATT&CK tactics | O19: Presentation was great and the presentation slides is very informative and does include all the essential info on the topic. However, I do feel the overall flow of the presentation was a little bit slow. For me personally, I really like the clean minimalist look of the slides. | P19: MITRE ATT&CK technique and detection | Q19: I love the implementation of REAL LIFE APT campaigns as their dataset. Moreover, the implementation of the Process system using a flowchart does wonders in assisting the comprehension of the concept's methodology. | R19: Although the content and information for the presentation are definitely numerous and very thorough, I felt the pacing and the speed of the presentation can be cranked up a little. | S19: Explainable Sequence-Based MITRE ATT&CK Technique Detection From Endpoint Telemetry Using AI and Large Language Models | T19: (our own group presentation) | U19: (our own group presentation) | V19: Stealing a Steam Session | W19: I really like the explanation where they emphasize the vulnerabilities of session cookies in modern browser can be exploited to gain access to steam accounts and bypassing password and 2FA | X19: I really resonated with the topic. As someone that uses steam as a main entertainment/gaming system, I do felt the importance of this presentation. However again, I do felt that the pacing and some of the pronunciation can be worked on.
A20: 46141.489 | B20: 柯議翔 | C20: M11407319 | D20: Visualizing EMBER fast t-SNE for malware feature exploration | E20: The picture visualization is very clear,beautiful and simple | F20: good | G20: Enhanced network intrusion detection using random forest classifiers | H20: By combining multiple decision trees, it significantly reduces the risk of overfitting and provides higher detection accuracy than single models. | I20: Incorporate specific techniques (like SMOTE or undersampling) to improve the detection rate of rare but critical types of cyberattacks. | J20: Automated MITRE ATTACK technique from CTI report using transfomer models | K20: It automates the labor-intensive process of manual analysis, allowing security teams to process vast amounts of unstructured text data in near real-time. | L20: good | M20: Automated CTI analysis via multimodal LLM | N20: Leveraging LLMs' advanced reasoning allows for better synthesis of fragmented intelligence into coherent, actionable reports compared to traditional tools. | O20: Need to think about how to do augmentation | P20: Mitre attack technique detection | Q20: Using GAT effectively captures critical attack patterns within complex audit logs. | R20: Good | S20: Explainable sequence-based mitre attack technique detection from endpoint telemetry using AI and large language models | T20: By analyzing sequences of events rather than isolated alerts, the model can effectively capture the progression of multi-stage attacks over time. | U20: good | V20: stealing a steam session | W20: The topic provides a clear case study on how session management vulnerabilities can be exploited, which is essential for understanding end-to-end web security. | X20: The implementation part is explained in great detail.
A21: 46141.49 | B21: Walfroy Saint Guilhem | C21: E11415031 | D21: Malware feature exploration | E21: Directly applicable in reality, already detailed in the usage of the data | F21: Maybe to binary for the detection of malware, granularity is good enough to classify : false positive ? What if a malware is between 1 and zero for detection | G21: T | H21: T | I21: T | J21: BENI : Automated MITRE ATTACK Technique classification from CTI Reports using Transformer Models | K21: Many models, already cleared features used | L21: Maybe over complicated number of models ? | M21: Automated CTI Analysis via multimodal LLMs | N21: Usage of LLMS, vision on pdfs and other materials | O21: Nots supporting images | P21: MITRE ATT&CK | Q21: Graph attention, content attention | R21: Only one reference, can be more clear on datasets usage | S21: EXPLAINABLE SEQUENCE-BASED MITRE ATT&CK TECHNIQUE DETECTION FROM ENDPOINT TELEMETRY USING AI AND LARGE LANGUAGE MODELS | T21: Can detect directly from the log, usage of splunk | U21: The logs can be deleted by the attacker and so the system could be inefficient, related to data base of splunk | V21: Stealing a steam session - session hijacking | W21: - | X21: -
A22: 46141.49 | B22: 許詠翔 | C22: M11407502 | D22: Visualizing EMBER: fast t-SNE for malware feature exploration | E22: using clustering to visualization, and use multiple techniques to classification. | F22: Maybe can add the concept of clustering, like NCA (Neighborhood Components Analysis) with classification method or other ways to improve more accuracy. | G22: Enhanced Network Intrusion Detection Using Random Forest Classifiers | H22: analyze Random Forest strength and challenge, use of realistic dataset | I22: Include real time detection analysis, compare other ml models. | J22: Automated MITRE ATT&CK Technique Classification from CTI Reports using Transformer Models | K22: compared with many models, and try to cross-dataset evaluation | L22: Macro-F1 is sensitive to imbalanced data; even a few errors in minority samples can cause intense fluctuations. Therefore, when using it for early stopping, increasing the patience or monitor the loss as a secondary signal to avoid stopping too early. | M22: NA | N22: NA | O22: NA | P22: MITRE ATT&CK Technique detection | Q22: use graph structure to express the SAGA logs | R22: GAT typically has high computational overhead. Maybe can monitor inference speed and confirmation of whether it can be done in real time. | S22: Explainable Sequence-Based MITRE ATT&CK Technique Detection From Endpoint Telemetry Using AI And Large Language Models | T22: using deep learning to classify sequence and LLM to generate readable sequence, which maybe can reduce hallucination of LLM | U22: maybe comparing with fixed-length windows and dynamic-length windows (fixed-length widow might sometimes divide the whole sequence) | V22: Stealing a Steam Session | W22: Implement simulated end-to-end attacks and defense perspective | X22: The simulation may become invalid after the website is updated.
A23: 46141.492 | B23: Oriiana Nedzelska | C23: F11415026 | D23: Visualizing EMBER: fast t-SNE for malware feature exploration | E23: Strong motivation (helping the cyber analysts classify/detect malware, considering humans can't analyse multidimensional data), use or preprocessed data to put more focus for this course into the deep learning techniques and not data preprocessing, | F23: Didn't mention novelty, so it is hard to judge the novelty of this approach | G23: Enhanced Network Intrusion Detection Using Random Forest Classifiers | H23: The project is very straightforward and relevant, use or random forest is a good baseline choice for classification problems | I23: Using two datasets might make this project unnecessarily more difficult because they will need to preprocess the data and align it between the reports | J23: Automated MITRE ATT&CK Technique Classification from CTI Reports using Transformer Models | K23: This is my group | L23: This is my group | M23: Analysis of CTI reports with multimodal vision | N23: The topic is very well defines, relevant and well structured | O23: Not exactly sure about the novelty of this approach comparing to the existing LLM + RAG approaches | P23: MITRE ATT&CK Technique detection | Q23: Strong motivation, it is also a strong choice to use GAT | R23: Evaluation strategy needs more detail | S23: Explainable Sequence-Based MITRE ATT&CK Technique Detection From Endpoint Telemetry Using AI and Large Language Models | T23: Very clearly defined pipeline | U23: Seems like it's a quite ambitious projects with complex xomponents, I wonder is the scope is appropriate | V23: Stealing a Steam Session | W23: The project is nicely structured and uses a real-world case | X23: Maybe a stronger focus on defensive measures would be beneficial
A24: 46141.497 | B24: Mikhael Gerson Silaen | C24: M11407809 | D24: Visualizing EMBER Fast t SNE for malware feature exploration | E24: - Using relevance dataset for malware classification, fast t sne method also applied where speed matters - Visualizing help both technical and non technical audience | F24: - benchmark with other method paper result - demonstrate how to interpret the visualization | G24: - | H24: - | I24: - | J24: Automated MITRE ATTCK Technique Classification from CTI Reports Using Transformer Models | K24: - Aligned with MITRE Attck mapping that widely used as framework for analyst - Automating Analysis help the analysis to save more time on more important tasks | L24: - Operational integration cross all data platform - Lots of Benchmark model to compared and strength for long term value research | M24: Automated CTI Analysis Via Multimodal LLMs | N24: - RAG pipeline integration and scalable architecture - Hardware optimization and applied outputs | O24: - Labelling challenges - Considering Data Set diversty | P24: MITRE ATT&CK Technique detection | Q24: - End to end automation, using high fidelity dataset - Applied Relevance for analysts to help them maps the mitre attck framework | R24: - Compare with other model benchmark - Explainability about the visualization result | S24: Explainable Sequence Based MITRE ATTck Technique Detection From Endpoint Telemetry Using AI and LLMs | T24: - Inetgrating LLMs for human readable explaination makes output actionable and analyst friendly - Sequence learning caoture temporal attack behaviour that single event model might miss | U24: - Expand dataset coverage for borader applicability - Optimize deployment | V24: Stealing a Steam Sessions : A case study on DP API and browser cookie hijacking on windows | W24: - Applied relevance because steam is widely used and have a high value target (wallet, inventory ect) - Security awareness in nowadays world with hands on simulation | X24: - scope limited on steam, maybe can be try web context - Comparison model
A25: 46141.497 | B25: Rivaldo Yudha Pradana | C25: M11407804 | D25: Visual EMBER: fast t-SNE for malware feature exploration | E25: -The proposal has a clear motivation: t-SNE can help visualize high-dimensional malware features and make malware clusters easier to understand for analysts and non-technical audiences. -The use of the EMBER dataset is appropriate because it is a large, standardized malware dataset with pre-extracted features, allowing the group to focus on model training, evaluation, and visualization. | F25: -explain how the visualization result will be evaluated, for example by comparing whether benign and malicious samples form clear and understandable clusters. -They should discuss limitations of t-SNE, such as parameter sensitivity, scalability for large datasets, and the possibility that visual clusters may not always represent true malware family relationships. | G25: Enhanced Network Intrusion Detection using Random Forest Classifiers on the CIC-IDS2018 Dataset | H25: - | I25: - | J25: Automated MITRE ATTACK Technique classification from CTI Reports using Transformer Models | K25: -The proposal addresses a real cybersecurity problem: CTI reports are long and difficult to manually map to MITRE ATT&CK techniques, so automation could reduce analyst workload and improve response speed. -The methodology is well structured because it compares multiple transformer models, uses two public datasets, and evaluates performance using relevant metrics such as macro-F1, per-technique precision/recall, latency, memory usage, and cross-dataset transfer. | L25: -The group should make the workflow easier to understand by adding a simple diagram that shows the steps from CTI report input, text processing, model classification, and final MITRE ATT&CK technique output. -The group could briefly explain the difference between the transformer models they compare, so the audience can understand why models like BERT, SecureBERT, CTI-BERT, and ModernBERT are relevant for this project. | M25: Automated CTI Analysis via multimodal LLMs | N25: -The proposal has a clear motivation because CTI reports often contain long text, diagrams, screenshots, and unstructured information that can be difficult for analysts to process manually. -The project idea is practical because it combines multimodal LLMs and RAG to extract IoCs, identify TTPs, and map the information to the MITRE ATT&CK framework. | O25: -The group could add a simple example showing the input and output of the system, such as one CTI report being converted into extracted IoCs, TTPs, and MITRE ATT&CK mapping. -The group should keep the first version focused on a smaller scope, for example only a few types of CTI reports or selected MITRE ATT&CK tactics, so the prototype is easier to complete and evaluate. | P25: MITRE ATT&CK Technique Detection | Q25: -The proposal has a clear cybersecurity motivation because APT attacks are difficult to detect from raw system logs using traditional rule-based methods. -The use of provenance graphs and Graph Attention Network is suitable because it can capture relationships between processes, files, and network activities, not just isolated log events. | R25: -The group could add a simple example showing how one raw system log is transformed into a graph and then classified into a MITRE ATT&CK technique. -The group should briefly explain how they will evaluate the model, for example by showing accuracy, precision, recall, or comparing it with a simpler baseline method. | S25: Explainable Sequence-Based MITRE ATT&CK Technique Detection from Endpoint Telemetry using AI and Large Language Models | T25: -The proposal has a clear cybersecurity motivation because it focuses on detecting multi-stage attacks from system logs and mapping them to MITRE ATT&CK techniques. -The project is practical because it uses Splunk Attack Data and combines machine learning models with LLM explanations, making the result easier to understand for security analysts. | U25: The group should start with a smaller number of ATT&CK techniques or attack scenarios first, so the prototype is easier to build, test, and evaluate. | V25: Stealing a Steam Session: A Case Study on DPAPI and Browser Cookie Hijacking on Windows | W25: -The proposal has a clear and focused topic because it explains how session cookies can become a security risk even when users use passwords and 2FA. -The project is practical because it plans to demonstrate the attack in a controlled Windows VM and also produce a defender’s checklist for prevention and detection. | X25: -emphasize that the demo is only conducted in a safe lab environment and clearly explain the ethical boundaries of the project. -The group could make the defense section stronger by adding simple prevention steps for users and admins, such as locking devices, limiting admin access, enabling Steam Guard, and monitoring suspicious access to browser cookie files.
A26: 46141.497 | B26: REN-WEI YE | C26: M11407437 | D26: Ember model | E26: Lowering the barrier to entry for research Standardized benchmark High computational efficiency Transparency in feature engineering | F26: Vulnerability to adversarial attacks due to its open-source nature. "The dataset feels outdated. | G26: Enhanced Network Intrusion Detection System | H26: High Performance Low False Alarms Feature Handling | I26: May Overfitting Generalization Issues | J26: To automate the mapping of Cyber Threat Intelligence (CTI) reports to the MITRE ATT&CK framework using Transformer models | K26: Long-context window Domain-specific strength | L26: 512-token limit Generic pretraining Poor on long-tail | M26: Bottleneck" where legacy tools fail to parse mixed-media reports | N26: Vision Capability Maximized Efficiency High Traceability | O26: Context Truncation High Evaluation Cost | P26: Mitre Att&ck Technique detection | Q26: Strong motivation with a concrete provenance-graph + GAT pipeline for fine-grained TTP-level edge classification on a well-labeled dataset (SAGA) | R26: Relies solely on synthetic data (SAGA) without real-world validation or baseline comparison against existing provenance-based GNN methods (e.g., ProvDetector, ThreaTrace). | S26: AI/Sequence-Learning-based MITRE ATT&CK Technique Detection from Windows/Sysmon Endpoint Logs, with an LLM Explanation Engine | T26: Well-structured end-to-end pipeline (parsing → sequence windows → Transformer classifier → MITRE mapping → LLM explanation) on a real-world Splunk dataset, with strong motivation for sequence learning and ambitious sub-technique-level granularity (91 labels). | U26: Severe class imbalance across 91 sub-techniques is unaddressed, the LLM explanation module lacks any evaluation/validation plan (hallucination risk), and there’s no concrete baseline comparison against existing log-sequence TTP detection works.​​​​​​​​​​​​​​​​ | V26: We are GPT+ our main goal is to show that we can steal steam cookie and use it in attacker's computer | W26: I can use steam which is not mine to spread some stupid comments on community. | X26: Maybe we can steal cookie which has extra encripyt ?
A27: 46141.497 | B27: Tsu Hsiang-En | C27: M11307310 | D27: Ember model | E27: Lowering the barrier to entry for research Standardized benchmark High computational efficiency Transparency in feature engineering | F27: Vulnerability to adversarial attacks due to its open-source nature. "The dataset feels outdated. | G27: Enhanced Network Intrusion Detection System | H27: High Performance Low False Alarms Feature Handling | I27: May Overfitting Generalization Issues | J27: To automate the mapping of Cyber Threat Intelligence (CTI) reports to the MITRE ATT&CK framework using Transformer models | K27: Long-context window Domain-specific strength | L27: 512-token limit Generic pretraining Poor on long-tail | M27: The goal is to solve the "Information Overload" analysts face with massive volumes of reports, and to break through the "Unstructured Data Bottleneck" where legacy tools fail to parse mixed-media reports | N27: Vision Capability Maximized Efficiency High Traceability | O27: Context Truncation High Evaluation Cost | P27: ATTACK Technique detection | Q27: Strong motivation with a concrete provenance-graph + GAT pipeline for fine-grained TTP-level edge classification on a well-labeled dataset (SAGA) | R27: Relies solely on synthetic data (SAGA) without real-world validation or baseline comparison against existing provenance-based GNN methods (e.g., ProvDetector, ThreaTrace). | S27: AI/Sequence-Learning-based MITRE ATT&CK Technique Detection from Windows/Sysmon Endpoint Logs, with an LLM Explanation Engine | T27: Well-structured end-to-end pipeline (parsing → sequence windows → Transformer classifier → MITRE mapping → LLM explanation) on a real-world Splunk dataset, with strong motivation for sequence learning and ambitious sub-technique-level granularity (91 labels). | U27: Severe class imbalance across 91 sub-techniques is unaddressed, the LLM explanation module lacks any evaluation/validation plan (hallucination risk), and there’s no concrete baseline comparison against existing log-sequence TTP detection works.​​​​​​​​​​​​​​​​ | V27: We are GPT+ our main goal is to show that we can steal steam cookie and use it in attacker's computer | W27: I can use steam which is not mine to spread some stupid comments on community. | X27: Maybe we can steal cookie which has extra encripyt ?
A28: 46141.502 | B28: BERNARDO ANDRADE | C28: E11423008 | D28: my group | E28: my group | F28: my group | G28: ENHANCED NETWORK INTRUSION DETECTION USING RANDOM FOREST CLASSIFIERS | H28: Good, clear and appealing presentation with images that facilitated the understanding of the topic. Random forest has superior accuracy in network security tasks and thats why they choose it. | I28: In the other hand, overfitting can be a big problem in th RF so they should address that difficulty. Also, they should care about generalizations if they train th RF in a specific dataset. | J28: Mitre attack classification | K28: They will use the latest Mitre Attack framework and showed a good worklow of the project, explaining what are the objectives for every week and what they expect to accomplish. | L28: They could've show more images to illustrate the problem facilitating the understanding and explain with more detail what they expect about the results. | M28: automated CTI analysis via multimodal LLMS | N28: The pain points are reallly addresing a real existing problem, information overload and the bottleneck of unstructured data. It will be multimodal system allowing the use of images. | O28: The expected outputs weren't that clear for me and i think the workflow of the project can be more explicited, especially what will be their dataset. | P28: MITRE ATTACK TECHNIQUE CLASSIFICATION | Q28: They address the lack of high-quality data set with accurate mitre attack. They will use a robust data set with 8 APT campaigns and 20 APT campaigns created through SAGA's random generation. | R28: they could've use more images to illustrate and i think they lacked a bit of more knowledge about the theme. | S28: EXPLAINABLE SEQUENCE-BASED MITRE ATTACK TECHNIQUE DETECTION FROM ENDPOINT TELEMETRY | T28: Good , clear and detailed presentation with a lot of illustrations and thd group showed a great knowledge about the theme. | U28: the presentation is really good, maybe they could just explain better the dataset and why they didnt check the benign. | V28: Stealing a Steam Session | W28: well organized and explained presentation, with clear design and flow, also they already built a demo. | X28: explain better the terms for people without knolwdge like the gaming platform the "steam" but overall nothing more to improve.
A29: 46141.571 | B29: Diven Dechal Jatiputra | C29: F11415019 | D29: Visualizing EMBER: fast t-SNE for malware feature exploration. Using t-SNE dimensionality reduction to visually explore a Malware Dataset | E29: -Using High Dimensionality Malware model ensure that the complexity of the 2D map is too complex without losing the essential relationships between the datapoints. -If the machine learning model is consistently misclassifying a certain group of files, by using the map visualization allows researchers to see if those files are physically located in a "gray zone" between benign and malicious clusters, helping to refine feature extraction. | F29: - Using EMBER dataset, It is a static dataset which is quite old or traditional, for modern malware typically use Polymorphism so it would hide its features until it is executed. Maybe using/integrating dynamic features could create a more robust map against modern attacks. - It shows that while these visualizations are great for humans, using the resulting 2D images to train AI (like a CNN) often yields lower accuracy than using non-visual models like LightGBM on the raw data. | G29: Enhanced Network Intrusion Detection using Random Forest Classifiers | H29: -- | I29: - | J29: Automated MITRE ATTACK Technique classification from CTI Reports using Transformer Models | K29: - Using transformers capture the global context of a sentence. - The Use of SecureBERT and SecBERT | L29: - Ensure the dataset is not biased towards just phising - Include Dynamic datasets | M29: Automated CTI Analysis via multimodal LLMs | N29: - By using LLMs. it can automatically identify and extract indicators of compromise and TTPs. - Using RAG to accurately map the MITRE ATT&CK Framework with high traceability | O29: - Ensure that the RAG has a high precision to accurately map out the framework - For the LLM Inference, it doesn't state the parameter size | P29: MITRE ATT&CK Technique Detection | Q29: - SAGA is a great and high quality Dataset - | R29: - Unclear objectives - No dataset reference | S29: Explainable sequence based mitre attack technique detection from endpoint telemetry using ai and llm | T29: - Comparing ML with Transformer models while integrating LLMs - Large dataset with wide variety of data | U29: - Maybe Larger parameter size for the LLMs - | V29: Stealing a Steam Session | W29: - Unique use of injection in cookies - bypass 2fa | X29: - Try other website other than Steam - Strict device
... A36: 46141.974 | B36: Dennison Soedibjo | C36: F11415018 | D36: Visualizing EMBER: fast t-SNE for malware feature exploration | E36: - huge dimensions - visual debugging | F36: - evaluate and ensure reduction of features does not result in loss of information - increase adaptivity for non-static malware | G36: Enhanced Network Intrusion Detection using Random Forest Classifiers on the CIC-IDS2018 Dataset | H36: - | I36: - | J36: Automated MITRE ATTACK Technique classification from CTI Reports using Transformer Models | K36: - highly practical - strong methodology strategy | L36: - thorough report for transparency as BERT models can be a bit of a blackbox - apply temporal robustness | M36: Automated CTI Analysis via multimodal LLMs | N36: - clear end to end pipeline - grounded evaluation with a golden dataset | O36: - increase dataset size to train an LLM - define parameter size | P36: mitre attack technique detection | Q36: - high relevance & practicality - clear pipeline | R36: - define dataset properly - methodology could be more specified | S36: Explainable Sequence-based MITRE ATT&CK Technique Detection from Endpoint Telemetry Using AI and Large Language Models | T36: - Clear, complete end-to-end pipeline - Incorporation of temporal context via sequence modeling | U36: - AI model could be more specified - define parameters | V36: Stealing a Steam Session. A case study on DPAPI and Browser Cookie Hijacking on Windows. | W36: - highly practical and relatable (steam has a large user base) - good methodology | X36: - analyze the defense mitigations afterwards - address "App-Bound Encryption"

Sheet Camping Simulation
A1: 時間戳記 | B1: Name | C1: Student ID | D1: Cyber Punk Summary | E1: Insect Summary | F1: European Avalanche Summary | G1: ANTSLAB Summary | H1: BENI Summary | I1: Cyber Six Summary | J1: GPT+ Summary | K1: 第 1 欄
A2: 46148.389 | B2: Saint Guilhem Walfroy | C2: E11415031 | D2: Initial access, exfiltration, and persistence lab with Caldera and Procmon | K2: 85
A3: 46148.488 | B3: 祖祥恩 | C3: M11307310 | D3: This group conducted a controlled Red Team exercise on a Windows 10 VM, using CALDERA to simulate attacker behavior after initial access, and used Procmon logs to track and map each action to MITRE ATT&CK techniques — focusing on detection and defense analysis rather than the initial intrusion itself.​​​​​​​​​​​​​​​​ | E3: A well-structured simulation using CALDERA with both custom and built-in ATT&CK abilities, covering the full kill chain from execution to exfiltration, with Procmon as the detection/logging layer.​​​​​​​​​​​​​​​​ | F3: This group ran a full 6-tactic ATT&CK kill chain on a Windows 10 VM — from spearphishing and LSASS credential dumping (comsvcs.dll was the only method that worked out of 7 tried) to stealthy HTTPS exfiltration via curl to file.io, with Procmon log analysis to validate each step.​​​​​​​​​​​​​​​​ | G3: This group simulated a TrickBot-based attack (CISA Advisory AA21-076A) using MITRE Caldera and Procmon, covering a full 8-tactic ATT&CK kill chain from Initial Access to Exfiltration, with Caldera replacing malicious payloads with harmless markers for safe emulation.​​​​​​​​​​​​​​​​ | H3: This group simulated a Firefox cookie theft attack using Caldera, where a phishing email lures the victim (Windows 10) into opening an attachment, triggering a 7-step chain: OS Discovery → AutoRun Persistence → Stage Directory → Steal Firefox Cookies → ZIP Compress → Exfil to C2 → Clear History. The agent disguised itself as splunkd.exe to blend in, with stolen session cookies allowing account takeover and 2FA bypass without needing elevated privileges.​​​​​​​​​​​​​​​​ | I3: CyberSix ran a safe 5-stage ATT&CK simulation (spearphishing → PowerShell execution → scheduled task persistence → credential access → C2 exfiltration) on a Windows 10 VM using Caldera with dummy data throughout. All 5 stages succeeded, and their Procmon analysis of 620,606 events highlighted clear detection signals: the suspicious splunkd.exe → powershell.exe parent chain, staged artifact files in \ProgramData\caldera-lab\, and outbound TCP via Invoke-WebRequest — demonstrating that kernel-level logging can catch what standard app logs miss.​​​​​​​​​​​​​​​​ | J3: This report demonstrates how an APT-style attack similar to Volt Typhoon can be fully simulated in about 20 minutes using Caldera and Procmon. The attack relies only on built-in Windows tools and spans all seven stages, from initial access to data staging. Despite the lack of malware, each step leaves detectable behavioral traces, highlighting that effective defense depends on strong telemetry and behavior-based detection rather than signatures alone. | K3: 87
A4: 46148.493 | B4: Ugo LINDEPERG | C4: E11415027 | D4: Go in the system, look for the OS Version, look for credentials, persistence, exfiltration, | E4: Go in the system, execution, persistence, discovery, command and control, collection | F4: Go in the system, execution, discovery, credentials steal, extraction | G4: Go in the system, privilege escalation, defense evasion, execution, discovery, credentials steal, exfiltration | H4: My group | I4: Spear phishing, execution, persistence, credential steal, exfiltration | J4: Too much techniques | K4: 88
A5: 46148.495 | B5: Lucas Metzger | C5: F11415020 | D5: PowerShell execution in Windows System, Network Discovery, Credential artifact search, Local file collection, collecting data. Used Procmon logs | E5: Presented Caldera in detail. Started with Exfiltration and then continued with Collection | F5: My group | G5: payload retrieved from GitHub, process hollowing performed on Notepad, mutex created for control, scheduled task established, system information collected, JSON data exfiltrated via HTTP POST | H5: OS discovery, persistence, steal cookies from Firefox, compress into ZIP archive, exfiltration via HTTP POST, clear PowerShell history | I5: Spearfishing, PowerShell execution, create a scheduled task, read credential file, exfiltration | J5: Execution, exfiltration | K5: 87
A6: 46148.496 | B6: peter kuhn | C6: e11415021 | D6: they get passwords from password store. did they analyse the caldera report, or the actulal pocmon? | E6: Remote access to the machine. custom failed ability | F6: my group, LASSA Keys, analyse the pocmon with python | G6: rebuild the real trickbot attack flow, good connection to procmon files. | H6: steal cookies (containing session keys), compressed as zip, good discussion of clear history comand limitations | I6: fully sucsessfull simulation, password exfiltartion. good actulal pocman analysis | J6: only build in windows tools misused. same succsess with the comsvc.dll and LASSA extraction. good attack, best of the day. | K6: 88
A7: 46148.496 | B7: Adam Pach | C7: E11415030 | D7: They picked a post-compromise attack: PowerShell execution, Network Discovery. Looking to the credential registry and creating it. Local files collection and archiving a local data. | E7: Simulation done by Caldera. Using Mitre Attack framework. They really explain how to use the Caldera. Getting a remote access to the machine. | F7: Our group | G7: Focusing on TrickBot, modular trojan, includes a downloading payload from GitHub, Compiling a C# code. Checking the agent is running as a Admin or SYSTEM, Then trying to get a credentials by API Hooking | H7: Goal is to steal cookie of the firefox. Session cookies, Discovery of the OS, Registry Persistance, Staging directory - create a tmp dir for storing collected data. Clearing the PS history | I7: Spear fishing attachments, Local Receiver, System Analysis | J7: Volt typhone, Initial access by powershell, Internal Reconnaissance, then there are privilage escalations, Defence Evaision disable the win def. Persitance, Proxy for another access, Credential access LSASS and get a browser credentials | K7: 89
A8: 46148.497 | B8: Jules GIRARD | C8: E11415022 | D8: Credential thief (password from chrome/firefox) after reconnaissance, persistence with Register | E8: Webhook exfiltration of sensitive file ("killall.txt") from Desktop folder | F8: Persistence with local account lsass credential exfiltration over encrypted Non C2 protocol | G8: persistence with scheduled task after privilege escalation and Credential collection | I8: phishing and attachment execution, persistence via scheduled task and fake credential file exfiltration with C2 channel | J8: Footlhold with web shell and port forwarding, defensive evasion techniques (log cleared), persistence with IIS, credential access (bitadmin.exe) | K8: 89
A9: 46148.497 | B9: Alim Misbullah | C9: D11415803 | D9: - Use MITRE ATT&CK CALDERTA to simulate attacker behavior. - Present for workflow for simulation - Phase 1: Initial Compromise & Foothold - Phase 2: Internal Reconnaissance - Discovery - Phase 3: Internal Reconnaissance - Credential - Phase 4: Maintain Presence - Persistence - Phase 5: Complete Mission - Collection Use procmon to onserve the activities inside the system. | E9: Our group presentation. | F9: - They simulate the attacks to the machine - Caldera requires turn off deferender - They implemented 6 MITRE ATT&CK tactics: Initial Access, Executioon, Persistence, Credential Access, Discovery, Exfiltration - They conclude with high severity and low visibility for simulation | G9: - TrickBot Real Attack Flow: Initial Access, Execution + Defense Evasion, Single-instance lock, Persistence + Priviliege Escalation, Discovery, Browser Injection, Credential Capture, Exfiltration + Self-Update - Simulated Attack Flow: Initial, Execution, Stealth / Privilege Escalation, Defense Evision, Execution / Persistence / Priviliege Escalation, Discovery, Collection / Credential Access - They compare real attack with simulated attacks flow from MITRE CALDERA. - They success to simulate the real attack using MITRE CALDERA for each phase and show what kind of MITRE Techniques use in their simulation. | H9: - Title: Adversary Emulation with Caldera: A Cookie Theft Attack Simulation - Sending Phishing Email, Windows 10 as victim, Cookie Recovery, Ubuntu as attacker - They explain about lab environment including how to setup caldera and target victim - Walkthrough: OS Discovery (T1082), Persist Autorun (T1546), Stage Dir (T1074), Steal Cookies (T1539), Compress ZIP (T1560), Exfil C2 (T1041), Clear History (T1070). - In their simulation, they also mapp each step into tactics and techniques from MITRE ATT&CK. - They also show content analysis from their process monitor. - Conclusion: Don't disable antivirus, don't save password, don't open attachment. - VoidStealer was a malware more complex than our. | I9: - Phase-by-phase breakdown: Initial Access, Execution, Persistence, Creadential Access, Exfiltration, - They success to simulate all of operations. - The final phase sent dummy data from victim to a local http receiver on the caldera VM. - All 5 attacks stages produced distinct, observable artefacts. - Key detection points & takeaways: Process anomaly, Execution chain, Data access, Network traffic, Registry task, Early interruption, Logging visibiltiy. - Real world applicability: Emulating modern threat | J9: - Simulation Volt Typhoon - Threat Model and Toolchai: Mardiant Attack Lifecycle: (1) Initial Compromise, (2) Established Foothold, (3) Escalate Privileges, (4) Internal Recon, (5) Move Laterally, (6) Maintain Presence, (7) Complete Mission - Lesson from a Living-off-the-Land Adversary | K9: 93
A10: 46148.497 | B10: 龔效諄 | C10: M11407618 | D10: This report describes a Windows post-compromise simulation using MITRE CALDERA. The Sandcat agent is used to simulate an already-compromised host and establish a foothold on the victim machine. After the agent connects to CALDERA, the adversary performs host and network discovery using commands such as systeminfo, ipconfig, and netstat. It then searches for credential-related artifacts, such as browser login data or a fake credential file, to simulate credential reconnaissance. Next, the adversary creates a Registry Run Key under HKCU\Software\Microsoft\Windows\CurrentVersion\Run to simulate persistence. This registry value is harmless and only runs an echo command. Finally, the adversary collects fake sensitive files from the victim machine, copies them into a staging directory, and compresses them into simulated_exfil.zip. This represents exfiltration preparation, not real data exfiltration, because no files are transmitted outside the victim machine. Procmon evidence is used throughout the report to verify each behavior, including process creation, registry modification, file reading, staging, and archive creation. | E10: This project demonstrates a cyber attack simulation using MITRE CALDERA based on the MITRE ATT&CK framework. The simulation successfully performed several attack stages, including execution, discovery, persistence, and command-and-control activities. The project also explored collection and exfiltration techniques, although some stages were unsuccessful due to environment limitations. In addition, manual ability creation and Webhook.site were used to simulate external communication behavior. Overall, the project provided practical experience with adversary emulation, attack lifecycle analysis, and system monitoring in a controlled cybersecurity environment. | F10: This project used MITRE CALDERA to simulate cyber attacks based on the MITRE ATT&CK framework. Several attack techniques were tested, including phishing, command execution, credential access, discovery, and data exfiltration. The system analysis showed suspicious activities such as repeated access to lsass-comsvcs.dmp files and sensitive DLL files, which may indicate credential dumping behavior. Procmon logs were analyzed using Python tools to identify abnormal system operations and process activities. The results demonstrate that cyber attacks can succeed with low visibility and minimal effort, highlighting the importance of behavior-based monitoring instead of relying only on traditional antivirus detection. | G10: This presentation introduces a simulated TrickBot cyberattack using the MITRE ATT&CK framework and MITRE Caldera. The project demonstrates how attackers perform different stages of an attack, including execution, persistence, defense evasion, discovery, credential access, and exfiltration. Procmon was used to monitor and analyze system activities during the simulation. The attack walkthrough compares the real TrickBot attack flow with a safe emulation environment, where harmful payloads were replaced with harmless markers. The simulation shows how malware can download files, create scheduled tasks, gather system information, and simulate credential theft and data exfiltration. The presentation also discusses possible mitigations against real TrickBot attacks, such as avoiding suspicious email attachments, disabling Office macros, and not using administrator accounts for daily activities. These practices help reduce the risk of malware infection and privilege abuse. | H10: Users should avoid opening suspicious email attachments, disabling antivirus or EDR protection, and saving passwords directly in web browsers. The presentation also mentions VoidStealer as a more advanced malware example that can steal browser secrets such as saved passwords and cookies from memory. | I10: These slides summarize the key lessons and real-world implications of the TrickBot attack simulation. The project showed that human error, stored credentials, persistence mechanisms, and hidden network traffic are major security risks. It also demonstrated how attackers can abuse legitimate system tools such as PowerShell and Scheduled Tasks to avoid detection. The simulation highlighted the importance of deep monitoring tools like Procmon and EDR solutions for detecting suspicious process chains, registry changes, file artifacts, and outbound network traffic. Overall, the project emphasized safe attack emulation, practical threat detection, and the value of early interruption before attackers can escalate or exfiltrate data. | J10: The conclusion highlights that Volt Typhoon’s “Living-off-the-Land” techniques can be realistically reproduced without custom malware by abusing built-in Windows tools. The simulation also showed that behavioral monitoring, process anomaly detection, and tamper-resistant logging are important for identifying advanced persistent threats (APTs) targeting critical infrastructure. | K10: 92
A11: 46148.497 | B11: Danis Putra Perdana | C11: D11415806 | D11: They use mix framework (mandiant and MITRE att&ck) to do the simulation. They success to capture the attack, but Some of captured log in procmon are not relates with the attack. | E11: We are the presenter | F11: Use mitre framework. try many attack technique which is good. Maybe you can explain why it's failed for some attack. | G11: Use many technique and structured. Clear explainable. They compare trickbot real attack flow with simulation process | H11: Use mitre frame work. Use some structures attack technique. | I11: They use mitre framework. Use some variants of attack technique. Success to capture kernel level log in process monitoring | J11: They use volt typhoon. Every tactic has high behavioural malware | K11: 89
A12: 46148.497 | B12: Puspa Ira Dewi Candra Wulan | C12: D11415807 | D12: 4 detection points process monitoring, registry monitoring, file system analyst and network analyst. succes maped fully attack lifecycle using caldera and validated via system level logs. tactics demonstated common in APT campaigns. for mitigation implement EDR rules to flag suspicious powershell commands and registry modification and for prevention restrict powershell execution policies andenforce the principle of least privilege. | E12: Our Team | F12: this group have a result high severity low visibiliy and for defense GAP windows defender had to be off, real defences needs behaviour monitoring not just signatures. they say that they success with minimum effort | G12: they using simulated attack process and Trickbot real attack flow . | H12: voidstealer was a malware more complex than they have, they wait for the reboot chrome to sniff in ram , reads it out and uses that key to decrypt and steal saved password, cookies and other browser secret | I12: This group highlighted several important cybersecurity lessons learned from attack simulations and analysis. They emphasized that human factors remain one of the biggest security weaknesses, as a single spearphishing email can bypass technical defenses if a user clicks a malicious attachment. The presentation also showed that unmanaged built in system tools can be abused by attackers to hide malicious activities, while stored credentials create critical risks that may allow privilege escalation and impersonation. In addition, simple persistence techniques such as scheduled tasks can help malware survive reboots, and data exfiltration can be hidden within normal encrypted network traffic, making detection more difficult. Overall, the group concluded that effective cybersecurity requires not only strong technical controls but also user awareness, credential protection, and continuous monitoring. | J12: Discussed lessons learned from analyzing a Living-off-the-Land (LotL) adversary, specifically Volt Typhoon style attacks. The group showed that attackers can abuse legitimate built-in system tools without using custom malware, making malicious activities harder to detect. They also emphasized the importance of behavioral monitoring, anomaly detection, and secure logging systems to identify activities such as credential access, registry hijacking, and log clearing. Overall, the presentation highlighted how modern attackers can blend into normal system operations and why continuous monitoring is essential for protecting critical infrastructure | K12: 90
A13: 46148.497 | B13: 葉人瑋 | C13: M11407437 | D13: Steal computer information ,all abilitys they used are example in caldera? | E13: Indtroduce " what is red team attack and how to observe" they use over half of ppt to present this part . 👌 | F13: They provide a attack process like how to get lsass memory dump and how to extract to remote attack host and 7 ways to dump lsass information which is "GPT+" mentioned last week(but only have 1 is work which method is same as "GPT+". AND THEY ANALYSED system log very precisely.Data shows The dump part may discovered by detector! | G13: They introduce trick bot ,they fetch a file from github but that has some hardness code rename it and show how to steal victim machine's credentials or something . | H13: Steal firefox cookie and decrypt the cookie. | I13: they show a method to performance a exfiltration . | J13: We collect a lot of computer info and credential from victim computer | K13: 89
A14: 46148.497 | B14: Benjamin Gillard | C14: E11415026 | D14: They have done a malware to steal login and password store locally on the target and send them to C2 after compressing the data | E14: They begin by presenting what is Red Team After they have made a malware to steal file on the victim computer to do that they scan the desktop to find the file, they use the outlook home page to achieve persistence. | F14: they create a malware creating a new user and then do the stealing of data login, password, history. then they use curl to exfiltrate the data by the C2 server. The rest of the presentation is presenting the analysis of procmon report. | G14: they have done malware that use privilege escalation to steal generated credential data. they use defense evasion. They achieve persistence thanks to the windows task scheduler. | H14: we have done a malware to steal credential and cookies of firefox. | I14: They have made a malware to steal credentials and achieve persistence. | J14: They have done a malware to steal browser credential. | K14: 89
A15: 46148.497 | B15: Aurelio Naufal Effendy | C15: M11415802 | D15: Simulate a windows system attack using mandiant attack and MITRE framework. Including 4 steps: Initial and foothold, internal reconnaissance, maintain presence and complete mission. The main goal is local file collection. First phase is for initial attack with the sandcat, the attacker then collects the os version, ip address, and the active network connection in the second phase. Third phase seeks for credential. Keep persistence in the phase 4 (with evidence from Procmon in regvalue). Lastly phase 5, where it succesfully get/collect the file and exfiltrate it in the phase 6, transfer the file over c2 channel. The detection points are: anomalous lineage, persistence hooks in the monitoring, data staging patterns, and network/c2 context. | E15: Our group | F15: Simulate attack by caldera. 6 MITRE ATT&CK tactics: 1. Initial Access (spearphising attachment) 2. Execution (command and scripting interpreter: visual basic) 3. Persistence (create local account) 4. Credential access (7 types of LSASS memory dumping : .NET, Nanodump, coomsvcs.dll, silent process exit out-minidump.ps1, direct system calls and API, imported microsoft.dll ) 5. Discovery (edge browsing history and windows firewall rules) 6. Exfiltration (over asymmetric encrypted non-c2 protocol, native binary execution, encrypted transmission and external destination with public file sharing service) The attack is not 100% successful, based on system analysis through procmon, we can detect some of the attack especially through the dumpfiles. The attack was success with minimal effort, with high severity but low visibility, but the windows defender had to be off to achieve the success. | G15: The attack focuses on TrickBot (CISA advisory AA21-076A), a trojan known for credential theft, lateral movement and defense evasion, with MITRE ATT&CK framework. So the attack process is following/similar to the Trickbot: 1. Execution (invoke webrequest, download malicious file) 2. Privilege Escalation (process hollowing, CreateProcessW with CREATE_SUSPENDED) 3. Defense Evasion (modify registry) 4. Persistence (scheduled task to establish a continuous foothold) 5. Discovery (collect system information, systeminfo32) 6. Collection/Credential Access (credential API hooking, create injectDll32 targeting web browser) 7. Exfiltration (send data collected over C2 channel) Through procmon, they can monitor the attack. There is some possible mitigations for this attack like do not open attachments from suspicious email, disable macros, avoid using administrator account. | H15: Adversary emulation with cookie theft attack simulation using caldera. The goal are stealing the cookies of firefox: authentication tokens to gain access to the victim's accounts and bypass 2FA. The stages are: 1. System information discovery 2. Registry persistence via autorun 3. Create staging directory, for data to be collected 4. Stealing cookies using powershell script that target the firefox directories 5. Archive via utility, the directory is compressed using compress-archive command 6. Exfiltration over C2, the file is sent to the attackers C2 server 7. Clear powershell command history, to wipe/clean the activity trace All stages are successful, they successfully capture the browser cookies. Procmon also recognize the attack. In conclusion keep safe and dont open any attachment from unknown sources, disable antivirus or save passwords directly in the web browser (use a dedicated password manager instead) | I15: Caldera adversary profile: 1. Initial access, create a marker file to simulate attachment execution 2. Execution, run powershell discovery commands and write output to lab files 3. Persistence, create a benign scheduled task 4. Credential access, read a dummy credential file 5. Exfiltration, post the dummy data collected to a local http receiver on the caldera VM All stages are successfully executed. prcomon captured 3 event classes: file system, registry and network, all the stages can be monitored through the procmon. The core lesson learned are human factor is also important, credentials are a risk, built-in tools are dangerous if unmanaged, persistence is effective and exfiltration can hide in traffic. | J15: Simulating volt typhoon with caldera, the reason they choose this is because its forces to detect technique. Consist of several phases: 1. Initial foothold and execution: using powershell command 2. Internal reconaissance: get system info 3. Privilege escalation using UAC bypass via fodhelper registry hijacking 4. Defense evasion using five chained abilities disable defender, masquarade, etc 5. Persistence and Command and control: drop web shell and create port proxy via netsh then use C2 traffic 6.Credential access using comsvcs.dll minidump 7. Collection and exfil staging: create staging directory and compress to collected files/credential Not all of the ability are successful. Procmon notices the attack (via splunk.exe, etc), the volt typhoon is reproducible inside a 19-minute caldera run with no custom malware, almost every tactic has a high-fidelity behavioral detection. | K15: 95
A16: 46148.498 | B16: 許詠翔 | C16: M11407502 | D16: N/A | E16: Did an excellent job detailing the tool's background, workflow, and attack techniques. The experiment involved six stages, and while Collection and Exfiltration didn't succeed, the group provided a evaluation of the failure scenarios and their potential causes. | F16: Structured from simulation to conclusion, this presentation offers a clear guide on attack techniques (e.g., T1003.001) and their execution. A notable strength is the group's transparent approach to the experiment; they provided detailed system analysis for the stages. | G16: The project utilizes Caldera to simulate a Trickbot-inspired attack chain and evaluates it against real-world attack patterns. It provides a step-by-step breakdown of goals and techniques for every stage, followed by an in-depth analysis of system logs to verify the attack's impact. Furthermore, it outlines key mitigation strategies to defend against such threats. | H16: The objective is to execute cookie theft and session hijacking. The report outlines the full attack flow and the specific techniques used at every stage. It concludes with a Procmon log analysis to identify and hunt for indicators of compromise (IOCs). | I16: The project simulates a comprehensive five-stage attack lifecycle, successfully achieving Initial Access, Execution, Persistence, Credential Access, and Exfiltration. It provides a detailed breakdown of the TTPs used and evaluates captured system logs. These logs successfully recorded critical event data, including evidence of the initial breach, persistence mechanisms, and the final exfiltration. | J16: By leveraging Caldera, the report replicated the Volt Typhoon attack chain, covering 31 steps and 9 tactics. The report provides a comprehensive breakdown of the 7-phase lifecycle, including goals, command execution, and host-level artifacts. It concludes with an analysis of log hunting techniques, defensive mitigations gained from the experiment. | K16: 92
A17: 46148.498 | B17: 陳增勇 | C17: B11007106 | D17: The group concluded an attack with varying degrees of success | E17: Our group presentation. | F17: The group did an attack using phishing, and the attack sucessfully bypass all phases, from the intial acess to ex filtration. However, it is worth mentioning that the group manages to do this because winder defender was off. | G17: Trickbot is the name of their system. They mainly uses office apps (word) and phishing link attempt. In the end, the group managed to reach their goal and they advise to be more cautious in clicking suspicious links as well as unauthorized office macros. | H17: Cookies is the main target of the attack. In short, they explained cookies allows attackers to bypass 2FA. They specify that they extract the cookies from firefox. They also did a procmon analysis on the attack. To conclude, they advise to not open any attachments, disable antiviruses, nor saving passwords directly on your browser. | I17: The main theme of the system is to steal data from the victim . To conclude, the attack are all successful. The team also adds the exfiltration proof where they include a screenshot of a local reciever where they managed to transfer over 200 files. Procmon capture events from powershell, schtasks, and splunkd, in the end they explain in detail on the prevention tactics of every stage. | J17: This groups main inspurstion is volt thunder. They did an attack that lasted 19 minutes. To conclude, they did put a lot of attack abilities with some that were successful and some that are not. In conclsuion, they did a pretty good job in conveying their system. | K17: 92
A18: 46148.498 | B18: Oriiana Nedzelska | C18: F11415026 | D18: This presentation focused on simulating a realistic post-compromise attack on a Windows 10 virtual machine using the CALDERA adversary emulation platform and Procmon for system monitoring. The group demonstrated specific techniques such as establishing a command-and-control connection through the Sandcat agent, performing internal reconnaissance with commands like systeminfo, ipconfig, and netstat, searching for stored browser credential artifacts, creating persistence through Windows Registry Run keys, and staging sensitive files into compresed archives for simulated exfiltration. They also correlated each action with Procmon evidence, including process creation, registry modification, file access, and archive creation events, to show how these attacker activities can be detected and analyzed in real environments | E18: The group demonstrated the full workflow, including deploying agents, creating abilities based on MITRE ATT&CK techniques, building adversary profiles, and running attack operations involving execution, persistence, discovery, comand and control, and exfiltration. What made the presentation interesting was the use of real CALDERA and Procmon screenshots to show system activity and attack behavior in practice, making the simulation feel realistic | F18: This presentation demonstrated a full cyberattack simulation using MITRE CALDERA and the MITRE ATT&CK framework against a Windows 10 virtual machine. The group explained each attack phase, including phishing-based initial access, PowerShell execution, credential dumping through LSASS memory extraction, discovery of browser and firewall information, and encrypted data exfiltration using HTTPS. They also analyzed system logs and Procmon data to identify suspicious behavior, showing which attack techniques succeeded or failed during the simulation. The presentation was highly technical, well-structured, and effectively connected attack execution with system analysis and cybersecurity defense concepts. The presentation included graphs (a hystogram), which made it more interesting | G18: This presentation demonstrates a safe emulation of TrickBot using MITRE Caldera and the MITRE ATT&CK framework. The project simulates multiple ATT&CK techniques, including user execution, process hollowing, modify registry, scheduled tasks, system information discovery, credential API hooking, and exfiltration over C2 channel, while replacing malicious actions with safe markers and controlled scripts. Using Procmon analysis and system logs, the presentation shows how TrickBot-like behavior can be safely studied for detection, analysis, and defensive cybersecurity training. | H18: This is my group | I18: This presentation showed a realistic but safe cyberattack simulation using MITRE Caldera and Procmon to demonstrate different ATT&CK techniques, including spearphishing, PowerShell execution, scheduled task persistence, credential access, and exfiltration over a C2 channel. I found it interesting how the presenters used Procmon to track system, registry, and network activity in real time, showing how attackers can abuse built-in Windows tools to avoid detection. The presentation also clearly explained detection methods and mitigations such as PowerShell logging, EDR monitoring, MFA, and email security. | J18: Group GPT+ gave a solid presentation on their red team exercise where they simulated the Volt Typhoon actor, specifically looking at how this PRC-linked group uses "living-off-the-land" techniques to stay hidden in critical infrastructure for months or even years. They walked us through a full seven-phase attack campaign using MITRE Caldera, starting from an initial PowerShell foothold and moving all the way through privilege escalation via registry hijacking and credential harvesting from the LSASS process. It was nice to see the actual commands they ran, like using 7-Zip for password-protected exfiltration, and then seeing the corresponding telemetry they caught in Procmon. Even though they had a couple of failed steps during internal recon because the target wasn't on a domain, they still managed to execute 31 total steps in just 19 minutes, proving how hard it is to detect these behavior-based attacks compared to just looking for traditional malware signatures. | K18: 92
A19: 46148.498 | B19: 柯議翔 | C19: M11407319 | D19: This project simulated a complete Windows attack chain—from initial breach to exfiltration—using MITRE Caldera and the ATT&CK framework. By leveraging Procmon, we successfully validated adversarial behaviors against low-level system logs. The study concludes with actionable detection rules and mitigation strategies derived from our experimental analysis. | E19: This group demonstrated a cyber attack simulation using MITRE CALDERA based on the MITRE ATT&CK framework, specifically focusing on WMI (T1047) and Signed Binary Proxy Execution techniques. While they successfully executed the Execution, Discovery, Persistence, and C2 stages, the simulation failed during the Collection and Exfiltration phases. | F19: This group simulated "European Avalanche," focusing on multiple LSASS credential dumping techniques. By analyzing large-scale logs, they concluded that behavioral monitoring is essential over signature-based defense。 | G19: Group ANTSLAB emulated the TrickBot malware, mapping its real-world flow (e.g., process hollowing, credential capture) to Caldera simulation steps. The report covers the entire chain from execution (T1204.002) to persistence via Windows Task Scheduler (T1053.005). It concludes with practical mitigations like disabling macros and limiting admin privileges, providing a comprehensive view of both attack emulation and defensive strategies. | H19: This group demonstrated using SQLite to extract browser cookies, including NTUST SSO tokens. Using VoidStealer as a case study, they explained memory-based decryption risks and warned against saving passwords in browsers or disabling EDR. | I19: "CyberSix" emphasized the necessity of kernel-level monitoring (Procmon) to detect stealthy "Living off the Land" (LotL) process anomalies, such as splunkd.exe spawning powershell.exe, which standard logs often miss. They demonstrated converting attack artifacts and scheduled tasks into actionable SOC intelligence for real-world defense. | J19: This group reproduced "Volt Typhoon" in 19 minutes using only native tools (LotL). Key findings highlight high-fidelity detection for LSASS and process anomalies, proving that secure logging exposes adversarial activities。 | K19: 90
A20: 46148.499 | B20: ZHENG Lise | C20: F11402009 | D20: N/A | E20: demonstrates a realistic cyber attack simulation across multiple stage : execution, discovery, persistence, command and control, collection, exfiltration | F20: their simulation lasted 9 min, with frequent access to lass-comsvcs.dmp, access to sensitive dll files, the simulation was successful | G20: simulate a complete kill chain across 8 distincts tactics, the goal is to simulate the download of the trickbot loader | H20: uses SQLite to extract browser cookies, including NTUST SSO tokens, uses VoidStealer as a case study, explained memory-based decryption risks and warned against saving passwords in browsers or disabling EDR | I20: demonstrate a realistic phase-by-phase adversary chain without collecting real credentials or attacking external systems | J20: Volt Typhoon's playbook is reproducible inside a 19-minute Caldera run with no custom malware, almost every tactic they used has a high-fidelity behavioral detection | K20: 90
... A36: 46148.98 | B36: Dennison Soedibjo | C36: F11415018 | D36: This presentation simulates a post-compromise attack on a Windows 10 VM using CALDERA, mapped to the Mandiant Attack Lifecycle and MITRE ATT&CK. The attack progresses through initial access (Sandcat agent), reconnaissance, persistence via Registry Run keys (CalderaLabUpdater), and data exfiltration over C2. A key finding is that Procmon captures detailed system events (e.g., Process Create, RegSetValue) that standard logs miss. The conclusion highlights detection strategies such as monitoring suspicious process chains, registry persistence, and bulk file staging activity. | E36: This presentation showcases a cyber attack simulation using MITRE ATT&CK and CALDERA, featuring an adversary profile called “Insect.” The simulation successfully executed Execution, Discovery, Persistence, and Command & Control stages using techniques like WMI and web-based exfiltration scripts. However, it failed to complete the Collection and Exfiltration phases, revealing gaps in the attack chain. | F36: This presentation simulates a cyber attack using CALDERA, covering six MITRE ATT&CK phases from spearphishing to data exfiltration. Persistence via local account creation failed due to limited privileges, but credential dumping succeeded using comsvcs.dll, generating over 2,400 LSASS-related events. Data was exfiltrated via curl over HTTPS to evade detection. The key takeaway is that behavior-based monitoring is essential, as signature-based defenses alone are insufficient. | G36: This presentation demonstrates a safe simulation of an eight-step TrickBot attack chain using harmless substitutes for malicious actions. It mimics persistence, data collection, and exfiltration without real compromise by using dummy files and controlled endpoints. The key insight is that organizations can test detection capabilities against advanced threats without risking actual damage. | H36: This presentation simulates a cookie theft and session hijacking attack using CALDERA. It begins with a phishing email and establishes a covert C2 connection disguised as a system process. The attack extracts Firefox session cookies to bypass authentication and 2FA. Key defenses include avoiding suspicious attachments, maintaining EDR protection, and using password managers instead of browser storage. | I36: - | J36: This presentation covers a 19-minute CALDERA simulation of Volt Typhoon’s “Living-off-the-Land” tactics. The attack executed 31 steps across 9 MITRE techniques, including UAC bypass, Defender disabling, data masquerading, and LSASS dumping. The conclusion emphasizes that while such attacks are easy to replicate, they leave detectable behavioral traces, making strong logging, hardened configurations, and targeted mitigations essential. | K36: 91

Sheet W12 paper end
A1: 時間戳記 | B1: Name | C1: Student ID | D1: What is a provenance graph? How is the provenance graph constructed in this paper? Please explain based on Section V.B and Table I. | E1: Why does the paper use causal path selection? What is the main rationale or purpose behind selecting causal paths? | F1: What embedding function is used in the paper? Please explain: * how the embedding function works, and * the intuition behind using this embedding method. | G1: How does the system determine whether a scenario is malicious or benign? | H1: Based on Section 2, what are the main challenges and limitations of existing approaches for binary analysis or instruction representation? | I1: The paper introduces three training tasks to build the assembly language model. Please explain: * what each training task is, and * why each task is important for learning instruction embeddings. | J1: Based on Section 3.4.6, what are the two ways to deploy PalmTree: Learning an Assembly Language Model for Instruction Embedding for downstream applications? | K1: What is the main intuition behind PalmTree’s instruction embedding model? Why is a language-model-based approach useful for assembly instructions? | L1: 第 1 欄
A2: 46155.476 | B2: Su Yadana Win | C2: D11415809 | D2: A system provenance graph (also called a dependency graph) for a process p is a representation of the system entities and events that have data or control dependencies on that process It is formally defined as a labeled temporal graph G(p)=<V,E>, where: V (Vertices): Represent system entities such as processes, files, and network sockets E (Edges): Represent system events or interactions between these entities Construction (based on Section V.B and Table I): ProvDetector builds the graph as a labeled temporal graph using data from a centralized database The construction follows these parameters: Starting Point: The process begins with a specific process instance v=p Iterative Addition: The system adds any edge e and its corresponding source (src) and destination (dst) nodes to the graph if either the source or destination is already a member of the vertex set V (e.src∈V or e.dst∈V) Entities and Attributes (Table I): Processes: Identified by attributes like executable path, PID, and host name Files: Identified by file path and host name Sockets: Identified by source/destination IP and port Relations (Table I): Edges are labeled based on the relationship between entities, such as Start/End (between processes), Read/Write/Execute (process to file), and Read/Write (process to socket) Each edge also includes a timestamp to maintain temporal order | E2: Rationale and Purpose: ProvDetector uses causal path selection—specifically identifying the top K most uncommon paths—to address several challenges: Isolating Malicious Behavior: Stealthy malware is designed to blend in with benign processes, meaning the majority of a provenance graph remains benign even during an attack Modeling the whole graph is ineffective because malicious signals are diluted Causal paths allow the system to isolate and focus specifically on the malicious fragments of activity Addressing Dependency Explosion: Provenance graphs can contain thousands of nodes, and the number of possible paths grows exponentially with the number of nodes It is computationally impossible to traverse and analyze every path; selecting a subset makes the system scalable Identifying Rare Workloads: The authors argue that "universal workloads" (like loading standard DLLs) are common across all instances and likely benign, while malicious activities are "instance-specific" and rare By selecting paths based on rareness, the system focuses on the parts of the graph most likely to contain anomalies Efficiency: Selecting only a subset of paths significantly reduces the data processing pressure during both the training and detection stages | F2: Embedding Function Used: The paper utilizes the PV-DM (Distributed Memory Model of Paragraph Vectors) model, which is a version of doc2vec How it Works: Path Translation: A causal path is first translated into a "sentence" where nodes are treated as words For example, a process writing to a file would be represented as: Process:[name] write File:[path] Vector Mapping: Every path (paragraph) is mapped to a unique paragraph vector, and every node/edge (word) is mapped to a word vector Training: The model uses a sliding window over the path. The paragraph vector and word vectors are averaged or concatenated to predict the next "word" in the sequence Through stochastic gradient descent, the model learns numerical vectors that represent the features of the paths Projection: This projects paths into an n-dimensional numerical vector space where similar behaviors are geographically closer Intuition: The intuition is that nodes and edges compose paths in the same way words compose sentences to describe behavior By treating paths as documents, ProvDetector can: Apply distance-based novelty detection Learn the "encoder" using purely benign data (self-supervised) Preserve temporal order, which is critical for security (e.g., a "command line starting Word" is benign, but "Word starting a command line" is suspicious) | G2: The system determines the status of a scenario through a two-step process: Path-Level Novelty Detection: ProvDetector applies the Local Outlier Factor (LOF) algorithm to the embedding vectors of the K selected paths LOF is a density-based method that identifies an outlier if its local density is significantly lower than that of its neighbors in the embedding space It is used because program behaviors are complex and do not follow a single mathematical distribution, often forming multiple distinct clusters for different types of normal workloads Graph-Level Final Decision: To make the final determination for a process instance, the system uses a threshold-based method If more than t (a predefined threshold) embedding vectors from a single provenance graph are predicted as malicious, the entire process is flagged as malicious This approach also allows for "early stopping" to reduce overhead if the first few paths selected are already identified as malicious | H2: Main Challenges and Limitations of Existing Approaches According to Section 2 of the paper, existing approaches for instruction representation face several significant challenges: Complex and Diverse Instruction Formats: Instructions, particularly in CISC architectures like x86, have highly varied internal structures Operands can range from zero to three and can include registers, memory expressions, or immediate constants Many existing models ignore these internal details by treating an entire instruction as a single "word" or by only supporting simplified formats Noisy Instruction Context: Existing methods often rely on Control Flow Graphs (CFGs) to capture contextual information However, compiler optimizations (such as instruction scheduling) frequently reorder instructions to maximize parallelism This reordering means that adjacent instructions in the control flow might be semantically unrelated, making the contextual information "noisy" Neglect of Data Flow Dependency: Most current models focus solely on control flow and fail to account for data flow dependencies (def-use relations) between instructions Unlike control flow, these data dependencies are clearly specified in instruction semantics and are not tampered with by compiler optimizations Rigid Encoding Schemes: Approaches like raw-byte encoding or manually-designed features are either too rigid to convey high-level semantic information or require tedious, error-prone expert effort | I2: PalmTree utilizes three self-supervised pre-training tasks to capture the characteristics of assembly language: Masked Language Model (MLM): What it is: This task involves randomly masking or corrupting 15% of the tokens within an instruction (which is treated as a sentence) and training the model to predict the original tokens Importance: It is crucial for training the model to understand the internal structures and formats of instructions by learning the relationships between opcodes and various types of operands Context Window Prediction (CWP): What it is: This is a binary classification task where the model predicts whether two given instructions co-occur within a specific sliding window in the control flow Importance: It captures contextual control flow dependency By using a sliding window rather than requiring instructions to be strictly adjacent, it accounts for the fact that compilers may have reordered the instructions Def-Use Prediction (DUP): What it is: The model is trained to predict whether two instructions have a "def-use" (data dependency) relation, meaning one instruction defines a value that the other uses Importance: This task captures data flow dependency, which provides a more stable semantic link between instructions than control flow, as it is unaffected by compiler optimizations | J2: Deployment Methods for Downstream Applications Section 3.4.6 identifies two ways to deploy PalmTree for downstream tasks: Instruction Embedding Generation: In this mode, the pre-trained parameters of PalmTree are frozen, and it is used as an off-the-shelf model to generate embeddings This is particularly useful for resource-constrained environments, where a static embedding lookup table can be pre-generated for common instructions to save computation time Fine-tuning: In this mode, the pre-trained parameters are further adjusted while training PalmTree together with the specific downstream model This typically provides extra performance benefits if sufficient computing resources and training data are available | K2: The main intuition behind PalmTree is that assembly language possesses "naturalness" similar to natural languages and programming languages Consequently, an instruction can be viewed as a "sentence" and its components (opcodes, registers, constants) as "words" A language-model-based approach (specifically one based on BERT) is useful for assembly instructions because: Automatic Feature Learning: It avoids the need for manual feature engineering, which requires significant expert knowledge and is often error-prone High-Level Semantics: It can learn higher-level semantic features rather than just pure syntactic features, enabling better performance on complex tasks like value set analysis or code similarity detection Self-Supervision: It allows the model to be trained on large-scale unlabeled binary corpora, leveraging massive amounts of raw data to capture complex dependencies that traditional methods might miss Contextual Awareness: Unlike simpler models like word2vec, the bidirectional transformer architecture allows the model to capture the meaning of instructions based on their full context within a program | L2: 94
A3: 46155.476 | B3: Peter Jonathan Kuhn | C3: e11415021 | D3: (i aswerde the questions based on the paper and not the presentionion. i dont understand what your definition of a discussion is) the graph shows the child parent relationsships of the processes. they are constrcted by only focusing on interesting graphs. | E3: this is a way to select the interesting paths. paths that are normal and boaring will have a short distance and the interesting ones have a long path that is seleceted for the next steps. the bulk of malicious paths is benigne, and not maliciois at all. with the selecion the data explosion can be avoided | F3: the embeding (doc2vec) maps the graphs into a high dimensional vector space. they use it to as it preserves the information contained in a graph. they think that the graphs behaves similar then natural linguage | G3: it is trained only on benign data. then it looks if the sample to determin is an outlier to all the known data. if many of the windows are flaged as outliers, then the whole process is flaged as malware | H3: my own presi | I3: my own presi | J3: my own presi | K3: my own presi | L3: 89
A4: 46155.478 | B4: 蔡哲維 | C4: M11407524 | D4: In this paper, a provenance graph is a structured representation of a process’s behavior that captures all relevant system interactions and dependencies between the process and other system entities over time. | E4: The paper selects causal paths to isolate rare malicious behaviors hidden inside mostly benign process activity, allowing PROVDETECTOR to focus on suspicious deviations while improving detection accuracy and scalability. | F4: The paper uses the PV-DM (Distributed Memory Paragraph Vector) model of Doc2Vec as its embedding function. It converts each selected causal path into a sentence-like sequence where system entities (processes, files, sockets) and relations are treated like words, then learns a numerical vector representation for each path based on contextual similarity. The intuition is that causal paths resemble natural language sentences: nodes act like nouns, edges like verbs, and together they describe process behavior. This allows similar behavioral paths to be embedded close together in vector space while anomalous malicious paths appear distinct, enabling effective machine learning-based anomaly detection. | G4: PROVDETECTOR determines whether a scenario is malicious or benign by first embedding the selected causal paths from a process’s provenance graph into vectors, then using a Local Outlier Factor (LOF) anomaly detection model trained only on benign data to identify abnormal paths. If the number of paths predicted as anomalous exceeds a predefined threshold, the entire process instance is classified as malicious; otherwise, it is considered benign. | H4: Existing binary analysis methods rely heavily on manual feature engineering or shallow embeddings, which struggle to capture the rich syntax, semantics, and contextual dependencies of assembly instructions. They often fail to generalize across architectures and tasks, limiting their effectiveness in complex binary analysis scenarios. | I4: PalmTree uses three training tasks: Masked Language Modeling (MLM), which masks parts of instructions so the model learns instruction syntax and semantics; Context Window Prediction (CWP), which predicts neighboring instructions to capture control-flow context; and Def-Use Prediction (DUP), which learns relationships between variable definitions and uses to model data-flow dependencies. Together, these tasks help PalmTree generate embeddings that understand syntax, execution context, and program behavior. | J4: Section 3.4.6 describes two deployment methods for PalmTree in downstream applications: feature-based deployment, where PalmTree generates pretrained instruction embeddings used as input features for task-specific models, and fine-tuning deployment, where the entire pretrained PalmTree model is further trained on a specific downstream task to optimize performance. | K4: PalmTree’s core intuition is that assembly instructions can be treated like natural language, where each instruction has syntax, semantics, and contextual relationships. By using a language-model-based approach, PalmTree learns deeper semantic and structural patterns automatically, enabling richer instruction representations than manual or shallow methods. | L4: 90
A5: 46155.483 | B5: Lucas Metzger | C5: F11415020 | D5: It is defined as PG = (V, E), where the node set V represents all system entities and the edge set E represents all system events. Each edge e = (u, v, a) denotes that system entity u (called subject) performs operation a on system entitiy v. It finds hidden malware by looking for unusual paths of activity in computer records | E5: points to actions based on how rare they are and picks the paths with the most points. | F5: PV-DM (Distributed Memory Model of Paragraph Vectors) model, which is a version of the doc2vec framework. It uses a computer model to turn a list of actions into a list of numbers | G5: Density-Based Anomaly Detection & Threshold-Based Decision. A whole program is marked as bad if the system finds just one abnormal path in its behavior | H5: My group | I5: My group | J5: My group | K5: My group | L5: 88
A6: 46155.493 | B6: Ayman Kallouz | C6: E11415023 | D6: A provenance graph is defined as PG = (V,E) where node set V represents all system entitites and the edge set E represents all system events. Based on Section V.B and Table I, the graph is built as a labeled temporal graph using data from a database. It is made up of nodes and edges. The nodes represent three types of system entities which are processes, files, and sockets. Each node carries specific identifying details, such as a process ID, an IP address, or a file path. The edges connect them by acting as a record of system events. Every edge tracks the source, the destination, the exact action that happened, and the time it occurred. | E6: The paper uses causal path selection primarily to deal with the overwhelming size of these graphs, since analyzing every single possible path would be too slow and take too much computing power. The main thought behind this approach is that stealthy malware tries to hide its actions within the normal behavior of a hijacked program. By filtering out the common background noise and only selecting the rarest causal paths, the system can successfully isolate the malicious activity. This focused selection makes it much easier to spot the attacks while also speeding up both the training and detection processes. | F6: The paper uses a function called doc2vec, specifically the PV-DM version, as its embedding function. The system makes this work by treating each causal path like a written sentence. It translates the nodes into nouns and the connecting edges into verbs. From there, a neural network uses those word vectors with a paragraph vector to predict the next word in the sequence. The main intuition behind this approach is that a path essentially tells us about how a program behaves and by converting these paths into numbers and placing them in a vector space, similar behaviors naturally show being closer together. This layout makes anomalies stand out easily, since a malicious path will naturally sit far outside the normal clusters. | G6: To figure out if a scenario is malicious, the system uses an algorithm called Local Outlier Factor to check the density of the data. If a causal path extracted from the provenance graph lands in a weird, isolated spot compared to its neighbors, it gets flagged as an outlier. After checking the paths, it just uses a threshold: if enough of the paths within that specific provenance graph are flagged, the system officially labels the entire process as a malicious attack. | H6: / I am in this group | I6: / I am in this group | J6: / I am in this group | K6: / I am in this group | L6: 89
A7: 46155.493 | B7: 祖祥恩 | C7: M11307310 | D7: A provenance graph G(p) = <V, E> is a labeled, directed temporal graph where nodes (V) represent system entities (processes, files, sockets) and edges (E) represent system events (e = {src, dst, rel, time}) capturing data and control dependencies of a process. Starting from the target process p, PROVDETECTOR iteratively adds any edge e and its endpoint nodes from the database if either endpoint already exists in V, using the three entity types and their relations defined in Table I (e.g., Process→File: read/write/execute; Process→Process: start/end; Process→Socket: read/write). | E7: Because stealthy malware blends its malicious activities with normal ones, using the entire provenance graph as a feature is ineffective — the malicious portion is only a small fraction of the graph. Therefore, the paper selects causal paths to isolate the rare, instance-specific behaviors most likely to be malicious, while filtering out common universal workloads shared across all benign instances. | F7: Embedding function: PV-DM (doc2vec) Each causal path is translated into a "sentence" where nodes are "nouns" and edges are "verbs" (e.g., winword.exe → write → cmd.exe), then PV-DM embeds the whole path into a 100-dimensional vector by learning to predict next tokens from a sliding window context. Intuition: A causal path behaves like a sentence describing program behavior — so document embedding naturally captures semantic similarity between paths, preserves event order (e.g., winword→cmd vs. cmd→winword), and requires only benign data to train. | G7: After embedding each causal path into a vector, PROVDETECTOR uses Local Outlier Factor (LOF) to detect anomalies — a path is flagged as malicious if its local density is significantly lower than its neighbors (i.e., it's an outlier in the embedding space). The final decision uses a threshold t: if more than t paths from a process's provenance graph are predicted malicious, the entire process is considered hijacked. | H7: Existing approaches fail in three ways: they treat instructions as opaque tokens ignoring complex internal formats, rely on noisy CFG-based context disrupted by compiler optimizations, and completely ignore long-range data flow dependencies between instructions. | I7: MLM: Masks random tokens within an instruction and trains the model to predict them, forcing it to learn the complex internal structure of instructions (opcodes, operands, registers, etc.). CWP: Predicts whether two instructions co-occur within a sliding control-flow window, capturing contextual dependencies while tolerating compiler-induced instruction reordering. DUP: Predicts whether a pair of instructions is in the correct def-use order based on the data flow graph, capturing long-range data dependencies that control flow alone cannot express.​​​​​​​​​​​​​​​​ | J7: Instruction embedding generation (frozen): PalmTree’s pre-trained parameters are frozen and used as an off-the-shelf embedding generator, suitable for resource-limited environments and can be further accelerated with a pre-built static lookup table. Fine-tuning: PalmTree’s parameters are further adjusted jointly with the downstream model, offering better performance when sufficient computing resources and training budget are available.​​​​​​​​​​​​​​​​ | K7: The core intuition is that assembly code has “naturalness” similar to natural language — an instruction can be treated as a sentence and its tokens (opcode, registers, operands) as words — so a language model like BERT can learn the semantic relationships between instruction components from large unlabeled binary corpora without manual feature engineering, producing richer, more generalizable embeddings than rigid hand-crafted or raw-byte approaches.​​​​​​​​​​​​​​​​ | L7: 90
A8: 46155.494 | B8: Benjamin Gillard | C8: E11415026 | D8: A provenance graph is a labeled temporal graph representing system entities (processes, files, sockets) and their interactions (e.g., read, write, execute) as nodes and edges. Construction: Nodes: System entities (processes, files, sockets) with attributes. Edges: System events (e.g., Process A -> read -> File B) with timestamps. Built by starting from a target process and recursively adding all entities/events with control/data dependencies to it. | E8: To isolate malicious behavior from benign parts of the provenance graph. Stealthy malware blends into benign processes, but its causal paths reveal deviations. Selecting rare causal paths focuses on instance-specific workloads rather than universal workloads. | F8: Treats a causal path as a "sentence" Nodes/edges are "words". The model learns embeddings for paths in a vector space where similar paths are closer. | G8: Path Selection: Extracts the top-K rarest causal paths (K=20) from the provenance graph using the regularity score | H8: Existing methods ignore complex instruction formats and fail to capture data flow dependencies or instruction reordering by compilers. | I8: MLM: Masks tokens to learn instruction structure. CWP: Predicts if instructions are in the same context window. DUP: Predicts def-use order in data flow graphs. | J8: Embedding generation: Use PalmTree as a feature extractor. Fine-tuning: Adapt PalmTree for specific tasks with labeled data. | K8: Assembly has natural language-like patterns. A BERT-based model captures its syntax and semantics for better embeddings. | L8: 88
